Workbook

Sheet Sales_RAW(BEFORE)
A1: SALES REPORT - system export (DO NOT TOUCH!!!)
A4: transaction id | B4: date | C4: Delivery Date | D4: Product Code | E4: Product Name | F4: category | G4: Quantity | H4: Unit Price | I4: Discount % | J4: Total | K4: Currency | L4: Employee ID | M4: Sales Rep | N4: Region | O4: City | P4: Customer | Q4: Tax ID | R4: CUSTOMER EMAIL | S4: Phone | T4: Address | U4: ZIP Code | V4: country | W4: Payment Method | X4: Status | Y4: Payment Status | Z4: Invoice No. | AA4: Sales Channel | AB4: Quarter | AC4: Month | AD4: Year | AE4: Payment Terms | AF4: Days Overdue | AG4: VAT | AH4: VAT Amount | AI4: Amount incl. VAT | AJ4: Shipping Cost | AK4: Courier | AL4: tracking no. | AM4: WEIGHT (KG) | AN4: Warehouse | AO4: Stock | AP4: Customer Rating | AQ4: COMMENT | AR4: Returned? | AS4: return reason | AT4: Margin | AU4: Rep Commission | AV4: Customer Full Name | AW4: Contact Person | AX4: NOTES
A5: TR-2025001 | B5: 09.09.2025. | C5: 23-Sep-25 | D5: P33 | E5: Printer X 33 | F5: Office | G5: 7 | H5: 129.06 USD | I5: 10% | J5: 903.42 | K5: $ | L5: E016 | M5: chris anderson | N5: East | O5: houston | P5: wayne llc | Q5: EIN: 388875967 | R5: daniel.gmail.com | S5: (536) 760-6300 | T5: 344 Davis Street | U5: 63212 | V5: US | W5: credit card | X5: DELIVERED | Y5: Paid | Z5: INV/2025/0001 | AA5: Online | AB5: 1st quarter | AC5: 9 | AD5: 2025 | AE5: immediate | AG5: 0.08 | AJ5: 15,21 | AK5: DHL | AL5: 1Z806032141 | AM5: 23.5 kg | AN5: wh b | AO5: 76 | AP5: 3 | AR5: 1 | AS5: doesn't fit | AU5: 27.1 | AV5: Daniel Davis | AW5: Daniel Davis | AX5: duplicate?
A6: TR-2025002 | B6: 24.08.2025 | C6: 31-Aug-25 | D6: P-052 | F6: Furniture | G6: 2 | H6: 1467.86 | I6: 0.1 | J6: - | K6: usd | L6: e-023 | M6: laura anderson | N6: North | O6: New Yrok | P6: Wayne inc | Q6: 790161495 | R6: john.company.com | S6: +1 836 781 3186 | T6: 276 Johnson St. | U6: 89566 | V6: U.S. | W6: Cash | X6: Cancelled | Y6: Partial | Z6: INV/2025/0002 | AA6: Phone | AB6: Q1 | AC6: Aug | AD6: 2025 | AE6: Net 60 | AF6: 10 | AG6: 8% | AJ6: 14.48 | AK6: ups | AL6: FX515375252 | AM6: 6,4 | AN6: Warehouse A | AO6: 72 | AP6: 5 | AQ6: late delivery!! | AR6: NO | AS6: doesn't fit | AT6: 15 % | AU6: $88.07 | AV6: John Williams | AW6: same
A7: TR-2025003 | B7: 07-Apr-26 | C7: 13.04.2026 | D7: P-032 | E7: Cable Basic 32 | F7: software | G7: 20 kom. | H7: USD 1,480 | J7: 29595.40 | K7: USD | L7: EMP22 | M7: N/A | N7: South | O7: Huston | P7: Umbrella inc | Q7: 943040526 | R7: emma.company.com | S7: 949.620.8386 | T7: 771 Williams Ave | U7: null | V7: US | W7: credit card | X7: Cancelled | Y7: Partial | Z7: INV/2026/0003 | AA7: Store | AB7: 1st quarter | AC7: April | AD7: 2026 | AE7: Net 60 | AF7: 51 | AG7: 0.08 | AJ7: 24.16 | AK7: Fed Ex | AL7: DH273577842 | AM7: 24,37 | AN7: WH-A | AO7: 231 | AQ7: OK | AR7: NO | AS7: doesn't fit | AT7: 0,18 | AU7: - | AV7: Emma Williams | AW7: same
A8: TR-2025004 | B8: 28.01.2026 | C8: 02/05/2026 | D8: P48 | E8: LICENSE PLUS 48 | F8: software | G8: 34 kom. | H8: $471.22 | I8: 5% | J8: #N/A | K8: USD | L8: E014 | M8: SOPHIA BROWN | N8: west | O8: Huston | P8: initech inc | Q8: EIN: 986261507 | R8: sarah.gmail.com | S8: (240) 201-3058 | T8: 642 Jones Blvd | U8: 92564 | V8: USA | W8: Credit Card | X8: Processing | Y8: YES | Z8: INV/2026/0004 | AA8: online | AB8: q1 | AC8: January | AD8: 2026 | AE8: 15 | AF8: null | AG8: 0.08 | AJ8: $49.82 | AK8: USPS | AL8: 1Z610354022 | AM8: 16.5 kg | AN8: Warehouse B | AO8: #N/A | AP8: excellent | AR8: Yes | AV8: Sarah Davis | AW8: Sarah | AX8: urgent
A9: TR-2025005 | B9: 2026-06-01 | C9: 2026-06-09 | D9: P1 | E9: DESK X 1 | F9: #N/A | G9: 14 | H9: null | I9: 0.1 | K9: usd | L9: E010 | N9: South | O9: NYC | P9: initech inc | Q9: EIN: 134245587 | R9: laura.company.com | S9: +1 373 311 1047 | T9: 431 Johnson St. | U9: 50824 | V9: United States | W9: Wire Transfer | X9: Delivered | Y9: Paid | Z9: INV/2026/0005 | AA9: Phone | AB9: q1 | AC9: June | AD9: '26 | AE9: immediate | AF9: 24 | AG9: 8 | AJ9: USD 2 | AK9: USPS | AL9: FX143647055 | AM9: 11.33 | AN9: Warehouse B | AO9: 99 | AP9: 5/5 | AQ9: late delivery!! | AR9: Yes | AS9: damaged | AT9: 15 % | AU9: - | AV9: Laura Brown | AW9: Laura Brown
A10: TR-2025006 | B10: 20-Apr-25 | C10: 04-May-25 | D10: P-053 | E10: monitor basic 53 | F10: Equipment | G10: 30 kom | H10: 553.22 USD | I10: 10% | J10: N/A | K10: usd | L10: E008 | M10: #N/A | N10: North | O10: Houston | P10: vortex inc | Q10: 862110984 | R10: chris.gmail.com | S10: +1 965 751 2985 | T10: 581 Jones Ave | U10: 34299 | V10: US | W10: Wire Transfer | X10: delivered | Y10: paid | Z10: INV/2025/0006 | AA10: Web | AB10: q1 | AC10: 4 | AD10: 2025 | AE10: 15 | AF10: - | AG10: 0,08 | AJ10: 25,37 | AK10: FedEx | AL10: DH598125683 | AM10: 29.73 | AN10: wh b | AO10: 468 | AP10: 5 | AQ10: all good | AR10: No | AT10: 0,18 | AU10: 497,90 | AV10: Chris Davis | AW10: same | AX10: VIP customer
A11: TR-2025118 | B11: 06/14/2026 | C11: 20-Jun-26 | D11: P_004 | E11: printer plus 4 | F11: null | G11: 7 kom. | H11: 364.79 | I11: 10 | J11: N/A | K11: usd | L11: E015 | M11: Sarah Jones | N11: South | O11: houston | P11: Stark Inc. | Q11: EIN: 986739414 | R11: sophia.gmail.com | S11: 348.471.3029 | T11: 450 Brown St. | U11: 58661 | V11: USA | W11: credit card | X11: delivered | Y11: Paid | Z11: INV/2026/0118 | AA11: Online | AB11: Q3 | AC11: Jun | AD11: 2026 | AE11: 15 | AF11: 34 | AG11: 8% | AJ11: 40.91 | AK11: DHL | AL11: 1Z412227285 | AM11: 22,73 | AN11: Warehouse C | AO11: 56 | AP11: excellent | AR11: NO | AS11: damaged | AT11: 15 % | AU11: USD 77 | AV11: Sophia Johnson | AX11: check price
A12: TR-2025007 | B12: 07.01.2025 | C12: 01/13/2025 | D12: p039 | E12: Cable Plus 39 | F12: SOFTWARE | G12: 39 kom | H12: 601.47 | I12: 5% | J12: USD 23,457 | K12: USD | L12: E009 | M12: OLIVIA WILSON | N12: North | O12: new york | P12: Initech INC | Q12: EIN: 430278432 | R12: emma.gmail.com | S12: 859.401.7401 | T12: 415 Brown Street | U12: 57906 | V12: usa | W12: Credit Card | X12: Delivered | Y12: Partial | Z12: INV/2025/0007 | AA12: online | AB12: 1st quarter | AC12: January | AD12: 2025 | AE12: 15 | AF12: N/A | AG12: 8 | AJ12: 4,45 | AK12: USPS | AL12: DH284346077 | AM12: 4.46 | AN12: Warehouse A | AO12: 196 | AP12: 4 | AQ12: late delivery!! | AR12: NO | AU12: #N/A | AV12: EMMA ANDERSON | AW12: same | AX12: urgent
A13: TR-2025008 | B13: 20-Jul-25 | C13: 2025-07-29 | D13: P-040 | E13: null | F13: Software | G13: 31 kom. | H13: 98,06 | I13: 5% | J13: 3039.86 | K13: USD | L13: EMP13 | M13: Robert Williams | N13: west | O13: Miami | P13: GLOBEX INC. | Q13: EIN: 579768106 | R13: michael.gmail.com | S13: 574.293.8241 | T13: 523 Smith Street | U13: 84419 | V13: United States | W13: PayPal | X13: DELIVERED | Y13: Paid | Z13: INV/2025/0008 | AA13: Online | AB13: Q3 | AC13: July | AD13: '25 | AE13: 15 | AF13: 3 | AG13: 8% | AJ13: USD 10 | AK13: Fed Ex | AL13: DH946518213 | AM13: 25,01 | AN13: Warehouse B | AO13: 81 | AP13: 5 | AQ13: complaint | AR13: yes | AT13: 0.3 | AU13: 91,20 | AV13: Michael Anderson | AW13: same | AX13: check price
A14: TR-2025009 | B14: 23-Jul-25 | C14: 07/26/2025 | D14: P_024 | E14: CHAIR PLUS 24 | F14: Electronics | G14: 26 kom. | H14: 95.7 | I14: 0.1 | J14: USD 2,488 | K14: EUR | L14: e-002 | N14: East | O14: los angeles | P14: Wayne inc | Q14: 812640864 | R14: N/A | S14: (497) 830-8081 | T14: 628 Smith Street | U14: - | V14: United States | W14: Credit Card | X14: DELIVERED | Y14: Unpaid | Z14: INV/2025/0009 | AA14: online | AB14: q1 | AC14: July | AD14: '25 | AE14: Net 60 | AF14: - | AG14: 8 | AJ14: 7.93 | AK14: Fed Ex | AL14: DH260323700 | AM14: 4,43 | AN14: Warehouse B | AO14: 205 | AP14: 1 | AR14: 0 | AS14: doesn't fit | AT14: 0.3 | AU14: 74,65 | AV14: Michael Jones | AW14: same | AX14: urgent
A15: TR-2025010 | B15: 2025-02-15 | C15: null | D15: P-058 | E15: Laptop Pro 58 | F15: Furniture | G15: 35 | H15: $711.00 | I15: 0 | J15: 24885.00 USD | K15: EUR | L15: E001 | M15: #N/A | N15: South | O15: new york | P15: Globex INC | Q15: EIN: 460257622 | R15: john.company.com | S15: (851) 767-8144 | T15: 902 Taylor Street | U15: 23252 | V15: US | W15: PayPal | X15: delivered | Y15: paid | Z15: INV/2025/0010 | AA15: Store | AB15: q1 | AC15: February | AD15: 2025 | AE15: 15 | AF15: 48 | AG15: 8 | AJ15: 23,61 | AK15: FedEx | AL15: FX878058375 | AM15: 26.6 kg | AN15: Warehouse C | AO15: 299 | AP15: 3 | AQ15: all good | AR15: No | AT15: 25% | AU15: 746.55 | AV15: john davis | AW15: John Davis
A16: TR-2025011 | B16: 02/13/2025 | C16: 17.02.2025. | D16: P-009 | E16: Chair Plus 9 | F16: - | G16: 5 kom. | H16: 813.33 | I16: 5% | J16: 4066.65 USD | K16: $ | L16: EMP23 | M16: Laura Anderson | N16: North | O16: seattle | P16: Acme Ltd. | Q16: EIN: 640883830 | R16: emma.yahoo.com | S16: 555.680.1788 | T16: 580 Brown Street | U16: 76306 | V16: US | W16: Wire Transfer | X16: Delivered | Y16: YES | Z16: INV/2025/0011 | AA16: Web | AB16: 1st quarter | AC16: 2 | AD16: 2025 | AE16: Net 60 | AF16: N/A | AG16: 8 | AJ16: 29.63 USD | AK16: DHL | AL16: 1Z404652501 | AM16: 24.48 | AN16: Warehouse A | AO16: 480 | AP16: 2 | AQ16: OK | AR16: 1 | AS16: doesn't fit | AT16: 25% | AU16: 122 | AV16: EMMA SMITH | AW16: Emma Smith | AX16: VIP customer
A17: TR-2025012 | B17: 26.01.2025. | C17: 29-Jan-25 | D17: P-057 | E17: keyboard x 57 | F17: Equipment | G17: 14 | H17: 741.71 USD | I17: 0 | J17: 10383,94 | K17: usd | L17: E021 | M17: #N/A | N17: West | O17: chicago | P17: Umbrella Ltd. | Q17: 987473445 | R17: david.company.com | S17: (453) 940-6350 | T17: 265 Johnson St. | U17: 87232 | V17: usa | W17: credit card | X17: delivered | Y17: Unpaid | Z17: INV/2025/0012 | AA17: Store | AB17: Q2 | AC17: January | AD17: 2025 | AE17: Net 30 | AF17: 81 | AG17: 0.08 | AJ17: USD 10 | AK17: FedEx | AL17: FX949334392 | AM17: 6.8 kg | AN17: wh b | AO17: 11 | AP17: excellent | AR17: 0 | AU17: 311.52 | AV17: David Jones | AW17: same | AX17: urgent
A18: TR-2025013 | B18: 10-Apr-26 | C18: 20260422 | D18: P42 | E18: Desk Max 42 | F18: Electronics | G18: 21 | H18: USD 158 | I18: 10% | J18: N/A | K18: usd | L18: e-004 | M18: #N/A | N18: NORTH | O18: Houston | P18: Umbrella INC | Q18: EIN: 896834466 | R18: david.gmail.com | S18: +1 981 325 6824 | T18: 392 Davis Street | U18: 02744 | V18: usa | W18: PayPal | X18: Pending | Y18: NO | Z18: INV/2026/0013 | AA18: Store | AB18: Q3 | AC18: April | AD18: 2026 | AE18: 15 | AF18: 38 | AG18: 0,08 | AJ18: USD 50 | AK18: Fed Ex | AL18: 1Z933875961 | AM18: 5,88 | AN18: Warehouse C | AO18: 369 | AP18: 3 | AQ18: late delivery!! | AR18: 0 | AS18: wrong item | AU18: $99.58 | AV18: David Johnson | AW18: same | AX18: check price
A19: TR-2025014 | B19: 09/17/2025 | C19: 20250921 | D19: P-046 | E19: - | F19: Equipment | G19: 12 | H19: 549,42 | I19: 0 | K19: usd | L19: E013 | M19: Robert Williams | N19: South | O19: Huston | P19: Vortex inc | Q19: 280294956 | R19: laura.company.com | S19: 743.280.8185 | T19: 904 Johnson Street | U19: 35667 | V19: US | W19: Wire Transfer | X19: Cancelled | Y19: YES | Z19: INV/2025/0014 | AA19: Online | AB19: Q2 | AC19: September | AD19: 2025 | AE19: immediate | AF19: 31 | AG19: 8% | AJ19: $8.02 | AK19: DHL | AL19: FX814361021 | AM19: 12,83 | AN19: Warehouse A | AO19: 92 | AP19: 1 | AT19: 0.3 | AU19: 197.79 USD | AV19: Laura Smith | AW19: Laura Smith | AX19: urgent
A20: TR-2025015 | B20: 10.05.2025. | C20: 2025-05-19 | D20: P46 | E20: Chair Basic 46 | F20: Equipment | G20: 7 kom | H20: 549,42 | I20: 5% | J20: 3845.94 | K20: $ | L20: EMP14 | M20: null | N20: west | O20: Chicago | P20: Initech LLC | Q20: 753571200 | R20: sophia.company.com | S20: 417.240.8501 | T20: 781 Williams Street | U20: 87981 | V20: USA | W20: Wire Transfer | X20: Delivered | Y20: NO | Z20: INV/2025/0015 | AA20: Online | AB20: 1st quarter | AC20: 5 | AD20: 2025 | AE20: Net 60 | AG20: 0.08 | AJ20: 1,02 | AK20: FedEx | AL20: FX709356414 | AM20: 24.8 kg | AN20: Warehouse C | AO20: 356 | AR20: No | AS20: wrong item | AT20: 15 % | AU20: 115,38 | AV20: Sophia Miller | AW20: Sophia Miller | AX20: VIP customer
A21: TR-2025016 | B21: 2025-01-16 | C21: 30.01.2025 | D21: P-014 | E21: license max 14 | F21: Software | G21: 1 | H21: 1166.96 | I21: 0.1 | J21: 1166.96 | K21: USD | L21: E005 | N21: North | O21: Houston | P21: VORTEX INC. | Q21: EIN: 517630478 | R21: john.yahoo.com | S21: (369) 698-1979 | T21: 990 Johnson Ave | U21: 85526 | V21: usa | W21: Wire Transfer | X21: Cancelled | Y21: Partial | Z21: INV/2025/0016 | AA21: Store | AB21: Q3 | AC21: January | AD21: 2025 | AE21: Net 60 | AF21: 7 | AG21: 0.08 | AJ21: 43.48 | AK21: Fed Ex | AL21: DH994024254 | AM21: 12.9 kg | AN21: wh b | AO21: 350 | AP21: 4 | AQ21: complaint | AR21: yes | AS21: damaged | AT21: 25% | AU21: #N/A | AV21: john johnson | AW21: John Johnson | AX21: check price
A22: TR-2025017 | B22: 08/09/2026 | C22: 18.08.2026 | D22: P-054 | E22: Mouse Basic 54 | F22: Office | G22: 18 kom | H22: 801,23 | I22: 5% | J22: USD 14,422 | K22: USD | L22: EMP5 | M22: null | N22: East | O22: Los Angles | P22: Wayne LLC | Q22: EIN: 852761906 | R22: sophia.yahoo.com | S22: +1 352 452 1730 | T22: 648 Wilson Street | U22: 21467 | V22: USA | W22: Cash | X22: Processing | Y22: YES | Z22: INV/2026/0017 | AA22: online | AB22: Q1 | AC22: 8 | AD22: 2026 | AE22: 15 | AF22: 72 | AG22: 0,08 | AJ22: 13.08 USD | AK22: FedEx | AL22: FX923827298 | AM22: 17.83 | AN22: Warehouse B | AO22: 102 | AP22: excellent | AR22: No | AT22: 25% | AU22: 432,66 | AV22: Sophia Taylor | AW22: Sophia Taylor | AX22: duplicate?
A23: TR-2025018 | B23: 20250503 | C23: 20250505 | D23: p041 | E23: Monitor X 41 | F23: SOFTWARE | G23: 6 | H23: 247.64 USD | I23: 0.1 | J23: 1485.84 USD | K23: USD | L23: E013 | M23: ROBERT WILLIAMS | N23: East | O23: seattle | P23: Stark INC | Q23: EIN: 375962955 | R23: david.gmail.com | S23: (588) 372-8231 | T23: 161 Brown Street | U23: 82088 | V23: US | W23: Wire Transfer | X23: Delivered | Y23: Partial | Z23: INV/2025/0018 | AA23: Online | AB23: Q4 | AC23: 5 | AD23: 2025 | AE23: Net 60 | AF23: 41 | AG23: 8 | AJ23: $5.78 | AK23: Fed Ex | AL23: DH160909509 | AM23: 13.6 kg | AN23: WH-A | AO23: 136 | AP23: 4 | AQ23: all good | AR23: No | AS23: damaged | AT23: 15 % | AU23: N/A | AV23: david miller | AW23: David Miller | AX23: urgent
A24: TR-2025019 | B24: 2025-08-05 | C24: 11-Aug-25 | D24: p033 | E24: - | F24: OFFICE | G24: 31 | H24: null | I24: 0.1 | J24: 4.000,86 | K24: USD | L24: E002 | M24: sarah wilson | N24: South | O24: BOSTON | P24: acme inc | Q24: EIN: 884743535 | R24: sophia.yahoo.com | S24: +1 796 515 4314 | T24: 862 Smith Ave | U24: 44937 | V24: usa | W24: Credit Card | X24: Delivered | Y24: Partial | Z24: INV/2025/0019 | AA24: Phone | AB24: q1 | AC24: Aug | AD24: 2025 | AE24: 15 | AF24: 23 | AG24: 0.08 | AJ24: 1.83 | AK24: DHL | AL24: 1Z482420536 | AM24: 15.64 | AN24: Warehouse B | AO24: 365 | AP24: 5/5 | AQ24: complaint | AR24: 0 | AS24: wrong item | AT24: 15 % | AU24: 120.03 USD | AV24: sophia jones | AW24: Sophia Jones | AX24: duplicate?
A26: TR-2025020 | B26: 2025-05-18 | C26: 05/20/2025 | D26: P-052 | E26: LAPTOP MAX 52 | F26: Furniture | G26: 16 kom. | H26: 1467.86 | I26: 10% | J26: - | K26: USD | L26: E018 | M26: #N/A | N26: South | O26: NY | P26: Stark INC | Q26: EIN: 901632584 | R26: emily.gmail.com | S26: +1 910 630 9611 | T26: 347 Davis St. | U26: 44919 | V26: U.S. | W26: Cash | X26: Cancelled | Y26: YES | Z26: INV/2025/0020 | AA26: Online | AB26: 1st quarter | AC26: May | AD26: 2025 | AE26: Net 60 | AF26: 31 | AG26: 8% | AJ26: 18,22 | AK26: UPS | AL26: FX315591108 | AM26: 0.7 kg | AN26: wh b | AP26: 1 | AQ26: complaint | AR26: 0 | AS26: doesn't fit | AT26: 0.3 | AU26: 704.57 | AV26: Emily Brown
A27: TR-2025021 | B27: 20260321 | C27: 24.03.2026 | D27: P_034 | F27: Office | G27: 3 kom | H27: 23,03 | I27: 0 | J27: #N/A | K27: EUR | L27: e-001 | M27: Sarah Wilson | N27: East | O27: Los Angles | P27: Initech inc | Q27: EIN: 650238460 | R27: david.company.com | S27: (561) 366-4908 | T27: 303 Smith Street | U27: 21783 | V27: U.S. | W27: Cash | X27: Cancelled | Y27: NO | Z27: INV/2026/0021 | AA27: Online | AB27: Q3 | AC27: March | AD27: 2026 | AE27: Net 60 | AF27: 13 | AG27: 0,08 | AJ27: 20.84 | AK27: USPS | AL27: 1Z761743464 | AM27: 18.36 | AN27: wh b | AO27: 137 | AP27: 3 | AQ27: OK | AR27: 1 | AT27: 25% | AU27: USD 2 | AV27: David Johnson | AW27: same | AX27: VIP customer
A28: TR-2025022 | B28: 04/24/2025 | C28: 30-Apr-25 | D28: P_055 | E28: Cable Basic 55 | F28: Office | G28: 29 kom. | H28: 921,78 | I28: 0.1 | J28: 26731.62 | K28: $ | L28: EMP9 | M28: #N/A | N28: North | O28: Houston | P28: INITECH INC | Q28: EIN: 930519543 | R28: emma.company.com | S28: (647) 729-9474 | T28: 609 Miller Blvd | U28: 02360 | V28: U.S. | W28: credit card | X28: Delivered | Y28: Partial | Z28: INV/2025/0022 | AA28: Store | AB28: Q3 | AC28: April | AD28: '25 | AE28: 15 | AF28: 24 | AG28: 8 | AJ28: 20.08 USD | AK28: DHL | AL28: FX842576360 | AM28: 24.5 kg | AN28: Warehouse B | AO28: 500 | AP28: 5 | AQ28: satisfied | AR28: NO | AT28: 0.3 | AU28: 801.95 | AV28: Emma Wilson | AW28: same | AX28: duplicate?
A29: TR-2025023 | B29: 01.08.2025. | C29: 08/03/2025 | D29: P-019 | E29: Monitor Max 19 | G29: 13 | H29: 251,62 | I29: 5% | J29: 3271,06 | K29: EUR | L29: e-017 | M29: Robert Davis | N29: NORTH | O29: Boston | P29: ACME LTD. | Q29: EIN: 758208298 | R29: james.gmail.com | S29: (900) 989-6289 | T29: 274 Johnson Street | U29: 46730 | V29: U.S. | W29: Wire Transfer | X29: Delivered | Y29: Paid | Z29: INV/2025/0023 | AA29: Web | AB29: Q2 | AC29: Aug | AD29: 2025 | AE29: immediate | AF29: 6 | AG29: 0,08 | AJ29: 11,14 | AK29: Fed Ex | AL29: FX106617834 | AM29: 9,18 | AN29: Warehouse B | AO29: 491 | AP29: 2 | AQ29: all good | AR29: 0 | AS29: wrong item | AT29: 15 % | AU29: 98,13 | AV29: James Williams | AW29: James Williams | AX29: urgent
A30: TR-2025024 | B30: 01/24/2026 | C30: 01/26/2026 | D30: P-011 | E30: Mouse Pro 11 | F30: Equipment | G30: 1 kom | H30: 858,95 | I30: 0.1 | J30: N/A | K30: usd | L30: e-012 | M30: #N/A | N30: west | O30: LA | P30: umbrella ltd. | Q30: 504686425 | R30: ryan.yahoo.com | S30: 923.467.8214 | T30: 377 Taylor St. | U30: 53972 | V30: US | W30: credit card | X30: Delivered | Y30: NO | Z30: INV/2026/0024 | AA30: online | AB30: Q1 | AC30: Jan | AD30: 2026 | AE30: immediate | AF30: 3 | AG30: 0,08 | AJ30: USD 16 | AK30: USPS | AL30: 1Z933371692 | AM30: 25.54 | AN30: Warehouse A | AO30: 287 | AP30: 4.5 | AQ30: complaint | AR30: Yes | AT30: 25% | AU30: 25.77 | AV30: ryan jones | AX30: VIP customer
A31: TR-2025025 | B31: 16-May-25 | C31: 20250517 | D31: P-055 | E31: cable basic 55 | F31: office | G31: 12 | H31: N/A | I31: 10 | J31: 11.061,36 | K31: usd | L31: E015 | M31: Sarah Jones | N31: NORTH | O31: chicago | P31: Wayne inc | Q31: EIN: 819550596 | R31: john.gmail.com | S31: (982) 995-5691 | T31: 811 Miller St. | U31: 46306 | V31: USA | W31: Wire Transfer | X31: Pending | Y31: NO | Z31: INV/2025/0025 | AA31: Phone | AB31: Q4 | AC31: May | AD31: 2025 | AE31: Net 60 | AF31: #N/A | AG31: 8 | AJ31: 46.51 | AK31: USPS | AL31: DH772107295 | AM31: 1.7 kg | AN31: Warehouse C | AO31: 433 | AP31: 3 | AQ31: OK | AR31: 1 | AT31: 25% | AU31: 331.84 | AV31: John Miller | AW31: same | AX31: duplicate?
A32: TR-2025026 | B32: 20250302 | C32: 2025-03-07 | D32: P-017 | E32: #N/A | F32: N/A | G32: 23 | H32: $1,313.33 | I32: 10% | J32: 30206,59 | K32: usd | L32: e-008 | M32: Michael Williams | N32: North | O32: los angeles | P32: ACME INC | Q32: 426314041 | R32: jessica.company.com | S32: (315) 365-6316 | T32: 12 Wilson Blvd | U32: 12006 | V32: United States | W32: PayPal | X32: DELIVERED | Y32: Unpaid | Z32: INV/2025/0026 | AA32: Online | AB32: Q4 | AC32: March | AD32: 2025 | AE32: immediate | AF32: 24 | AG32: 0.08 | AJ32: 0.42 | AK32: USPS | AL32: DH884520761 | AM32: 19.61 | AN32: Warehouse A | AO32: 12 | AP32: 3 | AQ32: late delivery!! | AR32: Yes | AT32: 15 % | AU32: 906.20 USD | AV32: Jessica Davis | AX32: VIP customer
A33: TR-2025027 | B33: 12/31/2025 | C33: null | D33: P-012 | E33: N/A | F33: Electronics | G33: 15 | H33: 823,88 | I33: 0.1 | J33: 12.358,20 | K33: USD | L33: E021 | M33: - | N33: North | O33: Chicago | P33: Stark inc | Q33: EIN: 253719173 | R33: jessica.gmail.com | S33: 209.882.3888 | T33: 169 Davis Ave | U33: 01549 | V33: U.S. | W33: PayPal | X33: Processing | Y33: YES | Z33: INV/2025/0027 | AA33: Web | AB33: Q2 | AC33: 12 | AD33: '25 | AE33: Net 60 | AF33: 66 | AG33: 0,08 | AJ33: 48,72 | AK33: FedEx | AL33: DH826328507 | AM33: 19.8 kg | AN33: Warehouse B | AO33: 246 | AP33: 3 | AQ33: late delivery!! | AR33: 1 | AS33: damaged | AT33: 15 % | AU33: N/A | AV33: jessica williams | AW33: same | AX33: duplicate?
A34: TR-2025028 | B34: 18-Aug-26 | C34: 23.08.2026 | D34: p024 | E34: - | F34: Electronics | G34: 24 | H34: 95.70 USD | I34: 10% | J34: 2296.80 USD | K34: EUR | L34: E018 | M34: John Miller | N34: West | O34: Huston | P34: Stark LLC | Q34: 932128440 | R34: robert.yahoo.com | S34: +1 248 581 1683 | T34: 308 Johnson St. | U34: 56833 | V34: USA | W34: wire | X34: delivered | Y34: YES | Z34: INV/2026/0028 | AA34: Online | AB34: Q4 | AC34: August | AD34: 2026 | AE34: Net 60 | AF34: 43 | AG34: 8% | AJ34: 41.28 | AK34: DHL | AL34: DH663401775 | AM34: 1,4 | AN34: Warehouse B | AO34: 51 | AP34: 5/5 | AQ34: complaint | AT34: 25% | AU34: - | AV34: robert brown | AW34: Robert
A35: TR-2025029 | B35: 15.05.2026. | C35: 20260520 | D35: p051 | E35: Cable Basic 51 | F35: office | G35: 5 kom. | I35: 10% | J35: 5.183,25 | K35: EUR | L35: E001 | M35: Sarah Wilson | N35: South | O35: NY | P35: Globex INC | Q35: 434209630 | R35: chris.gmail.com | S35: (569) 944-8663 | T35: 344 Anderson Blvd | U35: 44749 | V35: US | W35: Wire Transfer | X35: DELIVERED | Y35: Paid | Z35: INV/2026/0029 | AA35: Web | AB35: Q4 | AC35: May | AD35: 2026 | AE35: Net 60 | AF35: 49 | AG35: 0.08 | AJ35: 17,84 | AK35: Fed Ex | AL35: DH136627024 | AM35: 27.46 | AN35: wh b | AO35: 324 | AP35: 2 | AQ35: late delivery!! | AR35: 1 | AS35: damaged | AT35: 0,18 | AU35: 155.50 USD | AV35: CHRIS JONES | AW35: same | AX35: check price
A36: TR-2025030 | B36: 20-Feb-26 | C36: 03/01/2026 | D36: p056 | E36: Keyboard X 56 | F36: Software | G36: 4 | H36: 1.111,11 | I36: 0.1 | J36: $4,444.44 | K36: EUR | L36: EMP18 | M36: - | N36: west | O36: CHICAGO | P36: Wayne inc | Q36: EIN: 620244895 | R36: emma.gmail.com | S36: (463) 759-1378 | T36: 49 Davis Blvd | U36: 27259 | V36: United States | W36: wire | X36: Pending | Y36: Paid | Z36: INV/2026/0030 | AA36: Web | AB36: q1 | AC36: Feb | AD36: 2026 | AE36: 15 | AG36: 0.08 | AJ36: 35.95 | AK36: DHL | AL36: DH116113610 | AM36: 27.7 kg | AN36: Warehouse A | AO36: 332 | AP36: 5/5 | AQ36: all good | AR36: No | AS36: wrong item | AT36: 25% | AU36: 133.33 | AV36: Emma Miller | AX36: VIP customer
A37: TR-2025031 | B37: 27.01.2025. | C37: 20250208 | D37: p056 | E37: KEYBOARD X 56 | F37: Software | G37: 37 | H37: 1111.11 | J37: null | K37: $ | L37: E001 | M37: Sarah Wilson | N37: West | O37: Chicgo | P37: Acme LLC | Q37: EIN: 241588570 | R37: daniel.gmail.com | S37: (302) 871-6939 | T37: 640 Williams Street | U37: 08886 | V37: US | W37: wire | X37: delivered | Y37: Unpaid | Z37: INV/2025/0031 | AA37: online | AB37: 1st quarter | AC37: Jan | AD37: 2025 | AE37: 15 | AF37: 20 | AG37: 0.08 | AJ37: 38,91 | AK37: ups | AL37: 1Z783034651 | AM37: 27.38 | AN37: Warehouse B | AO37: 404 | AP37: 2 | AR37: 0 | AT37: 25% | AU37: 1233.33 USD | AV37: Daniel Miller | AW37: Daniel | AX37: VIP customer
A38: TR-2025032 | B38: 2025-08-18 | C38: 08/22/2025 | D38: P-059 | E38: Keyboard Max 59 | F38: - | G38: 17 kom | H38: 673.61 | I38: 10 | J38: 11451.37 USD | K38: usd | L38: EMP13 | M38: Robert Williams | N38: South | O38: NYC | P38: WAYNE LLC | Q38: EIN: 250107754 | S38: (355) 209-3185 | T38: 476 Davis Street | U38: 55290 | V38: usa | W38: Cash | X38: Delivered | Y38: YES | Z38: INV/2025/0032 | AA38: Web | AB38: q1 | AC38: Aug | AD38: '25 | AE38: Net 30 | AF38: null | AG38: 0,08 | AJ38: 28.74 | AK38: FedEx | AL38: 1Z439828953 | AM38: 2.03 | AN38: Warehouse C | AO38: N/A | AP38: 4.5 | AQ38: all good | AR38: 0 | AS38: doesn't fit | AT38: 15 % | AU38: 343.54 | AV38: John Jones | AW38: same
A39: TR-2025193 | B39: 01/22/2025 | C39: 02/03/2025 | D39: P21 | E39: Monitor Max 21 | F39: N/A | G39: 30 | H39: 1184,70 | I39: 10 | J39: 35541,00 | K39: usd | L39: E012 | M39: #N/A | N39: NORTH | O39: NY | P39: Acme Inc. | Q39: 499269182 | R39: laura.gmail.com | S39: (798) 468-6016 | T39: 428 Jones Street | U39: 51354 | V39: United States | W39: wire | X39: delivered | Y39: NO | Z39: INV/2025/0193 | AA39: Store | AB39: Q3 | AC39: Jan | AD39: 2025 | AE39: immediate | AF39: 84 | AG39: 0.08 | AJ39: 21.04 | AK39: ups | AL39: FX387168701 | AM39: 25.4 kg | AN39: Warehouse B | AO39: 197 | AP39: 2 | AQ39: all good | AR39: 0 | AU39: 1066.23 | AV39: Laura Williams | AW39: same | AX39: duplicate?
A40: TR-2025033 | B40: 01.07.2025. | C40: 02-Jul-25 | D40: P18 | E40: license basic 18 | F40: Equipment | G40: 17 kom | H40: USD 1,470 | J40: USD 24,996 | K40: usd | L40: E023 | M40: Laura Anderson | N40: West | O40: New York | P40: acme inc | Q40: EIN: 755957168 | R40: david.gmail.com | S40: 615.910.6314 | T40: 662 Wilson Ave | U40: 60702 | V40: USA | W40: Wire Transfer | X40: Pending | Y40: NO | Z40: INV/2025/0033 | AA40: Phone | AB40: Q3 | AC40: July | AD40: '25 | AE40: immediate | AF40: 30 | AG40: 8 | AJ40: 17.76 | AK40: DHL | AL40: FX758003774 | AM40: 2,25 | AN40: WH-A | AO40: 473 | AP40: 5 | AQ40: late delivery!! | AR40: 1 | AS40: wrong item | AT40: 0.3 | AU40: 749,88 | AV40: David Johnson | AX40: duplicate?
A41: TR-2025034 | B41: 2025-06-23 | C41: 20250704 | D41: P-014 | E41: License Max 14 | F41: Software | G41: 24 kom | H41: USD 1,167 | I41: 0.1 | J41: #N/A | K41: USD | L41: E017 | M41: N/A | N41: East | O41: miami | P41: Globex LLC | Q41: EIN: 509238663 | R41: sarah.gmail.com | S41: +1 259 804 3923 | T41: 939 Miller Ave | U41: 32697 | V41: usa | W41: Credit Card | X41: DELIVERED | Y41: NO | Z41: INV/2025/0034 | AA41: Phone | AB41: Q1 | AC41: 6 | AD41: 2025 | AE41: immediate | AF41: 37 | AG41: 0.08 | AJ41: 46.03 | AK41: UPS | AL41: 1Z865080132 | AM41: 12,99 | AN41: Warehouse B | AO41: 180 | AP41: 3 | AQ41: satisfied | AR41: NO | AS41: doesn't fit | AT41: 0.3 | AU41: 840.21 | AV41: Sarah Williams | AW41: Sarah | AX41: VIP customer
A42: TR-2025035 | B42: 27-Jan-25 | C42: 2025-02-04 | D42: P-060 | E42: Desk Basic 60 | F42: Electronics | G42: 38 kom. | H42: 334.59 USD | I42: 10% | J42: 12.714,42 | K42: EUR | L42: E021 | M42: N/A | N42: West | O42: NYC | P42: Umbrella LLC | Q42: EIN: 250559903 | R42: olivia.gmail.com | S42: 390.751.5500 | T42: 269 Johnson Ave | U42: 51295 | V42: United States | W42: wire | X42: Cancelled | Y42: YES | Z42: INV/2025/0035 | AA42: Phone | AB42: Q4 | AC42: 1 | AD42: 2025 | AE42: Net 60 | AF42: 31 | AG42: 8 | AJ42: $42.83 | AK42: Fed Ex | AL42: 1Z322808127 | AM42: 11.3 kg | AN42: Warehouse C | AO42: 72 | AP42: 5/5 | AQ42: all good | AR42: yes | AS42: doesn't fit | AT42: 25% | AU42: 381.43 | AV42: Olivia Wilson
A43: TR-2025036 | B43: 26.03.2026. | C43: 03-Apr-26 | D43: P-018 | E43: license basic 18 | F43: EQUIPMENT | G43: 13 | H43: 1470.36 | I43: 5% | J43: 19.114,68 | K43: $ | L43: e-008 | M43: Michael Williams | N43: South | O43: Chicago | P43: Vortex Ltd. | Q43: EIN: 858287081 | R43: emma.company.com | S43: 500.976.4812 | T43: 817 Miller St. | U43: 41575 | V43: United States | W43: wire | X43: delivered | Y43: paid | Z43: INV/2026/0036 | AA43: Web | AB43: Q2 | AC43: 3 | AD43: 2026 | AE43: immediate | AF43: 19 | AG43: 0,08 | AJ43: 32.74 | AK43: ups | AL43: 1Z881941210 | AM43: 5.6 | AN43: Warehouse B | AO43: 62 | AP43: 4 | AS43: doesn't fit | AT43: 25% | AU43: $573.44 | AV43: EMMA BROWN | AW43: Emma Brown | AX43: urgent
A44: TR-2025037 | B44: 07-Nov-25 | C44: 2025-11-12 | D44: P32 | E44: CABLE BASIC 32 | F44: Software | G44: 38 kom. | H44: 1.479,77 | I44: 0.1 | J44: - | K44: USD | L44: E009 | M44: OLIVIA WILSON | N44: west | O44: Boston | P44: GLOBEX INC | Q44: EIN: 241701002 | R44: robert.company.com | S44: +1 568 373 2475 | T44: 153 Jones Street | U44: 14963 | V44: USA | W44: credit card | X44: Cancelled | Y44: Unpaid | Z44: INV/2025/0037 | AA44: online | AB44: Q3 | AC44: 11 | AD44: 2025 | AE44: immediate | AF44: null | AG44: 8% | AJ44: $25.34 | AK44: UPS | AL44: FX696240173 | AM44: 7,27 | AN44: Warehouse C | AO44: 122 | AP44: 1 | AR44: No | AS44: wrong item | AT44: 15 % | AU44: 1.686,94 | AV44: robert johnson | AW44: Robert Johnson | AX44: VIP customer
A45: TR-2025038 | B45: 2026-06-15 | C45: 2026-06-19 | D45: P_026 | E45: Printer Basic 26 | F45: ELECTRONICS | G45: 19 kom | H45: 1411.27 | I45: 10 | J45: 26814,13 | K45: USD | L45: EMP20 | M45: N/A | N45: South | O45: NY | P45: Acme Ltd. | Q45: 318762581 | R45: olivia.company.com | S45: 997.537.2131 | T45: 652 Johnson St. | U45: 82940 | V45: United States | W45: Wire Transfer | X45: Delivered | Y45: NO | Z45: INV/2026/0038 | AA45: Store | AB45: Q3 | AC45: 6 | AD45: 2026 | AE45: immediate | AF45: 17 | AG45: 0.08 | AJ45: 45.24 | AK45: USPS | AL45: DH276871522 | AM45: 23,55 | AN45: Warehouse B | AO45: 382 | AP45: 4.5 | AR45: 0 | AT45: 25% | AU45: 804.42 USD | AV45: olivia johnson | AW45: Olivia | AX45: duplicate?
A46: TR-2025039 | B46: 12-Aug-26 | C46: 19.08.2026 | D46: P-016 | E46: Keyboard X 16 | F46: Office | G46: 4 kom. | H46: USD 127 | I46: 0.1 | J46: null | K46: usd | L46: E016 | N46: East | O46: Seattle | P46: Vortex inc | Q46: 966650888 | R46: james.gmail.com | S46: (242) 584-4016 | T46: 360 Anderson Blvd | U46: 41444 | V46: U.S. | W46: wire | X46: delivered | Y46: paid | Z46: INV/2026/0039 | AA46: Phone | AB46: Q3 | AC46: 8 | AD46: 2026 | AE46: 15 | AF46: 13 | AG46: 8 | AJ46: 28.26 | AK46: UPS | AL46: DH208348261 | AM46: 22,62 | AN46: wh b | AO46: 69 | AP46: 5 | AR46: yes | AT46: 15 % | AU46: 15,28 | AV46: james davis | AW46: James | AX46: duplicate?
A47: TR-2025315 | B47: 2026-05-02 | C47: 20260511 | D47: P-051 | E47: Cable Basic 51 | F47: OFFICE | G47: 3 | H47: 1036.65 USD | I47: 5% | J47: 3109,95 | K47: usd | L47: EMP8 | M47: #N/A | N47: South | O47: NYC | P47: Globex LLC | Q47: EIN: 676954297 | R47: sarah.yahoo.com | S47: (873) 709-9403 | T47: 961 Johnson Street | U47: 49274 | V47: United States | W47: wire | X47: Delivered | Y47: Partial | Z47: INV/2026/0315 | AA47: online | AB47: Q4 | AC47: May | AD47: '26 | AE47: Net 60 | AF47: 43 | AG47: 0.08 | AJ47: 5,85 | AK47: Fed Ex | AL47: DH773058896 | AM47: 16.22 | AN47: Warehouse B | AO47: 300 | AP47: excellent | AQ47: late delivery!! | AR47: 1 | AT47: 0.3 | AU47: - | AV47: Sarah Johnson | AW47: same | AX47: check price
A48: TR-2025040 | B48: 03.03.2025 | C48: 20250317 | D48: P-052 | E48: Laptop Max 52 | F48: - | G48: 32 | H48: 1.467,86 | J48: #N/A | K48: usd | L48: EMP22 | M48: Chris Williams | N48: West | O48: Seattle | P48: Wayne Inc. | Q48: EIN: 486805686 | R48: laura.yahoo.com | S48: (788) 707-1791 | T48: 316 Taylor St. | U48: 90313 | V48: USA | W48: wire | X48: Processing | Y48: Partial | Z48: INV/2025/0040 | AA48: Store | AB48: Q4 | AC48: 3 | AD48: 2025 | AE48: Net 60 | AF48: - | AG48: 8 | AJ48: 20.15 | AK48: ups | AL48: FX513945836 | AM48: 3,46 | AN48: wh b | AO48: 256 | AP48: 3 | AQ48: complaint | AR48: Yes | AT48: 0,18 | AU48: $1,409.15 | AV48: Laura Miller | AW48: Laura Miller | AX48: check price
A49: TR-2025142 | B49: 16-Sep-25 | C49: 20250921 | D49: P-010 | E49: N/A | F49: Equipment | G49: 25 | H49: USD 1,225 | I49: 10 | J49: 30627.75 | K49: USD | L49: EMP19 | M49: Sophia Taylor | N49: west | O49: Huston | P49: Globex Inc. | Q49: 115358037 | R49: chris.gmail.com | S49: (685) 870-5970 | T49: 614 Williams St. | U49: 26466 | V49: USA | W49: Credit Card | X49: Cancelled | Y49: Unpaid | Z49: INV/2025/0142 | AA49: Phone | AB49: Q4 | AC49: 9 | AD49: '25 | AE49: 15 | AF49: 79 | AG49: 0.08 | AJ49: N/A | AK49: UPS | AL49: DH682392370 | AM49: 26.05 | AN49: Warehouse A | AO49: null | AP49: 4 | AQ49: OK | AR49: yes | AS49: doesn't fit | AT49: 25% | AU49: 918,83 | AV49: chris jones | AW49: Chris | AX49: duplicate?
A50: TR-2025041 | B50: 10.02.2026 | C50: 11.02.2026. | D50: P_026 | E50: Printer Basic 26 | F50: Electronics | G50: 19 kom. | H50: 1411.27 USD | I50: 10% | J50: N/A | K50: USD | L50: E012 | M50: #N/A | N50: west | O50: Bostn | P50: Initech LLC | Q50: EIN: 544142395 | R50: sophia.gmail.com | S50: 787.883.4859 | T50: 443 Davis St. | U50: 76198 | V50: US | W50: credit card | X50: delivered | Y50: NO | Z50: INV/2026/0041 | AA50: Web | AB50: Q3 | AC50: 2 | AD50: 2026 | AE50: Net 30 | AF50: 83 | AG50: 0.08 | AJ50: 6.56 | AK50: ups | AL50: DH395362069 | AM50: 18,18 | AN50: Warehouse B | AO50: 311 | AP50: 4 | AQ50: late delivery!! | AR50: No | AS50: damaged | AT50: 15 % | AV50: Sophia Johnson | AW50: same | AX50: VIP customer
A51: TR-2025042 | B51: 02.03.2025 | C51: 11-Mar-25 | D51: p018 | E51: license basic 18 | F51: equipment | G51: 38 | H51: 1.470,36 | I51: 10% | J51: 55873.68 USD | K51: USD | L51: EMP17 | M51: ROBERT DAVIS | N51: west | O51: Huston | P51: Vortex Inc. | Q51: EIN: 498732700 | R51: robert.company.com | S51: (273) 857-8829 | T51: 350 Anderson St. | U51: 15664 | V51: United States | W51: credit card | X51: Delivered | Y51: NO | Z51: INV/2025/0042 | AA51: online | AB51: Q1 | AC51: March | AD51: 2025 | AE51: 15 | AF51: 33 | AG51: 0.08 | AJ51: 37.38 | AK51: USPS | AL51: DH872570652 | AM51: 12,6 | AN51: Warehouse C | AO51: 135 | AP51: 3 | AQ51: satisfied | AR51: 0 | AS51: damaged | AT51: 0.3 | AU51: N/A | AV51: Robert Anderson | AW51: Robert
A52: TR-2025043 | B52: 07-Jun-25 | C52: 2025-06-21 | D52: P_022 | E52: Desk Basic 22 | F52: Furniture | G52: 31 kom. | H52: 893.58 USD | I52: 10 | J52: 27.700,98 | K52: USD | L52: e-004 | N52: North | O52: Chicgo | P52: Initech inc | Q52: EIN: 447211740 | R52: laura.company.com | S52: (672) 696-4370 | T52: 606 Williams St. | U52: 58676 | V52: U.S. | W52: PayPal | X52: Pending | Y52: NO | Z52: INV/2025/0043 | AA52: Phone | AB52: Q1 | AC52: Jun | AD52: '25 | AE52: Net 30 | AF52: N/A | AG52: 8 | AJ52: USD 35 | AK52: FedEx | AL52: FX743248426 | AM52: 11.51 | AN52: Warehouse A | AO52: 200 | AP52: 4 | AR52: 0 | AT52: 0,18 | AU52: 831.03 | AV52: laura johnson | AW52: same
A53: TR-2025044 | B53: 15-Aug-26 | C53: 28.08.2026 | D53: P-060 | E53: DESK BASIC 60 | F53: Electronics | G53: 17 | J53: 5688,03 | K53: EUR | L53: E018 | M53: John Miller | N53: West | O53: Houston | P53: Umbrella Inc. | Q53: EIN: 999035931 | R53: john.gmail.com | S53: 827.288.9947 | T53: 361 Johnson Street | U53: 96705 | V53: USA | W53: Credit Card | X53: Processing | Y53: Unpaid | Z53: INV/2026/0044 | AA53: Store | AB53: 1st quarter | AC53: August | AD53: 2026 | AE53: immediate | AF53: 77 | AG53: 0.08 | AJ53: 38.44 | AK53: FedEx | AL53: 1Z833233426 | AM53: 18.0 kg | AN53: wh b | AO53: 472 | AP53: 4 | AQ53: complaint | AR53: 0 | AT53: 25% | AV53: John Williams | AW53: John Williams | AX53: urgent
A54: TR-2025045 | B54: 29.03.2026 | C54: 04-Apr-26 | D54: P-040 | E54: monitor plus 40 | F54: Software | G54: 9 | H54: 98.06 | I54: 10% | J54: - | K54: $ | L54: E010 | M54: Olivia Anderson | N54: NORTH | O54: chicago | P54: VORTEX INC | Q54: EIN: 461801009 | R54: david.gmail.com | S54: 450.617.9500 | T54: 796 Johnson St. | U54: 29581 | V54: USA | W54: PayPal | X54: Processing | Y54: Partial | Z54: INV/2026/0045 | AA54: Online | AB54: q1 | AC54: Mar | AD54: 2026 | AE54: 15 | AF54: 88 | AG54: 0.08 | AJ54: 37,66 | AK54: FedEx | AL54: 1Z842113802 | AM54: 18,59 | AN54: Warehouse C | AO54: 72 | AP54: 2 | AR54: yes | AS54: damaged | AT54: 25% | AU54: 26.48 | AV54: David Jones | AW54: David | AX54: duplicate?
A55: TR-2025046 | B55: 20260406 | C55: 2026-04-18 | D55: P-045 | E55: Keyboard Max 45 | F55: N/A | G55: 7 kom | H55: 227.08 | J55: 1589.56 | K55: USD | L55: E009 | M55: olivia wilson | N55: South | O55: Los Angeles | P55: UMBRELLA LLC | Q55: 800324313 | R55: david.gmail.com | S55: +1 563 572 9883 | T55: 807 Jones Ave | U55: 49002 | V55: USA | W55: credit card | X55: delivered | Y55: Unpaid | Z55: INV/2026/0046 | AA55: Phone | AB55: Q1 | AC55: 4 | AD55: '26 | AE55: 15 | AF55: 28 | AG55: 0.08 | AJ55: USD 12 | AK55: FedEx | AL55: 1Z206951192 | AM55: 19.94 | AN55: wh b | AO55: 224 | AP55: 2 | AQ55: OK | AS55: wrong item | AT55: 25% | AU55: #N/A | AV55: David Jones | AW55: David Jones
A56: TR-2025047 | B56: 30.09.2025 | C56: 02.10.2025. | D56: P-013 | E56: monitor max 13 | F56: Electronics | G56: 29 | H56: 930,42 | I56: 0.1 | J56: - | K56: USD | L56: E003 | M56: - | N56: West | O56: CHICAGO | P56: INITECH LTD. | Q56: 376295913 | R56: laura.company.com | S56: +1 903 958 1527 | T56: 681 Anderson St. | U56: 86345 | V56: usa | W56: Cash | X56: Pending | Y56: Paid | Z56: INV/2025/0047 | AA56: Store | AB56: Q4 | AC56: Sep | AD56: 2025 | AE56: 15 | AF56: 2 | AG56: 8% | AJ56: #N/A | AK56: Fed Ex | AL56: 1Z426893931 | AM56: 17.5 kg | AN56: Warehouse A | AO56: 347 | AP56: 5/5 | AQ56: OK | AR56: NO | AU56: $809.47 | AV56: Laura Brown | AW56: same | AX56: urgent
A57: TR-2025048 | B57: 26.07.2025 | C57: 2025-08-02 | D57: P-054 | E57: Mouse Basic 54 | F57: Office | G57: 30 kom. | H57: 801,23 | J57: #N/A | K57: usd | L57: e-016 | M57: N/A | N57: west | O57: chicago | P57: VORTEX INC | Q57: 371847290 | R57: david.gmail.com | S57: (475) 929-7680 | T57: 296 Williams St. | U57: 56061 | V57: usa | W57: Cash | X57: Pending | Y57: NO | Z57: INV/2025/0048 | AA57: online | AB57: Q3 | AC57: 7 | AD57: 2025 | AE57: 15 | AF57: 63 | AG57: 0.08 | AJ57: 44,94 | AK57: FedEx | AL57: DH372030581 | AM57: 5.5 kg | AN57: WH-A | AO57: 210 | AP57: 4.5 | AQ57: late delivery!! | AR57: 0 | AT57: 25% | AU57: 721,11 | AV57: david brown | AW57: David | AX57: VIP customer
A58: TR-2025049 | B58: 2025-07-04 | C58: 13-Jul-25 | D58: p022 | E58: Desk Basic 22 | F58: Furniture | G58: 21 kom | H58: N/A | I58: 10 | J58: 18765,18 | K58: USD | L58: E022 | M58: #N/A | N58: East | O58: Houston | P58: Umbrella Inc. | Q58: EIN: 272806008 | R58: chris.yahoo.com | S58: +1 763 857 4342 | T58: 785 Jones Ave | U58: 22418 | V58: U.S. | W58: Wire Transfer | X58: Pending | Y58: YES | Z58: INV/2025/0049 | AA58: Online | AB58: q1 | AC58: 7 | AD58: '25 | AE58: immediate | AF58: 71 | AG58: 8% | AJ58: 39.92 USD | AK58: USPS | AL58: 1Z104225747 | AM58: 5.29 | AN58: Warehouse A | AO58: 12 | AP58: 2 | AQ58: all good | AR58: NO | AS58: wrong item | AT58: 0.3 | AU58: 562.96 | AV58: Chris Brown | AX58: check price
A59: TR-2025050 | B59: 20250928 | C59: 2025-10-03 | D59: P-004 | E59: Printer Plus 4 | F59: Electronics | G59: 17 kom | H59: - | I59: 5% | J59: 6201.43 | K59: USD | L59: E003 | M59: Laura Miller | N59: South | O59: Los Angeles | P59: Stark Inc. | Q59: 114117891 | R59: emily.gmail.com | S59: (668) 446-5235 | T59: 235 Smith St. | U59: 68212 | V59: usa | W59: wire | X59: delivered | Y59: paid | Z59: INV/2025/0050 | AA59: Web | AB59: 1st quarter | AC59: Sep | AD59: 2025 | AE59: 15 | AF59: #N/A | AG59: 0.08 | AJ59: 41.35 | AK59: USPS | AL59: FX525758121 | AM59: 1,76 | AN59: Warehouse B | AO59: 45 | AP59: 5/5 | AQ59: satisfied | AR59: NO | AT59: 0,18 | AU59: 186.04 | AV59: Emily Johnson | AX59: VIP customer
A60: TR-2025051 | B60: 18.03.2025 | C60: 20250323 | D60: P-034 | E60: Mouse X 34 | F60: Office | G60: 5 | H60: 23.03 | I60: 10% | J60: 115.15 | K60: usd | L60: E010 | M60: null | N60: North | O60: NYC | P60: Umbrella LLC | Q60: 465930425 | R60: olivia.gmail.com | S60: +1 232 494 3212 | T60: 168 Taylor Blvd | U60: 23165 | V60: usa | W60: Wire Transfer | X60: Pending | Y60: Unpaid | Z60: INV/2025/0051 | AA60: Store | AB60: Q1 | AC60: 3 | AD60: 2025 | AE60: Net 30 | AF60: 11 | AG60: 8 | AJ60: 23,64 | AK60: UPS | AL60: FX522196969 | AM60: 21.51 | AN60: wh b | AO60: 54 | AP60: 4.5 | AQ60: late delivery!! | AR60: 1 | AT60: 25% | AU60: $3.45 | AV60: Olivia Davis | AX60: check price
A61: TR-2025052 | B61: 2025-12-16 | C61: - | D61: P_012 | E61: KEYBOARD BASIC 12 | F61: electronics | G61: 13 kom. | H61: $823.88 | I61: 0.1 | J61: 10710.44 | K61: USD | L61: e-024 | M61: N/A | N61: East | O61: Seatle | P61: Acme Inc. | Q61: 429757560 | R61: daniel.company.com | S61: 962.893.9889 | T61: 933 Smith Blvd | U61: 45474 | V61: usa | W61: PayPal | X61: delivered | Y61: NO | Z61: INV/2025/0052 | AA61: Store | AB61: 1st quarter | AC61: 12 | AD61: 2025 | AE61: Net 30 | AF61: 15 | AG61: 8% | AJ61: 45.15 | AK61: FedEx | AL61: DH172650775 | AM61: 25,81 | AN61: wh b | AO61: 159 | AP61: excellent | AQ61: late delivery!! | AR61: 0 | AS61: doesn't fit | AU61: $321.31 | AV61: Daniel Davis | AW61: Daniel Davis | AX61: duplicate?
A62: TR-2025311 | B62: 08-Feb-25 | C62: 02/11/2025 | D62: P-006 | E62: monitor x 6 | F62: equipment | G62: 14 kom. | H62: 1.421,82 | I62: 0.1 | J62: USD 19,905 | K62: $ | L62: E015 | M62: #N/A | N62: West | O62: NYC | P62: Initech LLC | Q62: 891637245 | R62: robert.gmail.com | S62: +1 588 405 8590 | T62: 170 Wilson Street | U62: 27723 | V62: U.S. | W62: credit card | X62: DELIVERED | Y62: paid | Z62: INV/2025/0311 | AA62: Online | AB62: Q2 | AC62: February | AD62: 2025 | AE62: Net 30 | AF62: 60 | AG62: 8% | AJ62: 13,63 | AK62: USPS | AL62: 1Z598689555 | AM62: 18.1 kg | AN62: Warehouse B | AO62: 443 | AP62: 1 | AQ62: all good | AR62: Yes | AT62: 15 % | AV62: ROBERT ANDERSON | AW62: Robert | AX62: VIP customer
A64: TR-2025053 | B64: 2025-03-12 | C64: 03/16/2025 | D64: P-038 | E64: Cable Max 38 | F64: ELECTRONICS | G64: 29 kom | H64: 687.68 | I64: 0 | J64: 19942,72 | K64: usd | L64: EMP17 | N64: west | O64: Houston | P64: Wayne INC | Q64: 300591442 | R64: james.company.com | S64: (819) 587-3688 | T64: 213 Taylor Street | U64: 66850 | V64: US | W64: wire | X64: Cancelled | Y64: paid | Z64: INV/2025/0053 | AA64: online | AB64: q1 | AC64: 3 | AD64: 2025 | AE64: immediate | AF64: 3 | AG64: 0.08 | AJ64: 30,21 | AK64: DHL | AL64: DH602821939 | AM64: 24,1 | AN64: WH-A | AO64: 383 | AP64: 4.5 | AQ64: late delivery!! | AR64: NO | AS64: doesn't fit | AT64: 0,18 | AU64: 598,28 | AV64: James Smith | AW64: James Smith | AX64: VIP customer
A65: TR-2025054 | B65: 10.08.2025 | C65: 18.08.2025 | D65: P_046 | E65: Chair Basic 46 | F65: Equipment | G65: 28 kom. | H65: $549.42 | I65: 0.1 | J65: N/A | K65: USD | L65: E020 | M65: #N/A | N65: west | O65: Chicgo | P65: Acme LLC | Q65: 606622553 | R65: ryan.company.com | S65: +1 271 613 2645 | T65: 361 Davis St. | U65: 61986 | V65: U.S. | W65: wire | X65: Delivered | Y65: Paid | Z65: INV/2025/0054 | AA65: Phone | AB65: 1st quarter | AC65: Aug | AD65: '25 | AE65: immediate | AF65: 55 | AG65: 0,08 | AJ65: 27.71 | AK65: FedEx | AL65: DH256032416 | AM65: 20.4 kg | AN65: Warehouse C | AO65: 292 | AP65: 5/5 | AQ65: complaint | AR65: NO | AS65: doesn't fit | AT65: 15 % | AU65: USD 462 | AV65: ryan taylor | AW65: Ryan | AX65: VIP customer
A66: TR-2025104 | B66: 05.04.2026 | C66: 20260412 | D66: P46 | E66: Chair Basic 46 | F66: Equipment | G66: 16 kom | H66: 549,42 | I66: 5% | J66: USD 8,791 | K66: USD | L66: EMP23 | M66: Laura Anderson | N66: North | O66: Houston | P66: Initech INC | Q66: 567147611 | R66: john.company.com | S66: +1 852 532 1222 | T66: 778 Davis Ave | U66: 02457 | V66: usa | W66: wire | X66: Cancelled | Y66: Unpaid | Z66: INV/2026/0104 | AA66: Web | AB66: 1st quarter | AC66: Apr | AD66: 2026 | AE66: 15 | AF66: 41 | AG66: 8 | AJ66: 48.82 | AK66: FedEx | AL66: DH627617812 | AM66: 17,98 | AN66: wh b | AO66: 284 | AP66: 2 | AR66: 1 | AS66: damaged | AT66: 15 % | AV66: John Anderson | AW66: same | AX66: urgent
A67: TR-2025055 | B67: 20260108 | C67: 16.01.2026 | D67: P-032 | E67: #N/A | F67: - | G67: 2 kom | H67: 1479.77 USD | I67: 0 | J67: N/A | K67: usd | L67: E009 | M67: Olivia Wilson | N67: North | O67: BOSTON | P67: Stark inc | Q67: 691518047 | R67: jessica.gmail.com | S67: 295.844.3940 | T67: 130 Jones Street | U67: 12023 | V67: USA | W67: Credit Card | X67: Delivered | Y67: Unpaid | Z67: INV/2026/0055 | AA67: Web | AB67: Q1 | AC67: January | AD67: 2026 | AE67: Net 30 | AF67: - | AG67: 0,08 | AJ67: 18.03 USD | AK67: ups | AL67: FX371992882 | AM67: 0,83 | AN67: WH-A | AO67: 84 | AP67: 3 | AQ67: complaint | AR67: Yes | AU67: 88,79 | AV67: Jessica Taylor | AW67: Jessica Taylor | AX67: VIP customer
A68: TR-2025056 | B68: 12.12.2025. | C68: 2025-12-21 | D68: P-029 | E68: Keyboard Plus 29 | F68: SOFTWARE | G68: 26 kom. | H68: 1375.64 | I68: 0.1 | J68: USD 35,767 | K68: EUR | L68: e-001 | M68: Sarah Wilson | N68: West | O68: seattle | P68: Vortex Inc. | Q68: EIN: 789866266 | R68: robert.company.com | S68: +1 481 284 9061 | T68: 780 Johnson Blvd | U68: 39546 | V68: usa | W68: PayPal | X68: Delivered | Y68: Paid | Z68: INV/2025/0056 | AA68: online | AB68: q1 | AC68: 12 | AD68: 2025 | AE68: Net 60 | AF68: 14 | AG68: 8 | AJ68: 22.09 | AK68: FedEx | AL68: DH582009372 | AM68: 14,87 | AN68: Warehouse B | AO68: 109 | AP68: 5 | AQ68: late delivery!! | AR68: 1 | AS68: damaged | AT68: 0,18 | AU68: 1073,00 | AV68: Robert Williams | AX68: VIP customer
A69: TR-2025057 | B69: 20260215 | C69: 20.02.2026 | D69: P_042 | E69: Desk Max 42 | F69: Electronics | G69: 31 | H69: 158.06 | I69: 5% | J69: null | K69: USD | L69: E011 | M69: N/A | N69: West | O69: Seattle | P69: Wayne INC | Q69: 276355873 | R69: emily.yahoo.com | S69: 827.509.2033 | T69: 393 Taylor Blvd | U69: 28818 | V69: usa | W69: Cash | X69: Pending | Y69: Paid | Z69: INV/2026/0057 | AA69: Phone | AB69: q1 | AC69: Feb | AD69: 2026 | AE69: immediate | AF69: 67 | AG69: 0.08 | AJ69: 8.02 | AK69: UPS | AL69: FX280115051 | AM69: 27.0 kg | AN69: Warehouse C | AO69: 188 | AQ69: complaint | AS69: damaged | AT69: 0,18 | AU69: $147.00 | AV69: Emily Smith | AW69: same | AX69: VIP customer
A70: TR-2025058 | B70: 12/05/2025 | C70: 09-Dec-25 | D70: P38 | E70: Cable Max 38 | F70: Electronics | G70: 37 | H70: $687.68 | I70: 0.1 | J70: N/A | K70: EUR | L70: E010 | M70: Olivia Anderson | N70: South | O70: houston | P70: INITECH INC. | Q70: 828226053 | R70: #N/A | S70: 727.625.6734 | T70: 604 Taylor St. | U70: 02712 | V70: US | W70: credit card | X70: Delivered | Y70: paid | Z70: INV/2025/0058 | AA70: Online | AB70: 1st quarter | AC70: Dec | AD70: '25 | AE70: Net 60 | AF70: 86 | AG70: 8 | AJ70: 49.63 | AK70: USPS | AL70: FX218650855 | AM70: 26.8 kg | AN70: Warehouse B | AO70: 445 | AP70: 1 | AR70: yes | AS70: doesn't fit | AT70: 15 % | AU70: 763.32 | AV70: Robert Williams | AX70: duplicate?
A71: TR-2025059 | B71: 2025-06-11 | C71: 16.06.2025. | D71: P-010 | F71: equipment | G71: 10 | H71: 1225.11 USD | I71: 10 | J71: USD 12,251 | K71: USD | L71: e-006 | N71: NORTH | O71: LA | P71: vortex inc. | Q71: EIN: 195399847 | R71: emily.company.com | S71: (972) 515-2215 | T71: 313 Davis Ave | U71: 14915 | V71: usa | W71: credit card | X71: DELIVERED | Y71: Paid | Z71: INV/2025/0059 | AA71: Phone | AB71: Q1 | AC71: Jun | AD71: '25 | AE71: 15 | AF71: 80 | AG71: 0.08 | AJ71: null | AK71: USPS | AL71: DH869629458 | AM71: 5.82 | AN71: wh b | AO71: 132 | AP71: 2 | AQ71: all good | AR71: yes | AT71: 0,18 | AU71: 367.53 | AV71: emily anderson | AX71: check price
A72: TR-2025060 | B72: 05.12.2025 | C72: 08.12.2025 | D72: P_016 | E72: keyboard x 16 | F72: Office | G72: 3 kom. | H72: $127.37 | J72: 382.11 USD | K72: usd | L72: e-009 | M72: N/A | N72: NORTH | O72: Los Angeles | P72: Wayne LLC | Q72: 357724330 | R72: james.company.com | S72: +1 912 575 7662 | T72: 449 Williams Street | U72: 18304 | V72: usa | W72: credit card | X72: Pending | Y72: paid | Z72: INV/2025/0060 | AA72: Store | AB72: Q4 | AC72: 12 | AD72: 2025 | AE72: immediate | AF72: 11 | AG72: 8% | AJ72: 7.65 USD | AK72: UPS | AL72: DH441786172 | AM72: 16,82 | AN72: wh b | AO72: 496 | AP72: 4.5 | AQ72: all good | AR72: Yes | AS72: doesn't fit | AT72: 0,18 | AU72: USD 11 | AV72: JAMES DAVIS | AW72: same | AX72: duplicate?
A73: TR-2025061 | B73: 2026-05-30 | C73: 31.05.2026. | D73: P-018 | E73: License Basic 18 | F73: equipment | G73: 33 kom | H73: $1,470.36 | I73: 0 | J73: 48521.88 | K73: USD | L73: EMP22 | M73: Chris Williams | N73: west | O73: los angeles | P73: UMBRELLA LTD. | Q73: EIN: 351046051 | R73: john.company.com | S73: +1 910 217 5469 | T73: 420 Smith Blvd | U73: 80736 | V73: United States | W73: credit card | X73: Processing | Y73: Unpaid | Z73: INV/2026/0061 | AA73: Phone | AB73: Q1 | AC73: May | AD73: '26 | AE73: 15 | AF73: N/A | AG73: 0.08 | AJ73: 44.82 | AK73: UPS | AL73: FX571642340 | AM73: 4,7 | AN73: WH-A | AO73: 364 | AP73: 5 | AR73: 0 | AT73: 0.3 | AU73: 1455.66 | AV73: John Davis | AW73: John Davis
A74: TR-2025062 | B74: 27-Mar-26 | C74: 30-Mar-26 | D74: P-058 | E74: Laptop Pro 58 | F74: Furniture | G74: 26 | H74: $711.00 | I74: 0 | J74: 18486.00 USD | K74: usd | L74: e-009 | M74: null | N74: East | O74: BOSTON | P74: Acme LLC | Q74: 231363363 | R74: olivia.yahoo.com | S74: (626) 571-1252 | T74: 342 Anderson St. | U74: 50441 | V74: U.S. | W74: wire | X74: Processing | Y74: Unpaid | Z74: INV/2026/0062 | AA74: Phone | AB74: Q4 | AC74: March | AD74: 2026 | AE74: Net 30 | AF74: 6 | AG74: 8 | AJ74: 11,39 | AK74: DHL | AL74: FX688786933 | AM74: 4.9 kg | AN74: wh b | AO74: 480 | AP74: 2 | AQ74: late delivery!! | AR74: yes | AT74: 25% | AV74: olivia jones | AX74: check price
A75: TR-2025063 | B75: 06/23/2025 | C75: 07.07.2025. | D75: P-034 | E75: Mouse X 34 | F75: null | G75: 33 kom | H75: 23,03 | I75: 5% | J75: 759.99 | K75: USD | L75: E012 | M75: N/A | N75: West | O75: NY | P75: Acme inc | Q75: EIN: 276734200 | R75: robert.company.com | S75: (585) 424-6255 | T75: 555 Williams Street | U75: 85572 | V75: US | W75: Cash | X75: Pending | Y75: YES | Z75: INV/2025/0063 | AA75: Web | AB75: Q4 | AC75: Jun | AD75: 2025 | AE75: Net 60 | AF75: 37 | AG75: 0,08 | AJ75: 35.83 | AK75: Fed Ex | AL75: FX431436898 | AM75: 29,21 | AN75: WH-A | AO75: 343 | AP75: 5/5 | AQ75: satisfied | AR75: NO | AS75: damaged | AU75: USD 23 | AV75: robert wilson | AW75: Robert Wilson | AX75: duplicate?
A76: TR-2025064 | B76: 09.06.2026 | C76: 10.06.2026. | D76: P-060 | E76: DESK BASIC 60 | F76: electronics | G76: 10 | H76: $334.59 | I76: 10% | J76: 3345.90 | K76: USD | L76: E023 | M76: laura anderson | N76: North | O76: Seattle | P76: Globex Ltd. | Q76: 401652263 | R76: david.gmail.com | S76: +1 877 765 8930 | T76: 717 Taylor Blvd | U76: 50373 | V76: usa | W76: credit card | X76: delivered | Y76: Unpaid | Z76: INV/2026/0064 | AA76: Store | AB76: Q4 | AC76: Jun | AD76: 2026 | AE76: 15 | AF76: 88 | AG76: 8% | AJ76: 11,20 | AK76: UPS | AL76: FX647444829 | AM76: 18,76 | AN76: Warehouse B | AO76: 205 | AP76: 5/5 | AQ76: OK | AR76: 0 | AS76: wrong item | AT76: 0,18 | AU76: 100,38 | AV76: David Johnson | AW76: same | AX76: check price
A77: TR-2025065 | B77: 28-Sep-25 | C77: 08.10.2025. | D77: P37 | E77: Headphones Basic 37 | F77: N/A | G77: 23 kom | H77: 1037.29 | I77: 5% | J77: 23857.67 | K77: USD | L77: E004 | M77: Sophia Johnson | N77: South | O77: Chicgo | P77: umbrella inc | Q77: EIN: 566010774 | R77: daniel.yahoo.com | S77: +1 365 686 9809 | T77: 857 Johnson Street | U77: 27114 | V77: U.S. | W77: Credit Card | X77: DELIVERED | Y77: Partial | Z77: INV/2025/0065 | AA77: Web | AB77: 1st quarter | AC77: Sep | AD77: '25 | AE77: 15 | AF77: - | AG77: 0.08 | AJ77: 5.22 USD | AK77: USPS | AL77: 1Z842246470 | AM77: 9.28 | AN77: Warehouse A | AO77: 429 | AP77: 1 | AQ77: all good | AR77: NO | AT77: 25% | AV77: daniel johnson | AW77: Daniel | AX77: urgent
A78: TR-2025066 | B78: 20260228 | C78: 02-Mar-26 | D78: P-024 | E78: Chair Plus 24 | F78: null | G78: 15 kom. | H78: 95.7 | I78: 5% | J78: 1435,50 | K78: USD | L78: EMP8 | M78: michael williams | N78: West | O78: New York | P78: Acme inc | Q78: 363185602 | R78: sophia.gmail.com | S78: +1 465 842 8999 | T78: 838 Williams Ave | U78: 57889 | V78: US | W78: credit card | X78: Pending | Y78: Partial | Z78: INV/2026/0066 | AA78: Online | AB78: Q4 | AC78: February | AD78: 2026 | AE78: immediate | AF78: 56 | AG78: 0,08 | AK78: UPS | AL78: 1Z948967854 | AM78: 8.93 | AN78: Warehouse A | AO78: 46 | AP78: 2 | AQ78: late delivery!! | AR78: No | AS78: damaged | AT78: 0,18 | AU78: 43,06 | AV78: Sophia Smith | AW78: Sophia | AX78: check price
A79: TR-2025067 | B79: 01/28/2026 | C79: 20260205 | D79: P-032 | F79: Software | G79: 28 kom. | H79: 1479.77 USD | I79: 0.1 | J79: 41.433,56 | K79: usd | L79: E015 | N79: west | O79: New York | P79: UMBRELLA INC | Q79: EIN: 729349177 | R79: ryan.company.com | S79: +1 508 718 1316 | T79: 91 Smith Street | U79: 20806 | V79: USA | W79: Credit Card | X79: DELIVERED | Y79: paid | Z79: INV/2026/0067 | AA79: online | AB79: Q3 | AC79: 1 | AD79: 2026 | AE79: Net 60 | AF79: 53 | AG79: 0,08 | AJ79: 15.64 | AK79: FedEx | AL79: DH804734710 | AM79: 12.31 | AN79: wh b | AO79: 32 | AP79: 4 | AQ79: satisfied | AR79: 1 | AS79: damaged | AU79: #N/A | AV79: RYAN BROWN | AX79: duplicate?
A80: TR-2025068 | B80: 13.06.2026. | C80: 27.06.2026. | D80: P6 | E80: Monitor X 6 | F80: Equipment | G80: 22 kom | H80: 1421.82 USD | I80: 5% | J80: null | K80: usd | L80: E004 | M80: SOPHIA JOHNSON | N80: South | O80: Huston | P80: Acme inc | Q80: 960141080 | R80: sarah.yahoo.com | S80: (741) 903-7874 | T80: 384 Taylor Ave | U80: 53736 | V80: usa | W80: wire | X80: Cancelled | Y80: paid | Z80: INV/2026/0068 | AA80: Phone | AB80: q1 | AC80: Jun | AD80: 2026 | AE80: immediate | AF80: 4 | AG80: 0,08 | AJ80: 34.15 | AK80: Fed Ex | AL80: FX939150328 | AM80: 23.6 kg | AN80: Warehouse C | AO80: 188 | AP80: 3 | AQ80: complaint | AT80: 0,18 | AU80: null | AV80: Sarah Miller | AW80: same | AX80: urgent
A81: TR-2025069 | B81: 08/18/2025 | C81: 22-Aug-25 | D81: P-046 | E81: chair basic 46 | F81: Equipment | G81: 22 | H81: USD 549 | J81: 12087.24 | K81: usd | L81: E018 | M81: john miller | N81: North | O81: Miami FL | P81: INITECH INC. | Q81: 846787451 | R81: sophia.yahoo.com | S81: 395.292.6502 | T81: 445 Brown Ave | U81: 75285 | V81: USA | W81: wire | X81: Processing | Y81: YES | Z81: INV/2025/0069 | AA81: Online | AB81: Q1 | AC81: August | AD81: 2025 | AE81: Net 60 | AF81: 84 | AG81: 8 | AJ81: USD 39 | AK81: ups | AL81: DH441134063 | AM81: 27.61 | AN81: WH-A | AO81: 380 | AP81: 3 | AQ81: all good | AR81: NO | AU81: 362.62 | AV81: Sophia Jones | AW81: Sophia Jones | AX81: urgent
A82: TR-2025070 | B82: 28-Jun-25 | C82: 10-Jul-25 | D82: P-053 | E82: Monitor Basic 53 | F82: equipment | G82: 5 | H82: #N/A | I82: 0.1 | J82: 2.766,10 | K82: USD | L82: E002 | M82: SARAH WILSON | N82: west | O82: Huston | P82: Acme Inc. | Q82: EIN: 511809674 | R82: emily.yahoo.com | S82: 703.300.7625 | T82: 105 Wilson Blvd | U82: 67143 | V82: USA | W82: PayPal | X82: DELIVERED | Y82: Partial | Z82: INV/2025/0070 | AA82: Store | AB82: Q1 | AC82: Jun | AD82: 2025 | AE82: Net 60 | AF82: 85 | AG82: 8 | AJ82: 44,76 | AK82: ups | AL82: FX211131300 | AM82: 22.9 kg | AN82: Warehouse B | AO82: 278 | AP82: excellent | AQ82: satisfied | AR82: 1 | AU82: USD 83 | AV82: Emily Wilson | AW82: Emily | AX82: check price
A83: TR-2025071 | B83: 20250216 | C83: 28.02.2025 | D83: p041 | E83: MONITOR X 41 | F83: Software | G83: 19 kom | H83: 247,64 | I83: 5% | J83: 4705.16 USD | K83: USD | L83: e-018 | M83: #N/A | N83: South | O83: seattle | P83: Globex inc | Q83: EIN: 390686616 | R83: daniel.gmail.com | S83: (367) 200-7507 | T83: 389 Williams Ave | U83: 72013 | V83: U.S. | W83: Credit Card | X83: Cancelled | Y83: YES | Z83: INV/2025/0071 | AA83: Web | AB83: Q2 | AC83: 2 | AD83: 2025 | AE83: 15 | AF83: 39 | AG83: 8% | AJ83: 2.71 USD | AK83: Fed Ex | AL83: FX780466790 | AM83: 15.7 | AN83: WH-A | AO83: 160 | AP83: excellent | AR83: NO | AS83: doesn't fit | AU83: $141.15 | AV83: Daniel Smith | AW83: same | AX83: urgent
A84: TR-2025072 | B84: 01/21/2025 | C84: 27.01.2025 | D84: P-045 | E84: #N/A | F84: #N/A | G84: 8 | H84: 227,08 | I84: 0 | J84: 1816.64 | K84: USD | L84: E023 | M84: LAURA ANDERSON | N84: West | O84: Seatle | P84: Vortex Inc. | Q84: 236601477 | R84: sarah.yahoo.com | S84: 655.489.4073 | T84: 815 Wilson Ave | U84: 50787 | V84: USA | W84: Credit Card | X84: Cancelled | Y84: Paid | Z84: INV/2025/0072 | AA84: online | AB84: Q2 | AC84: January | AD84: 2025 | AE84: immediate | AF84: 33 | AG84: 0,08 | AJ84: 25.10 USD | AK84: DHL | AL84: FX304889068 | AM84: 14.5 kg | AN84: wh b | AO84: 328 | AP84: 2 | AQ84: OK | AR84: 0 | AT84: 0.3 | AU84: USD 54 | AV84: sarah jones | AW84: Sarah | AX84: duplicate?
A85: TR-2025073 | B85: 06/27/2025 | C85: 11.07.2025. | D85: P40 | E85: #N/A | F85: N/A | G85: 33 kom | H85: USD 98 | I85: 0.1 | J85: 3235,98 | K85: USD | L85: E005 | M85: #N/A | N85: west | O85: CHICAGO | P85: Umbrella Inc. | Q85: EIN: 644652046 | R85: sophia.yahoo.com | S85: (522) 705-8311 | T85: 58 Miller Ave | U85: 11313 | V85: US | W85: Wire Transfer | X85: Processing | Y85: Partial | Z85: INV/2025/0073 | AA85: online | AB85: Q2 | AC85: Jun | AD85: 2025 | AE85: Net 30 | AF85: N/A | AG85: 8% | AJ85: 19,02 | AK85: UPS | AL85: FX171869367 | AM85: 4.33 | AN85: Warehouse A | AO85: 40 | AP85: 1 | AQ85: complaint | AR85: 0 | AS85: wrong item | AT85: 0.3 | AU85: $97.08 | AV85: sophia smith | AX85: urgent
A86: TR-2025074 | B86: 20260207 | C86: 12.02.2026. | D86: P-039 | E86: Cable Plus 39 | F86: SOFTWARE | G86: 36 kom | H86: $601.47 | J86: N/A | K86: $ | L86: E023 | N86: NORTH | O86: Miami | P86: Initech inc | Q86: EIN: 438265607 | R86: emily.gmail.com | S86: +1 701 237 8693 | T86: 797 Smith Ave | U86: 39289 | V86: US | W86: PayPal | X86: Cancelled | Y86: NO | Z86: INV/2026/0074 | AA86: online | AB86: Q4 | AC86: 2 | AD86: 2026 | AE86: immediate | AF86: N/A | AG86: 0.08 | AJ86: 19.91 | AK86: UPS | AL86: DH307392880 | AM86: 17.37 | AN86: Warehouse B | AO86: 384 | AP86: 2 | AQ86: late delivery!! | AR86: Yes | AS86: doesn't fit | AU86: $649.59 | AV86: Emily Brown | AX86: check price
A87: TR-2025075 | B87: 14-Jan-25 | C87: - | D87: P43 | E87: HEADPHONES X 43 | F87: EQUIPMENT | G87: 22 | H87: 156,69 | I87: 10 | J87: $3,447.18 | K87: EUR | L87: E024 | M87: Robert Smith | N87: west | O87: Los Angles | P87: Vortex INC | Q87: 205902968 | R87: null | S87: (443) 333-9775 | T87: 682 Brown Blvd | U87: 68855 | V87: US | W87: Credit Card | X87: Pending | Y87: Unpaid | Z87: INV/2025/0075 | AA87: Online | AB87: Q1 | AC87: January | AD87: 2025 | AE87: Net 30 | AF87: null | AG87: 0,08 | AJ87: 47.68 | AK87: DHL | AL87: 1Z503745264 | AM87: 6.6 kg | AN87: Warehouse A | AO87: 477 | AP87: excellent | AQ87: all good | AR87: 1 | AS87: damaged | AT87: 25% | AU87: USD 103 | AV87: sarah miller | AW87: Sarah Miller | AX87: VIP customer
A88: TR-2025305 | B88: 03.06.2026 | C88: 2026-06-08 | D88: P_038 | E88: N/A | F88: electronics | G88: 3 kom | H88: 687.68 | I88: 0.1 | J88: 2.063,04 | K88: usd | L88: E006 | M88: Emily Davis | N88: East | O88: NY | P88: Acme LLC | Q88: EIN: 224975322 | R88: john.yahoo.com | S88: (609) 585-5922 | T88: 965 Smith Blvd | U88: 74151 | V88: U.S. | W88: Wire Transfer | X88: Pending | Y88: Partial | Z88: INV/2026/0305 | AA88: Store | AB88: q1 | AC88: 6 | AD88: 2026 | AE88: 15 | AF88: 87 | AG88: 8 | AJ88: 24.6 | AK88: DHL | AL88: FX287036854 | AM88: 3,97 | AN88: wh b | AO88: 374 | AP88: 3 | AR88: 1 | AS88: doesn't fit | AT88: 0,18 | AU88: 61,89 | AV88: John Williams | AW88: John | AX88: VIP customer
A89: TR-2025076 | B89: 18.08.2025. | C89: 20250830 | D89: P-050 | E89: LICENSE X 50 | F89: Equipment | G89: 7 | H89: 39,53 | I89: 10% | J89: 276,71 | K89: EUR | L89: E024 | N89: NORTH | O89: Boston | P89: ACME INC | Q89: EIN: 809377576 | R89: jessica.yahoo.com | S89: 339.672.4395 | T89: 884 Brown St. | U89: null | V89: United States | W89: credit card | X89: Cancelled | Y89: Partial | Z89: INV/2025/0076 | AA89: Store | AB89: Q1 | AC89: August | AD89: 2025 | AE89: Net 30 | AF89: 64 | AG89: 8% | AJ89: 24,92 | AK89: USPS | AL89: 1Z535082081 | AM89: 20.89 | AN89: Warehouse C | AO89: 206 | AP89: 3 | AQ89: satisfied | AR89: yes | AS89: damaged | AT89: 0.3 | AU89: #N/A | AV89: Jessica Williams | AW89: same | AX89: duplicate?
A90: TR-2025077 | B90: 17.01.2025 | C90: #N/A | D90: P-014 | E90: License Max 14 | F90: null | G90: 22 kom. | H90: 1166.96 USD | I90: 10% | J90: $25,673.12 | K90: usd | L90: EMP5 | M90: - | N90: West | O90: NY | P90: Globex Inc. | Q90: 834490030 | R90: sarah.company.com | S90: (207) 705-7898 | T90: 443 Brown Ave | U90: 68805 | V90: usa | W90: Cash | X90: Processing | Y90: Unpaid | Z90: INV/2025/0077 | AA90: online | AB90: Q1 | AC90: January | AD90: 2025 | AE90: Net 60 | AF90: 14 | AG90: 8 | AJ90: 8.75 | AK90: Fed Ex | AL90: DH116486037 | AM90: 1.6 kg | AN90: Warehouse B | AO90: 465 | AP90: 4 | AQ90: complaint | AR90: 0 | AU90: $770.19 | AV90: Sarah Miller | AW90: Sarah Miller | AX90: urgent
A91: TR-2025078 | B91: 28-Apr-25 | C91: 2025-05-10 | D91: P-012 | E91: Keyboard Basic 12 | F91: Electronics | G91: 38 | H91: 823,88 | I91: 0.1 | J91: 31.307,44 | K91: $ | L91: E012 | M91: John Smith | N91: West | O91: Chicago | P91: Globex Inc. | Q91: EIN: 288109254 | R91: sophia.gmail.com | S91: +1 375 513 9778 | T91: 261 Anderson Ave | U91: 59544 | V91: US | W91: Cash | X91: Processing | Y91: NO | Z91: INV/2025/0078 | AA91: Phone | AB91: q1 | AC91: Apr | AD91: 2025 | AE91: 15 | AF91: N/A | AG91: 0.08 | AJ91: 8.67 USD | AK91: ups | AL91: FX525665926 | AM91: 1,55 | AN91: Warehouse B | AO91: 90 | AP91: 4.5 | AQ91: late delivery!! | AR91: 0 | AU91: $939.22 | AV91: SOPHIA WILSON | AW91: Sophia | AX91: duplicate?
A92: TR-2025079 | B92: 07/31/2025 | C92: 20250801 | D92: P-034 | E92: mouse x 34 | F92: Office | G92: 12 kom | H92: 23.03 | I92: 5% | J92: 276.36 | K92: EUR | L92: E020 | M92: Robert Taylor | N92: West | O92: Los Angles | P92: wayne ltd. | Q92: EIN: 466401441 | R92: daniel.gmail.com | S92: 766.504.2651 | T92: 204 Anderson Ave | U92: 37975 | V92: U.S. | W92: Credit Card | X92: delivered | Y92: Paid | Z92: INV/2025/0079 | AA92: Online | AB92: Q3 | AC92: July | AD92: 2025 | AE92: 15 | AF92: 83 | AG92: 0.08 | AJ92: 12,39 | AK92: USPS | AL92: DH648304435 | AM92: 26,88 | AN92: WH-A | AO92: 15 | AP92: 4.5 | AQ92: satisfied | AR92: yes | AT92: 15 % | AU92: 8.29 | AV92: Daniel Miller | AW92: Daniel Miller | AX92: check price
A93: TR-2025080 | B93: 01/27/2025 | C93: 20250210 | D93: P_054 | E93: - | F93: Office | G93: 4 kom | H93: USD 801 | I93: 0.1 | J93: - | K93: USD | L93: EMP5 | M93: null | N93: NORTH | O93: BOSTON | P93: Globex inc | Q93: EIN: 452526338 | S93: 348.966.5480 | T93: 128 Miller Ave | U93: 45997 | V93: usa | W93: Wire Transfer | X93: Pending | Y93: Paid | Z93: INV/2025/0080 | AA93: Store | AB93: 1st quarter | AC93: January | AD93: '25 | AE93: Net 30 | AF93: 40 | AG93: 0.08 | AJ93: 35,56 | AK93: UPS | AL93: DH696226436 | AM93: 17.76 | AN93: Warehouse B | AO93: 321 | AP93: 4 | AR93: yes | AT93: 25% | AU93: 96.15 USD | AV93: chris williams | AW93: Chris Williams | AX93: urgent
A94: TR-2025081 | B94: 20250416 | C94: 2025-04-17 | D94: P-059 | E94: Keyboard Max 59 | F94: Furniture | G94: 9 kom. | H94: USD 674 | I94: 10% | J94: 6062.49 USD | K94: $ | L94: EMP8 | M94: #N/A | N94: South | O94: seattle | P94: Wayne Ltd. | Q94: 668157470 | R94: daniel.company.com | S94: 209.545.8832 | T94: 849 Davis Ave | U94: 75301 | V94: usa | W94: Credit Card | X94: Delivered | Y94: Partial | Z94: INV/2025/0081 | AA94: Online | AB94: Q1 | AC94: Apr | AD94: 2025 | AE94: Net 60 | AF94: 29 | AG94: 8 | AJ94: USD 32 | AK94: DHL | AL94: FX722826456 | AM94: 10,47 | AN94: WH-A | AO94: 422 | AP94: excellent | AS94: damaged | AT94: 0,18 | AU94: 181,87 | AV94: Daniel Wilson | AW94: same | AX94: urgent
A95: TR-2025082 | B95: 24-Jan-25 | C95: 20250129 | D95: P-015 | E95: License Max 15 | F95: Software | G95: 18 | H95: 545.57 | J95: null | K95: USD | L95: E011 | M95: Michael Taylor | N95: North | O95: Huston | P95: ACME LTD. | Q95: 741744300 | R95: david.yahoo.com | S95: 803.264.8564 | T95: 751 Miller St. | U95: 66781 | V95: United States | W95: credit card | X95: Cancelled | Y95: YES | Z95: INV/2025/0082 | AA95: Store | AB95: 1st quarter | AC95: January | AD95: '25 | AE95: Net 30 | AF95: 9 | AG95: 0.08 | AJ95: 34.81 | AK95: DHL | AL95: DH862273622 | AM95: 28.41 | AN95: Warehouse B | AO95: - | AP95: 5 | AR95: Yes | AT95: 15 % | AU95: null | AV95: David Smith | AX95: check price
A96: TR-2025083 | B96: 03/21/2025 | C96: 03/30/2025 | D96: P-007 | E96: Headphones Max 7 | F96: Software | G96: 30 | H96: 79,14 | I96: 5% | J96: USD 2,374 | K96: USD | L96: E005 | M96: null | N96: South | O96: Seattle | P96: globex ltd. | Q96: 868666386 | R96: laura.gmail.com | S96: +1 261 641 5316 | T96: 215 Johnson St. | U96: 15111 | V96: USA | W96: Wire Transfer | X96: DELIVERED | Y96: Paid | Z96: INV/2025/0083 | AA96: Store | AB96: Q2 | AC96: March | AD96: 2025 | AE96: 15 | AF96: 51 | AG96: 0,08 | AJ96: 16.20 USD | AK96: DHL | AL96: 1Z829609521 | AM96: 18.85 | AN96: Warehouse A | AO96: 382 | AP96: 5/5 | AQ96: complaint | AR96: NO | AT96: 15 % | AU96: 71.23 | AV96: Laura Brown | AW96: Laura | AX96: VIP customer
A97: TR-2025084 | B97: 10/22/2025 | C97: 2025-10-28 | D97: P-012 | E97: keyboard basic 12 | F97: Electronics | G97: 7 | H97: 823,88 | I97: 5% | J97: - | K97: USD | L97: E015 | M97: sarah jones | N97: west | O97: Boston | P97: Stark INC | Q97: 301779581 | R97: ryan.gmail.com | S97: (552) 623-6330 | T97: 965 Brown Ave | U97: 98548 | V97: U.S. | W97: Credit Card | X97: Delivered | Y97: NO | Z97: INV/2025/0084 | AA97: Store | AB97: Q1 | AC97: Oct | AD97: '25 | AE97: Net 30 | AF97: 3 | AG97: 8 | AJ97: 48.70 USD | AK97: ups | AL97: FX117761864 | AM97: 27.55 | AN97: Warehouse C | AO97: 18 | AQ97: late delivery!! | AS97: damaged | AT97: 15 % | AU97: - | AV97: Ryan Anderson | AW97: Ryan Anderson | AX97: duplicate?
A98: TR-2025085 | B98: 07-May-26 | C98: 09.05.2026. | D98: P_027 | E98: Desk X 27 | F98: EQUIPMENT | G98: 6 | H98: 180,06 | I98: 0 | J98: N/A | K98: usd | L98: e-004 | M98: #N/A | N98: West | O98: Miami | P98: Initech Inc. | Q98: 658482290 | R98: chris.yahoo.com | S98: 242.546.7353 | T98: 236 Davis Blvd | U98: 11069 | V98: USA | W98: Cash | X98: DELIVERED | Y98: Paid | Z98: INV/2026/0085 | AA98: Phone | AB98: Q1 | AC98: May | AD98: 2026 | AE98: Net 30 | AF98: N/A | AG98: 0,08 | AJ98: USD 31 | AK98: UPS | AL98: FX259516665 | AM98: 19.3 | AN98: wh b | AO98: 135 | AR98: 1 | AS98: damaged | AT98: 0,18 | AU98: - | AV98: Chris Johnson
A99: TR-2025086 | B99: 2025-05-10 | C99: - | D99: P47 | E99: Monitor Pro 47 | F99: Software | G99: 8 | H99: 1489,69 | I99: 0 | J99: 11917,52 | K99: USD | L99: e-018 | M99: JOHN MILLER | N99: west | O99: new york | P99: VORTEX INC. | Q99: EIN: 105590612 | R99: sarah.gmail.com | S99: (889) 394-7192 | T99: 908 Johnson St. | U99: 59238 | V99: US | W99: wire | X99: Cancelled | Y99: Unpaid | Z99: INV/2025/0086 | AA99: Web | AB99: 1st quarter | AC99: May | AD99: '25 | AE99: Net 30 | AF99: 86 | AG99: 0.08 | AJ99: 19.09 | AK99: DHL | AL99: 1Z274782453 | AM99: 19,24 | AN99: WH-A | AO99: 268 | AP99: 4 | AQ99: OK | AT99: 0,18 | AU99: #N/A | AV99: SARAH WILLIAMS | AW99: Sarah Williams | AX99: urgent
A100: TR-2025087 | B100: 27.06.2026. | C100: 10.07.2026 | D100: P5 | E100: cable plus 5 | F100: Electronics | G100: 2 | H100: 1241.14 USD | I100: 0 | J100: 2482.28 USD | K100: USD | L100: EMP19 | M100: Sophia Taylor | N100: west | O100: New Yrok | P100: stark ltd. | Q100: EIN: 543403500 | R100: daniel.company.com | S100: +1 927 885 9118 | T100: 367 Taylor Street | U100: 86659 | V100: U.S. | W100: Cash | X100: Processing | Y100: Paid | Z100: INV/2026/0087 | AA100: Phone | AB100: Q2 | AC100: 6 | AD100: 2026 | AE100: 15 | AF100: 56 | AG100: 0.08 | AJ100: $23.90 | AK100: ups | AL100: DH243395740 | AM100: 18.8 kg | AN100: Warehouse B | AO100: 76 | AP100: 5/5 | AQ100: late delivery!! | AR100: 0 | AS100: wrong item | AU100: 74,47 | AV100: DANIEL JOHNSON | AW100: same | AX100: VIP customer
A102: TR-2025088 | B102: 20250514 | C102: 24.05.2025. | D102: p022 | E102: Desk Basic 22 | F102: FURNITURE | G102: 29 kom | H102: USD 894 | I102: 0.1 | J102: N/A | K102: usd | L102: E013 | M102: N/A | N102: west | O102: Boston | P102: Stark Inc. | Q102: 374562596 | R102: olivia.gmail.com | S102: (302) 565-9064 | T102: 935 Wilson St. | U102: 07528 | V102: US | W102: wire | X102: Cancelled | Y102: YES | Z102: INV/2025/0088 | AA102: Web | AB102: q1 | AC102: May | AD102: 2025 | AE102: immediate | AF102: - | AG102: 0,08 | AJ102: 25,45 | AK102: FedEx | AL102: FX738455583 | AM102: 25.6 | AN102: WH-A | AO102: 315 | AQ102: all good | AR102: yes | AT102: 0,18 | AU102: 777,41 | AV102: Olivia Anderson | AW102: Olivia Anderson | AX102: check price
A103: TR-2025089 | B103: 2025-08-24 | C103: 28.08.2025. | D103: p030 | E103: License Pro 30 | F103: Office | G103: 17 | H103: 676.54 USD | I103: 10% | J103: 11501.18 | K103: USD | L103: e-003 | N103: west | O103: houston | P103: Initech Inc. | Q103: 234255914 | R103: laura.yahoo.com | S103: +1 535 907 2408 | T103: 54 Brown Ave | U103: 78974 | V103: USA | W103: Cash | X103: Processing | Y103: Paid | Z103: INV/2025/0089 | AA103: Phone | AB103: q1 | AC103: Aug | AD103: 2025 | AE103: Net 30 | AF103: 27 | AG103: 0,08 | AJ103: 0,24 | AK103: USPS | AL103: 1Z110516077 | AM103: 2.41 | AN103: Warehouse A | AO103: 48 | AP103: 4 | AQ103: satisfied | AT103: 0,18 | AU103: #N/A | AV103: Laura Williams | AW103: same
A104: TR-2025090 | B104: 04/20/2025 | C104: 28.04.2025 | D104: p006 | E104: MONITOR X 6 | F104: Equipment | G104: 17 kom | H104: 1421,82 | I104: 0 | J104: null | K104: $ | L104: EMP24 | M104: Robert Smith | N104: North | O104: CHICAGO | P104: STARK LLC | Q104: EIN: 513495468 | R104: emma.gmail.com | S104: (459) 339-5932 | T104: 877 Jones Ave | U104: 81877 | V104: United States | W104: credit card | X104: Cancelled | Y104: Unpaid | Z104: INV/2025/0090 | AA104: Web | AB104: Q1 | AC104: Apr | AD104: 2025 | AE104: Net 30 | AF104: 14 | AG104: 0.08 | AJ104: $42.92 | AK104: DHL | AL104: FX620596295 | AM104: 14,12 | AN104: Warehouse B | AQ104: OK | AR104: No | AS104: damaged | AT104: 0.3 | AV104: Emma Davis | AW104: same
A105: TR-2025091 | B105: 18.01.2026. | C105: 19.01.2026 | D105: P_026 | E105: Printer Basic 26 | F105: ELECTRONICS | G105: 25 | H105: $1,411.27 | I105: 5% | J105: USD 35,282 | K105: usd | L105: e-001 | M105: Sarah Wilson | N105: NORTH | O105: Seatle | P105: Wayne Ltd. | Q105: 908656028 | R105: olivia.yahoo.com | S105: +1 345 986 2726 | T105: 959 Miller Blvd | U105: 11652 | V105: US | W105: wire | X105: Pending | Y105: paid | Z105: INV/2026/0091 | AA105: Phone | AB105: Q3 | AC105: January | AD105: 2026 | AE105: Net 60 | AF105: 90 | AG105: 0.08 | AJ105: $45.93 | AK105: Fed Ex | AL105: 1Z269489121 | AM105: 11.0 kg | AN105: wh b | AO105: 497 | AP105: 5 | AR105: No | AU105: 1.058,45 | AV105: Olivia Johnson | AW105: Olivia | AX105: VIP customer
...

Sheet PivotChartRepCommission
A1: Row Labels | B1: Sum of Rep Commission
A2: E001 | B2: 7254.1719
A3: E002 | B3: 5397.9858
A4: E003 | B4: 6186.3912
A5: E004 | B5: 8268.362
A6: E005 | B6: 6276.0839
A7: E006 | B7: 8969.9147
A8: E007 | B8: 3689.322
A9: E008 | B9: 7027.1083
A10: E009 | B10: 8450.572
A11: E010 | B11: 4987.8695
A12: E011 | B12: 1180.6019
A13: E012 | B13: 4796.6891
... A27: Grand Total | B27: 136678.65

Sheet PivotChartDepartmentProfit
A1: Row Labels | B1: Sum of Profit
A2: Online | B2: 167469.84
A3: Retail | B3: 129231.36
A4: Sales | B4: 192890.22
A5: Wholesale | B5: 224800.04
A6: Grand Total | B6: 714391.45

Sheet PivotChartTrend
A1: Row Labels | B1: Sum of Profit
A2: January | B2: 66014.064
A3: February | B3: 73288.987
A4: March | B4: 74549.902
A5: April | B5: 55299.642
A6: May | B6: 74952.254
A7: June | B7: 94160.644
A8: July | B8: 88210.536
A9: August | B9: 70481.925
A10: September | B10: 31947.528
A11: October | B11: 24843.26
A12: November | B12: 29531.663
A13: December | B13: 31111.042
A14: Grand Total | B14: 714391.45

Sheet Sales_RAW(AFTER)
A4: Transaction ID | B4: Date | C4: Delivery Date | D4: Product Code | E4: Product Name | F4: Supplier | G4: Category | H4: Quantity | I4: Unit Price | J4: Discount % | K4: Total | L4: Currency | M4: Employee ID | N4: Sales Rep | O4: Department | P4: Region | Q4: City | R4: Customer | S4: Tax ID | T4: CUSTOMER EMAIL | U4: Phone | V4: Address | W4: ZIP Code | X4: Country | Y4: Payment Method | Z4: Status | AA4: Payment Status | AB4: Invoice No. | AC4: Sales Channel | AD4: Quarter | AE4: Month | AF4: Year | AG4: Payment Terms | AH4: Days Overdue | AI4: VAT | AJ4: VAT Amount | AK4: Amount incl. VAT | AL4: Shipping Cost | AM4: Courier | AN4: Tracking no. | AO4: Weight (KG) | AP4: Warehouse | AQ4: Stock | AR4: Customer Rating | AS4: Comment | AT4: Returned? | AU4: Return reason | AV4: Margin | AW4: Rep Commission | AX4: Customer Full Name | AY4: Contact Person | AZ4: Notes | BA4: Price With Discount | BB4: Warranty | BC4: Profit
A5: TR-2025001 | B5: 45909 | C5: 45923 | D5: ="P-" & TEXT(VALUE(SUBSTITUTE(SUBSTITUTE(SUBSTITUTE(UPPER(TRIM('Sales_RAW(BEFORE)'!D5)), "P", ""), "-", ""), "_", "")),"000") -> P-033 | E5: =PROPER(TRIM('Sales_RAW(BEFORE)'!E5)) -> Printer X 33 | F5: =_xlfn.XLOOKUP(E5,Product_List!$B$2:$B$61,Product_List!$E$2:$E$61,2) -> Global Distrib | G5: =VLOOKUP(E5,Product_List!$B$2:$C$61,2,FALSE) -> Office | H5: =SUBSTITUTE(SUBSTITUTE('Sales_RAW(BEFORE)'!G5,"kom",""),".","") -> 7 | I5: =VLOOKUP(E5,Product_List!$B$2:$D$61,3,FALSE) -> 129.06 | J5: =IF(IFERROR(VALUE(SUBSTITUTE(SUBSTITUTE(TRIM('Sales_RAW(BEFORE)'!I5), "%", ""), ",", ".")), 0) > 1, IFERROR(VALUE(SUBSTITUTE(SUBSTITUTE(TRIM('Sales_RAW(BEFORE)'!I5), "%", ""), ",", ".")), 0) / 100, IFERROR(VALUE(SUBSTITUTE(SUBSTITUTE(TRIM('Sales_RAW(BEFORE)'!I5), "%", ""), ",", ".")), 0)) -> 0.1 | K5: =IFERROR(H5*I5,0) -> 903.42 | L5: {=_xlfn.LET( _xlpm.valuta, UPPER(TRIM('Sales_RAW(BEFORE)'!K5)), _xlfn.IFS( _xlpm.valuta = "", "", OR(_xlpm.valuta = "USD", _xlpm.valuta = "$"), "$", OR(_xlpm.valuta = "EUR", _xlpm.valuta = "€"), "€", TRUE, _xlpm.valuta ) )} -> $ | M5: ="E" & TEXT(VALUE(SUBSTITUTE(SUBSTITUTE(SUBSTITUTE(UPPER(TRIM('Sales_RAW(BEFORE)'!L5)), "EMP", ""), "E", ""), "-", "")),"000") -> E016 | N5: =_xlfn.XLOOKUP(M5,Employees!$D$2:$D$26,Employees!$A$2:$A$26) -> Chris Anderson | O5: =_xlfn.XLOOKUP(N5,Employees!$A$2:$A$26,Employees!$C$2:$C$26,2) -> Online | P5: =PROPER('Sales_RAW(BEFORE)'!N5) -> East | Q5: =VLOOKUP(N5,Employees!$A$2:$B$26,2,FALSE) -> Chicago | R5: =PROPER('Sales_RAW(BEFORE)'!P5) -> Wayne Llc | S5: =SUBSTITUTE(SUBSTITUTE('Sales_RAW(BEFORE)'!Q5,"EIN",""),":","") -> 388875967 | T5: daniel.gmail.com | U5: (536) 760-6300 | V5: 344 Davis Street | W5: 63212 | X5: USA | Y5: =PROPER('Sales_RAW(BEFORE)'!W5) -> Credit Card | Z5: =PROPER('Sales_RAW(BEFORE)'!X5) -> Delivered | AA5: {=_xlfn.LET( _xlpm.val, TRIM(LOWER('Sales_RAW(BEFORE)'!Y5)), _xlfn.IFS( OR(_xlpm.val="yes", _xlpm.val="paid"), "Paid", OR(_xlpm.val="no", _xlpm.val="unpaid"), "Unpaid", OR(_xlpm.val="partial", _xlpm.val="partial paid"), "Partial", _xlpm.val="", "", TRUE, 'Sales_RAW(BEFORE)'!AY5 ) )} -> Paid | AB5: INV/2025/0001 | AC5: =PROPER('Sales_RAW(BEFORE)'!AA5) -> Online | AD5: =SUBSTITUTE(SUBSTITUTE(SUBSTITUTE(SUBSTITUTE('Sales_RAW(BEFORE)'!AB5,"st",""),"q",""),"Q",""),"uarter","") -> 1 | AE5: =TEXT(IFERROR(DATEVALUE('Sales_RAW(BEFORE)'!AC5 & " 1"), IFERROR(DATE(2025, 'Sales_RAW(BEFORE)'!AC5, 1), 'Sales_RAW(BEFORE)'!AC5)), "mmmm") -> September | AF5: =_xlfn.LET( _xlpm.raw, TRIM(SUBSTITUTE('Sales_RAW(BEFORE)'!AD5, "'", "")), _xlpm.num, IFERROR(VALUE(_xlpm.raw), 0), IF(_xlpm.num < 100, 2000 + _xlpm.num, _xlpm.num) ) -> 2025 | AG5: =PROPER('Sales_RAW(BEFORE)'!AE5) -> Immediate | AH5: {=_xlfn.LET( _xlpm.val, LOWER(TRIM('Sales_RAW(BEFORE)'!AF5)), _xlfn.IFS( OR(_xlpm.val="", _xlpm.val="null", _xlpm.val="N/A", _xlpm.val="-", _xlpm.val="#N/A"), 0, ISNUMBER('Sales_RAW(BEFORE)'!AF5), 'Sales_RAW(BEFORE)'!AF5, TRUE, IFERROR(_xlfn.NUMBERVALUE(_xlpm.val), 0) ) )} -> 0 | AI5: =IF(IFERROR(VALUE(SUBSTITUTE(SUBSTITUTE(TRIM('Sales_RAW(BEFORE)'!AG5), "%", ""), ",", ".")), 0) > 1, IFERROR(VALUE(SUBSTITUTE(SUBSTITUTE(TRIM('Sales_RAW(BEFORE)'!AG5), "%", ""), ",", ".")), 0) / 100, IFERROR(VALUE(SUBSTITUTE(SUBSTITUTE(TRIM('Sales_RAW(BEFORE)'!AG5), "%", ""), ",", ".")), 0)) -> 0.08 | AJ5: =K5*AI5 -> 72.2736 | AK5: =AJ5+K5 -> 975.6936 | AL5: =IFERROR(VALUE(SUBSTITUTE(SUBSTITUTE(SUBSTITUTE('Sales_RAW(BEFORE)'!AJ5,"$",""),"USD",""),",",".")),0) -> 15.21 | AM5: =SUBSTITUTE(SUBSTITUTE(PROPER('Sales_RAW(BEFORE)'!AK5), "Fed Ex", "FedEx"),"Fedex","FedEx") -> Dhl | AN5: 1Z806032141 | AO5: =SUBSTITUTE('Sales_RAW(BEFORE)'!AM5,"kg","") -> 23.5 | AP5: =_xlfn.LET( _xlpm.raw, UPPER(TRIM('Sales_RAW(BEFORE)'!AN5)), _xlpm.clean, RIGHT(_xlpm.raw, 1), IF(OR(_xlpm.raw="", _xlpm.raw="null"), "N/A", _xlpm.clean) ) -> B | AQ5: 76 | AR5: {=_xlfn.LET( _xlpm.raw, LOWER(TRIM('Sales_RAW(BEFORE)'!AP5)), _xlfn.IFS( OR(_xlpm.raw="", _xlpm.raw="null"), "", _xlpm.raw="excellent", 5, _xlpm.raw="good", 4, _xlpm.raw="average", 3, _xlpm.raw="poor", 2, _xlpm.raw="terrible", 1, ISNUMBER(SEARCH("/", _xlpm.raw)), _xlfn.NUMBERVALUE(_xlfn.TEXTBEFORE(_xlpm.raw, "/")), TRUE, IFERROR(_xlfn.NUMBERVALUE(_xlpm.raw), "") ) )} -> 3 | AS5: OK | AT5: No | AV5: =IF(IFERROR(VALUE(SUBSTITUTE(SUBSTITUTE(TRIM('Sales_RAW(BEFORE)'!AT5), "%", ""), ",", ".")), 0) > 1, IFERROR(VALUE(SUBSTITUTE(SUBSTITUTE(TRIM('Sales_RAW(BEFORE)'!AT5), "%", ""), ",", ".")), 0) / 100, IFERROR(VALUE(SUBSTITUTE(SUBSTITUTE(TRIM('Sales_RAW(BEFORE)'!AT5), "%", ""), ",", ".")), 0)) -> 0 | AW5: =BA5*(_xlfn.XLOOKUP(N5,Employees!$A$2:$A$26,Employees!$E$2:$E$26,2)) -> 23.416646 | AX5: =PROPER('Sales_RAW(BEFORE)'!AV5) -> Daniel Davis | AY5: =AX5 -> Daniel Davis | AZ5: Duplicate | BA5: =AK5*(1-(_xlfn.XLOOKUP(G5, Exchange_Rates!$B$8:$F$8, Exchange_Rates!$B$9:$F$9, 0)+J5)) -> 780.55488 | BB5: {=_xlfn.LET( _xlpm.raw_dt, SUBSTITUTE(TRIM(C5), ".", "/"), _xlpm.dt, IFERROR(DATEVALUE(_xlpm.raw_dt), C5), _xlpm.p_code, TRIM(E5), _xlpm.w_text, LOWER(_xlfn.XLOOKUP(_xlpm.p_code, Product_List!$B$2:$B$61, Product_List!$F$2:$F$61, "24")), _xlpm.m_count, _xlfn.IFS( ISNUMBER(SEARCH("36", _xlpm.w_text)), 36, ISNUMBER(SEARCH("3 yr", _xlpm.w_text)), 36, ISNUMBER(SEARCH("12", _xlpm.w_text)), 12, ISNUMBER(SEARCH("1 yr", _xlpm.w_text)), 12, TRUE, 24 ), IFERROR(EDATE(_xlpm.dt, _xlpm.m_count), "Proveri datum") )} -> 46653 | BC5: =BA5*AV5 -> 0
A6: TR-2025002 | B6: 45893 | C6: 45900 | D6: ="P-" & TEXT(VALUE(SUBSTITUTE(SUBSTITUTE(SUBSTITUTE(UPPER(TRIM('Sales_RAW(BEFORE)'!D6)), "P", ""), "-", ""), "_", "")),"000") -> P-052 | E6: =VLOOKUP(D6,Product_List!$A$2:$B$61,2,FALSE) -> Laptop Max 52 | F6: =_xlfn.XLOOKUP(E6,Product_List!$B$2:$B$61,Product_List!$E$2:$E$61,2) -> TechSupply Co | G6: =VLOOKUP(E6,Product_List!$B$2:$C$61,2,FALSE) -> Furniture | H6: =SUBSTITUTE(SUBSTITUTE('Sales_RAW(BEFORE)'!G6,"kom",""),".","") -> 2 | I6: =VLOOKUP(E6,Product_List!$B$2:$D$61,3,FALSE) -> 1467.86 | J6: =IF(IFERROR(VALUE(SUBSTITUTE(SUBSTITUTE(TRIM('Sales_RAW(BEFORE)'!I6), "%", ""), ",", ".")), 0) > 1, IFERROR(VALUE(SUBSTITUTE(SUBSTITUTE(TRIM('Sales_RAW(BEFORE)'!I6), "%", ""), ",", ".")), 0) / 100, IFERROR(VALUE(SUBSTITUTE(SUBSTITUTE(TRIM('Sales_RAW(BEFORE)'!I6), "%", ""), ",", ".")), 0)) -> 0.1 | K6: =IFERROR(H6*I6,0) -> 2935.72 | L6: {=_xlfn.LET( _xlpm.valuta, UPPER(TRIM('Sales_RAW(BEFORE)'!K6)), _xlfn.IFS( _xlpm.valuta = "", "", OR(_xlpm.valuta = "USD", _xlpm.valuta = "$"), "$", OR(_xlpm.valuta = "EUR", _xlpm.valuta = "€"), "€", TRUE, _xlpm.valuta ) )} -> $ | M6: ="E" & TEXT(VALUE(SUBSTITUTE(SUBSTITUTE(SUBSTITUTE(UPPER(TRIM('Sales_RAW(BEFORE)'!L6)), "EMP", ""), "E", ""), "-", "")),"000") -> E023 | N6: =_xlfn.XLOOKUP(M6,Employees!$D$2:$D$26,Employees!$A$2:$A$26) -> Laura Anderson | O6: =_xlfn.XLOOKUP(N6,Employees!$A$2:$A$26,Employees!$C$2:$C$26,2) -> Sales | P6: =PROPER('Sales_RAW(BEFORE)'!N6) -> North | Q6: =VLOOKUP(N6,Employees!$A$2:$B$26,2,FALSE) -> Seattle | R6: =PROPER('Sales_RAW(BEFORE)'!P6) -> Wayne Inc | S6: =SUBSTITUTE(SUBSTITUTE('Sales_RAW(BEFORE)'!Q6,"EIN",""),":","") -> 790161495 | T6: john.company.com | U6: +1 836 781 3186 | V6: 276 Johnson St. | W6: 89566 | X6: USA | Y6: =PROPER('Sales_RAW(BEFORE)'!W6) -> Cash | Z6: =PROPER('Sales_RAW(BEFORE)'!X6) -> Cancelled | AA6: {=_xlfn.LET( _xlpm.val, TRIM(LOWER('Sales_RAW(BEFORE)'!Y6)), _xlfn.IFS( OR(_xlpm.val="yes", _xlpm.val="paid"), "Paid", OR(_xlpm.val="no", _xlpm.val="unpaid"), "Unpaid", OR(_xlpm.val="partial", _xlpm.val="partial paid"), "Partial", _xlpm.val="", "", TRUE, 'Sales_RAW(BEFORE)'!AY6 ) )} -> Partial | AB6: INV/2025/0002 | AC6: =PROPER('Sales_RAW(BEFORE)'!AA6) -> Phone | AD6: =SUBSTITUTE(SUBSTITUTE(SUBSTITUTE(SUBSTITUTE('Sales_RAW(BEFORE)'!AB6,"st",""),"q",""),"Q",""),"uarter","") -> 1 | AE6: =TEXT(IFERROR(DATEVALUE('Sales_RAW(BEFORE)'!AC6 & " 1"), IFERROR(DATE(2025, 'Sales_RAW(BEFORE)'!AC6, 1), 'Sales_RAW(BEFORE)'!AC6)), "mmmm") -> August | AF6: =_xlfn.LET( _xlpm.raw, TRIM(SUBSTITUTE('Sales_RAW(BEFORE)'!AD6, "'", "")), _xlpm.num, IFERROR(VALUE(_xlpm.raw), 0), IF(_xlpm.num < 100, 2000 + _xlpm.num, _xlpm.num) ) -> 2025 | AG6: =PROPER('Sales_RAW(BEFORE)'!AE6) -> Net 60 | AH6: {=_xlfn.LET( _xlpm.val, LOWER(TRIM('Sales_RAW(BEFORE)'!AF6)), _xlfn.IFS( OR(_xlpm.val="", _xlpm.val="null", _xlpm.val="N/A", _xlpm.val="-", _xlpm.val="#N/A"), 0, ISNUMBER('Sales_RAW(BEFORE)'!AF6), 'Sales_RAW(BEFORE)'!AF6, TRUE, IFERROR(_xlfn.NUMBERVALUE(_xlpm.val), 0) ) )} -> 10 | AI6: =IF(IFERROR(VALUE(SUBSTITUTE(SUBSTITUTE(TRIM('Sales_RAW(BEFORE)'!AG6), "%", ""), ",", ".")), 0) > 1, IFERROR(VALUE(SUBSTITUTE(SUBSTITUTE(TRIM('Sales_RAW(BEFORE)'!AG6), "%", ""), ",", ".")), 0) / 100, IFERROR(VALUE(SUBSTITUTE(SUBSTITUTE(TRIM('Sales_RAW(BEFORE)'!AG6), "%", ""), ",", ".")), 0)) -> 0.08 | AJ6: =K6*AI6 -> 234.8576 | AK6: =AJ6+K6 -> 3170.5776 | AL6: =IFERROR(VALUE(SUBSTITUTE(SUBSTITUTE(SUBSTITUTE('Sales_RAW(BEFORE)'!AJ6,"$",""),"USD",""),",",".")),0) -> 14.48 | AM6: =SUBSTITUTE(SUBSTITUTE(PROPER('Sales_RAW(BEFORE)'!AK6), "Fed Ex", "FedEx"),"Fedex","FedEx") -> Ups | AN6: FX515375252 | AO6: =SUBSTITUTE('Sales_RAW(BEFORE)'!AM6,"kg","") -> 6,4 | AP6: =_xlfn.LET( _xlpm.raw, UPPER(TRIM('Sales_RAW(BEFORE)'!AN6)), _xlpm.clean, RIGHT(_xlpm.raw, 1), IF(OR(_xlpm.raw="", _xlpm.raw="null"), "N/A", _xlpm.clean) ) -> A | AQ6: 72 | AR6: {=_xlfn.LET( _xlpm.raw, LOWER(TRIM('Sales_RAW(BEFORE)'!AP6)), _xlfn.IFS( OR(_xlpm.raw="", _xlpm.raw="null"), "", _xlpm.raw="excellent", 5, _xlpm.raw="good", 4, _xlpm.raw="average", 3, _xlpm.raw="poor", 2, _xlpm.raw="terrible", 1, ISNUMBER(SEARCH("/", _xlpm.raw)), _xlfn.NUMBERVALUE(_xlfn.TEXTBEFORE(_xlpm.raw, "/")), TRUE, IFERROR(_xlfn.NUMBERVALUE(_xlpm.raw), "") ) )} -> 5 | AS6: all good | AV6: =IF(IFERROR(VALUE(SUBSTITUTE(SUBSTITUTE(TRIM('Sales_RAW(BEFORE)'!AT6), "%", ""), ",", ".")), 0) > 1, IFERROR(VALUE(SUBSTITUTE(SUBSTITUTE(TRIM('Sales_RAW(BEFORE)'!AT6), "%", ""), ",", ".")), 0) / 100, IFERROR(VALUE(SUBSTITUTE(SUBSTITUTE(TRIM('Sales_RAW(BEFORE)'!AT6), "%", ""), ",", ".")), 0)) -> 0.15 | AW6: =BA6*(_xlfn.XLOOKUP(N6,Employees!$A$2:$A$26,Employees!$E$2:$E$26,2)) -> 50.729242 | AX6: =PROPER('Sales_RAW(BEFORE)'!AV6) -> John Williams | AY6: =AX6 -> John Williams | AZ6: Urgent | BA6: =AK6*(1-(_xlfn.XLOOKUP(G6, Exchange_Rates!$B$8:$F$8, Exchange_Rates!$B$9:$F$9, 0)+J6)) -> 2536.4621 | BB6: {=_xlfn.LET( _xlpm.raw_dt, SUBSTITUTE(TRIM(C6), ".", "/"), _xlpm.dt, IFERROR(DATEVALUE(_xlpm.raw_dt), C6), _xlpm.p_code, TRIM(E6), _xlpm.w_text, LOWER(_xlfn.XLOOKUP(_xlpm.p_code, Product_List!$B$2:$B$61, Product_List!$F$2:$F$61, "24")), _xlpm.m_count, _xlfn.IFS( ISNUMBER(SEARCH("36", _xlpm.w_text)), 36, ISNUMBER(SEARCH("3 yr", _xlpm.w_text)), 36, ISNUMBER(SEARCH("12", _xlpm.w_text)), 12, ISNUMBER(SEARCH("1 yr", _xlpm.w_text)), 12, TRUE, 24 ), IFERROR(EDATE(_xlpm.dt, _xlpm.m_count), "Proveri datum") )} -> 46996 | BC6: =BA6*AV6 -> 380.46931
A7: TR-2025003 | B7: 46119 | C7: 46125 | D7: ="P-" & TEXT(VALUE(SUBSTITUTE(SUBSTITUTE(SUBSTITUTE(UPPER(TRIM('Sales_RAW(BEFORE)'!D7)), "P", ""), "-", ""), "_", "")),"000") -> P-032 | E7: =VLOOKUP(D7,Product_List!$A$2:$B$61,2,FALSE) -> Cable Basic 32 | F7: =_xlfn.XLOOKUP(E7,Product_List!$B$2:$B$61,Product_List!$E$2:$E$61,2) -> OfficeHub | G7: =VLOOKUP(E7,Product_List!$B$2:$C$61,2,FALSE) -> Software | H7: =SUBSTITUTE(SUBSTITUTE('Sales_RAW(BEFORE)'!G7,"kom",""),".","") -> 20 | I7: =VLOOKUP(E7,Product_List!$B$2:$D$61,3,FALSE) -> 1479.77 | J7: =IF(IFERROR(VALUE(SUBSTITUTE(SUBSTITUTE(TRIM('Sales_RAW(BEFORE)'!I7), "%", ""), ",", ".")), 0) > 1, IFERROR(VALUE(SUBSTITUTE(SUBSTITUTE(TRIM('Sales_RAW(BEFORE)'!I7), "%", ""), ",", ".")), 0) / 100, IFERROR(VALUE(SUBSTITUTE(SUBSTITUTE(TRIM('Sales_RAW(BEFORE)'!I7), "%", ""), ",", ".")), 0)) -> 0 | K7: =IFERROR(H7*I7,0) -> 29595.4 | L7: {=_xlfn.LET( _xlpm.valuta, UPPER(TRIM('Sales_RAW(BEFORE)'!K7)), _xlfn.IFS( _xlpm.valuta = "", "", OR(_xlpm.valuta = "USD", _xlpm.valuta = "$"), "$", OR(_xlpm.valuta = "EUR", _xlpm.valuta = "€"), "€", TRUE, _xlpm.valuta ) )} -> $ | M7: ="E" & TEXT(VALUE(SUBSTITUTE(SUBSTITUTE(SUBSTITUTE(UPPER(TRIM('Sales_RAW(BEFORE)'!L7)), "EMP", ""), "E", ""), "-", "")),"000") -> E022 | N7: =_xlfn.XLOOKUP(M7,Employees!$D$2:$D$26,Employees!$A$2:$A$26) -> Chris Williams | O7: =_xlfn.XLOOKUP(N7,Employees!$A$2:$A$26,Employees!$C$2:$C$26,2) -> Sales | P7: =PROPER('Sales_RAW(BEFORE)'!N7) -> South | Q7: =VLOOKUP(N7,Employees!$A$2:$B$26,2,FALSE) -> Boston | R7: =PROPER('Sales_RAW(BEFORE)'!P7) -> Umbrella Inc | S7: =SUBSTITUTE(SUBSTITUTE('Sales_RAW(BEFORE)'!Q7,"EIN",""),":","") -> 943040526 | T7: emma.company.com | U7: 949.620.8386 | V7: 771 Williams Ave | W7: null | X7: USA | Y7: =PROPER('Sales_RAW(BEFORE)'!W7) -> Credit Card | Z7: =PROPER('Sales_RAW(BEFORE)'!X7) -> Cancelled | AA7: {=_xlfn.LET( _xlpm.val, TRIM(LOWER('Sales_RAW(BEFORE)'!Y7)), _xlfn.IFS( OR(_xlpm.val="yes", _xlpm.val="paid"), "Paid", OR(_xlpm.val="no", _xlpm.val="unpaid"), "Unpaid", OR(_xlpm.val="partial", _xlpm.val="partial paid"), "Partial", _xlpm.val="", "", TRUE, 'Sales_RAW(BEFORE)'!AY7 ) )} -> Partial | AB7: INV/2026/0003 | AC7: =PROPER('Sales_RAW(BEFORE)'!AA7) -> Store | AD7: =SUBSTITUTE(SUBSTITUTE(SUBSTITUTE(SUBSTITUTE('Sales_RAW(BEFORE)'!AB7,"st",""),"q",""),"Q",""),"uarter","") -> 1 | AE7: =TEXT(IFERROR(DATEVALUE('Sales_RAW(BEFORE)'!AC7 & " 1"), IFERROR(DATE(2025, 'Sales_RAW(BEFORE)'!AC7, 1), 'Sales_RAW(BEFORE)'!AC7)), "mmmm") -> April | AF7: =_xlfn.LET( _xlpm.raw, TRIM(SUBSTITUTE('Sales_RAW(BEFORE)'!AD7, "'", "")), _xlpm.num, IFERROR(VALUE(_xlpm.raw), 0), IF(_xlpm.num < 100, 2000 + _xlpm.num, _xlpm.num) ) -> 2026 | AG7: =PROPER('Sales_RAW(BEFORE)'!AE7) -> Net 60 | AH7: {=_xlfn.LET( _xlpm.val, LOWER(TRIM('Sales_RAW(BEFORE)'!AF7)), _xlfn.IFS( OR(_xlpm.val="", _xlpm.val="null", _xlpm.val="N/A", _xlpm.val="-", _xlpm.val="#N/A"), 0, ISNUMBER('Sales_RAW(BEFORE)'!AF7), 'Sales_RAW(BEFORE)'!AF7, TRUE, IFERROR(_xlfn.NUMBERVALUE(_xlpm.val), 0) ) )} -> 51 | AI7: =IF(IFERROR(VALUE(SUBSTITUTE(SUBSTITUTE(TRIM('Sales_RAW(BEFORE)'!AG7), "%", ""), ",", ".")), 0) > 1, IFERROR(VALUE(SUBSTITUTE(SUBSTITUTE(TRIM('Sales_RAW(BEFORE)'!AG7), "%", ""), ",", ".")), 0) / 100, IFERROR(VALUE(SUBSTITUTE(SUBSTITUTE(TRIM('Sales_RAW(BEFORE)'!AG7), "%", ""), ",", ".")), 0)) -> 0.08 | AJ7: =K7*AI7 -> 2367.632 | AK7: =AJ7+K7 -> 31963.032 | AL7: =IFERROR(VALUE(SUBSTITUTE(SUBSTITUTE(SUBSTITUTE('Sales_RAW(BEFORE)'!AJ7,"$",""),"USD",""),",",".")),0) -> 24.16 | AM7: =SUBSTITUTE(SUBSTITUTE(PROPER('Sales_RAW(BEFORE)'!AK7), "Fed Ex", "FedEx"),"Fedex","FedEx") -> FedEx | AN7: DH273577842 | AO7: =SUBSTITUTE('Sales_RAW(BEFORE)'!AM7,"kg","") -> 24,37 | AP7: =_xlfn.LET( _xlpm.raw, UPPER(TRIM('Sales_RAW(BEFORE)'!AN7)), _xlpm.clean, RIGHT(_xlpm.raw, 1), IF(OR(_xlpm.raw="", _xlpm.raw="null"), "N/A", _xlpm.clean) ) -> A | AQ7: 231 | AV7: =IF(IFERROR(VALUE(SUBSTITUTE(SUBSTITUTE(TRIM('Sales_RAW(BEFORE)'!AT7), "%", ""), ",", ".")), 0) > 1, IFERROR(VALUE(SUBSTITUTE(SUBSTITUTE(TRIM('Sales_RAW(BEFORE)'!AT7), "%", ""), ",", ".")), 0) / 100, IFERROR(VALUE(SUBSTITUTE(SUBSTITUTE(TRIM('Sales_RAW(BEFORE)'!AT7), "%", ""), ",", ".")), 0)) -> 0.18 | AW7: =BA7*(_xlfn.XLOOKUP(N7,Employees!$A$2:$A$26,Employees!$E$2:$E$26,2)) -> 815.05732 | AX7: =PROPER('Sales_RAW(BEFORE)'!AV7) -> Emma Williams | AY7: =AX7 -> Emma Williams | AZ7: VIP customer | BA7: =AK7*(1-(_xlfn.XLOOKUP(G7, Exchange_Rates!$B$8:$F$8, Exchange_Rates!$B$9:$F$9, 0)+J7)) -> 27168.577 | BB7: {=_xlfn.LET( _xlpm.raw_dt, SUBSTITUTE(TRIM(C7), ".", "/"), _xlpm.dt, IFERROR(DATEVALUE(_xlpm.raw_dt), C7), _xlpm.p_code, TRIM(E7), _xlpm.w_text, LOWER(_xlfn.XLOOKUP(_xlpm.p_code, Product_List!$B$2:$B$61, Product_List!$F$2:$F$61, "24")), _xlpm.m_count, _xlfn.IFS( ISNUMBER(SEARCH("36", _xlpm.w_text)), 36, ISNUMBER(SEARCH("3 yr", _xlpm.w_text)), 36, ISNUMBER(SEARCH("12", _xlpm.w_text)), 12, ISNUMBER(SEARCH("1 yr", _xlpm.w_text)), 12, TRUE, 24 ), IFERROR(EDATE(_xlpm.dt, _xlpm.m_count), "Proveri datum") )} -> 47221 | BC7: =BA7*AV7 -> 4890.3439
A8: TR-2025004 | B8: 46050 | C8: 46144 | D8: ="P-" & TEXT(VALUE(SUBSTITUTE(SUBSTITUTE(SUBSTITUTE(UPPER(TRIM('Sales_RAW(BEFORE)'!D8)), "P", ""), "-", ""), "_", "")),"000") -> P-048 | E8: =VLOOKUP(D8,Product_List!$A$2:$B$61,2,FALSE) -> License Plus 48 | F8: =_xlfn.XLOOKUP(E8,Product_List!$B$2:$B$61,Product_List!$E$2:$E$61,2) -> BestParts | G8: =VLOOKUP(E8,Product_List!$B$2:$C$61,2,FALSE) -> Software | H8: =SUBSTITUTE(SUBSTITUTE('Sales_RAW(BEFORE)'!G8,"kom",""),".","") -> 34 | I8: =VLOOKUP(E8,Product_List!$B$2:$D$61,3,FALSE) -> 471.22 | J8: =IF(IFERROR(VALUE(SUBSTITUTE(SUBSTITUTE(TRIM('Sales_RAW(BEFORE)'!I8), "%", ""), ",", ".")), 0) > 1, IFERROR(VALUE(SUBSTITUTE(SUBSTITUTE(TRIM('Sales_RAW(BEFORE)'!I8), "%", ""), ",", ".")), 0) / 100, IFERROR(VALUE(SUBSTITUTE(SUBSTITUTE(TRIM('Sales_RAW(BEFORE)'!I8), "%", ""), ",", ".")), 0)) -> 0.05 | K8: =IFERROR(H8*I8,0) -> 16021.48 | L8: {=_xlfn.LET( _xlpm.valuta, UPPER(TRIM('Sales_RAW(BEFORE)'!K8)), _xlfn.IFS( _xlpm.valuta = "", "", OR(_xlpm.valuta = "USD", _xlpm.valuta = "$"), "$", OR(_xlpm.valuta = "EUR", _xlpm.valuta = "€"), "€", TRUE, _xlpm.valuta ) )} -> $ | M8: ="E" & TEXT(VALUE(SUBSTITUTE(SUBSTITUTE(SUBSTITUTE(UPPER(TRIM('Sales_RAW(BEFORE)'!L8)), "EMP", ""), "E", ""), "-", "")),"000") -> E014 | N8: =_xlfn.XLOOKUP(M8,Employees!$D$2:$D$26,Employees!$A$2:$A$26) -> Sophia Brown | O8: =_xlfn.XLOOKUP(N8,Employees!$A$2:$A$26,Employees!$C$2:$C$26,2) -> Online | P8: =PROPER('Sales_RAW(BEFORE)'!N8) -> West | Q8: =VLOOKUP(N8,Employees!$A$2:$B$26,2,FALSE) -> New York | R8: =PROPER('Sales_RAW(BEFORE)'!P8) -> Initech Inc | S8: =SUBSTITUTE(SUBSTITUTE('Sales_RAW(BEFORE)'!Q8,"EIN",""),":","") -> 986261507 | T8: sarah.gmail.com | U8: (240) 201-3058 | V8: 642 Jones Blvd | W8: 92564 | X8: USA | Y8: =PROPER('Sales_RAW(BEFORE)'!W8) -> Credit Card | Z8: =PROPER('Sales_RAW(BEFORE)'!X8) -> Processing | AA8: {=_xlfn.LET( _xlpm.val, TRIM(LOWER('Sales_RAW(BEFORE)'!Y8)), _xlfn.IFS( OR(_xlpm.val="yes", _xlpm.val="paid"), "Paid", OR(_xlpm.val="no", _xlpm.val="unpaid"), "Unpaid", OR(_xlpm.val="partial", _xlpm.val="partial paid"), "Partial", _xlpm.val="", "", TRUE, 'Sales_RAW(BEFORE)'!AY8 ) )} -> Paid | AB8: INV/2026/0004 | AC8: =PROPER('Sales_RAW(BEFORE)'!AA8) -> Online | AD8: =SUBSTITUTE(SUBSTITUTE(SUBSTITUTE(SUBSTITUTE('Sales_RAW(BEFORE)'!AB8,"st",""),"q",""),"Q",""),"uarter","") -> 1 | AE8: =TEXT(IFERROR(DATEVALUE('Sales_RAW(BEFORE)'!AC8 & " 1"), IFERROR(DATE(2025, 'Sales_RAW(BEFORE)'!AC8, 1), 'Sales_RAW(BEFORE)'!AC8)), "mmmm") -> January | AF8: =_xlfn.LET( _xlpm.raw, TRIM(SUBSTITUTE('Sales_RAW(BEFORE)'!AD8, "'", "")), _xlpm.num, IFERROR(VALUE(_xlpm.raw), 0), IF(_xlpm.num < 100, 2000 + _xlpm.num, _xlpm.num) ) -> 2026 | AG8: =PROPER('Sales_RAW(BEFORE)'!AE8) -> 15 | AH8: {=_xlfn.LET( _xlpm.val, LOWER(TRIM('Sales_RAW(BEFORE)'!AF8)), _xlfn.IFS( OR(_xlpm.val="", _xlpm.val="null", _xlpm.val="N/A", _xlpm.val="-", _xlpm.val="#N/A"), 0, ISNUMBER('Sales_RAW(BEFORE)'!AF8), 'Sales_RAW(BEFORE)'!AF8, TRUE, IFERROR(_xlfn.NUMBERVALUE(_xlpm.val), 0) ) )} -> 0 | AI8: =IF(IFERROR(VALUE(SUBSTITUTE(SUBSTITUTE(TRIM('Sales_RAW(BEFORE)'!AG8), "%", ""), ",", ".")), 0) > 1, IFERROR(VALUE(SUBSTITUTE(SUBSTITUTE(TRIM('Sales_RAW(BEFORE)'!AG8), "%", ""), ",", ".")), 0) / 100, IFERROR(VALUE(SUBSTITUTE(SUBSTITUTE(TRIM('Sales_RAW(BEFORE)'!AG8), "%", ""), ",", ".")), 0)) -> 0.08 | AJ8: =K8*AI8 -> 1281.7184 | AK8: =AJ8+K8 -> 17303.198 | AL8: =IFERROR(VALUE(SUBSTITUTE(SUBSTITUTE(SUBSTITUTE('Sales_RAW(BEFORE)'!AJ8,"$",""),"USD",""),",",".")),0) -> 49.82 | AM8: =SUBSTITUTE(SUBSTITUTE(PROPER('Sales_RAW(BEFORE)'!AK8), "Fed Ex", "FedEx"),"Fedex","FedEx") -> Usps | AN8: 1Z610354022 | AO8: =SUBSTITUTE('Sales_RAW(BEFORE)'!AM8,"kg","") -> 16.5 | AP8: =_xlfn.LET( _xlpm.raw, UPPER(TRIM('Sales_RAW(BEFORE)'!AN8)), _xlpm.clean, RIGHT(_xlpm.raw, 1), IF(OR(_xlpm.raw="", _xlpm.raw="null"), "N/A", _xlpm.clean) ) -> B | AQ8: 0 | AR8: {=_xlfn.LET( _xlpm.raw, LOWER(TRIM('Sales_RAW(BEFORE)'!AP8)), _xlfn.IFS( OR(_xlpm.raw="", _xlpm.raw="null"), "", _xlpm.raw="excellent", 5, _xlpm.raw="good", 4, _xlpm.raw="average", 3, _xlpm.raw="poor", 2, _xlpm.raw="terrible", 1, ISNUMBER(SEARCH("/", _xlpm.raw)), _xlfn.NUMBERVALUE(_xlfn.TEXTBEFORE(_xlpm.raw, "/")), TRUE, IFERROR(_xlfn.NUMBERVALUE(_xlpm.raw), "") ) )} -> 5 | AS8: satisfied | AV8: =IF(IFERROR(VALUE(SUBSTITUTE(SUBSTITUTE(TRIM('Sales_RAW(BEFORE)'!AT8), "%", ""), ",", ".")), 0) > 1, IFERROR(VALUE(SUBSTITUTE(SUBSTITUTE(TRIM('Sales_RAW(BEFORE)'!AT8), "%", ""), ",", ".")), 0) / 100, IFERROR(VALUE(SUBSTITUTE(SUBSTITUTE(TRIM('Sales_RAW(BEFORE)'!AT8), "%", ""), ",", ".")), 0)) -> 0 | AW8: =BA8*(_xlfn.XLOOKUP(N8,Employees!$A$2:$A$26,Employees!$E$2:$E$26,2)) -> 415.27676 | AX8: =PROPER('Sales_RAW(BEFORE)'!AV8) -> Sarah Davis | AY8: =AX8 -> Sarah Davis | AZ8: Check price | BA8: =AK8*(1-(_xlfn.XLOOKUP(G8, Exchange_Rates!$B$8:$F$8, Exchange_Rates!$B$9:$F$9, 0)+J8)) -> 13842.559 | BB8: {=_xlfn.LET( _xlpm.raw_dt, SUBSTITUTE(TRIM(C8), ".", "/"), _xlpm.dt, IFERROR(DATEVALUE(_xlpm.raw_dt), C8), _xlpm.p_code, TRIM(E8), _xlpm.w_text, LOWER(_xlfn.XLOOKUP(_xlpm.p_code, Product_List!$B$2:$B$61, Product_List!$F$2:$F$61, "24")), _xlpm.m_count, _xlfn.IFS( ISNUMBER(SEARCH("36", _xlpm.w_text)), 36, ISNUMBER(SEARCH("3 yr", _xlpm.w_text)), 36, ISNUMBER(SEARCH("12", _xlpm.w_text)), 12, ISNUMBER(SEARCH("1 yr", _xlpm.w_text)), 12, TRUE, 24 ), IFERROR(EDATE(_xlpm.dt, _xlpm.m_count), "Proveri datum") )} -> 46509 | BC8: =BA8*AV8 -> 0
A9: TR-2025005 | B9: 46174 | C9: 46271 | D9: ="P-" & TEXT(VALUE(SUBSTITUTE(SUBSTITUTE(SUBSTITUTE(UPPER(TRIM('Sales_RAW(BEFORE)'!D9)), "P", ""), "-", ""), "_", "")),"000") -> P-001 | E9: =VLOOKUP(D9,Product_List!$A$2:$B$61,2,FALSE) -> Desk X 1 | F9: =_xlfn.XLOOKUP(E9,Product_List!$B$2:$B$61,Product_List!$E$2:$E$61,2) -> Global Distrib | G9: =VLOOKUP(E9,Product_List!$B$2:$C$61,2,FALSE) -> Software | H9: =SUBSTITUTE(SUBSTITUTE('Sales_RAW(BEFORE)'!G9,"kom",""),".","") -> 14 | I9: =VLOOKUP(E9,Product_List!$B$2:$D$61,3,FALSE) -> 978.15 | J9: =IF(IFERROR(VALUE(SUBSTITUTE(SUBSTITUTE(TRIM('Sales_RAW(BEFORE)'!I9), "%", ""), ",", ".")), 0) > 1, IFERROR(VALUE(SUBSTITUTE(SUBSTITUTE(TRIM('Sales_RAW(BEFORE)'!I9), "%", ""), ",", ".")), 0) / 100, IFERROR(VALUE(SUBSTITUTE(SUBSTITUTE(TRIM('Sales_RAW(BEFORE)'!I9), "%", ""), ",", ".")), 0)) -> 0.1 | K9: =IFERROR(H9*I9,0) -> 13694.1 | L9: {=_xlfn.LET( _xlpm.valuta, UPPER(TRIM('Sales_RAW(BEFORE)'!K9)), _xlfn.IFS( _xlpm.valuta = "", "", OR(_xlpm.valuta = "USD", _xlpm.valuta = "$"), "$", OR(_xlpm.valuta = "EUR", _xlpm.valuta = "€"), "€", TRUE, _xlpm.valuta ) )} -> $ | M9: ="E" & TEXT(VALUE(SUBSTITUTE(SUBSTITUTE(SUBSTITUTE(UPPER(TRIM('Sales_RAW(BEFORE)'!L9)), "EMP", ""), "E", ""), "-", "")),"000") -> E010 | N9: =_xlfn.XLOOKUP(M9,Employees!$D$2:$D$26,Employees!$A$2:$A$26) -> Olivia Anderson | O9: =_xlfn.XLOOKUP(N9,Employees!$A$2:$A$26,Employees!$C$2:$C$26,2) -> Online | P9: =PROPER('Sales_RAW(BEFORE)'!N9) -> South | Q9: =VLOOKUP(N9,Employees!$A$2:$B$26,2,FALSE) -> Houston | R9: =PROPER('Sales_RAW(BEFORE)'!P9) -> Initech Inc | S9: =SUBSTITUTE(SUBSTITUTE('Sales_RAW(BEFORE)'!Q9,"EIN",""),":","") -> 134245587 | T9: laura.company.com | U9: +1 373 311 1047 | V9: 431 Johnson St. | W9: 50824 | X9: USA | Y9: =PROPER('Sales_RAW(BEFORE)'!W9) -> Wire Transfer | Z9: =PROPER('Sales_RAW(BEFORE)'!X9) -> Delivered | AA9: {=_xlfn.LET( _xlpm.val, TRIM(LOWER('Sales_RAW(BEFORE)'!Y9)), _xlfn.IFS( OR(_xlpm.val="yes", _xlpm.val="paid"), "Paid", OR(_xlpm.val="no", _xlpm.val="unpaid"), "Unpaid", OR(_xlpm.val="partial", _xlpm.val="partial paid"), "Partial", _xlpm.val="", "", TRUE, 'Sales_RAW(BEFORE)'!AY9 ) )} -> Paid | AB9: INV/2026/0005 | AC9: =PROPER('Sales_RAW(BEFORE)'!AA9) -> Phone | AD9: =SUBSTITUTE(SUBSTITUTE(SUBSTITUTE(SUBSTITUTE('Sales_RAW(BEFORE)'!AB9,"st",""),"q",""),"Q",""),"uarter","") -> 1 | AE9: =TEXT(IFERROR(DATEVALUE('Sales_RAW(BEFORE)'!AC9 & " 1"), IFERROR(DATE(2025, 'Sales_RAW(BEFORE)'!AC9, 1), 'Sales_RAW(BEFORE)'!AC9)), "mmmm") -> June | AF9: =_xlfn.LET( _xlpm.raw, TRIM(SUBSTITUTE('Sales_RAW(BEFORE)'!AD9, "'", "")), _xlpm.num, IFERROR(VALUE(_xlpm.raw), 0), IF(_xlpm.num < 100, 2000 + _xlpm.num, _xlpm.num) ) -> 2026 | AG9: =PROPER('Sales_RAW(BEFORE)'!AE9) -> Immediate | AH9: {=_xlfn.LET( _xlpm.val, LOWER(TRIM('Sales_RAW(BEFORE)'!AF9)), _xlfn.IFS( OR(_xlpm.val="", _xlpm.val="null", _xlpm.val="N/A", _xlpm.val="-", _xlpm.val="#N/A"), 0, ISNUMBER('Sales_RAW(BEFORE)'!AF9), 'Sales_RAW(BEFORE)'!AF9, TRUE, IFERROR(_xlfn.NUMBERVALUE(_xlpm.val), 0) ) )} -> 24 | AI9: =IF(IFERROR(VALUE(SUBSTITUTE(SUBSTITUTE(TRIM('Sales_RAW(BEFORE)'!AG9), "%", ""), ",", ".")), 0) > 1, IFERROR(VALUE(SUBSTITUTE(SUBSTITUTE(TRIM('Sales_RAW(BEFORE)'!AG9), "%", ""), ",", ".")), 0) / 100, IFERROR(VALUE(SUBSTITUTE(SUBSTITUTE(TRIM('Sales_RAW(BEFORE)'!AG9), "%", ""), ",", ".")), 0)) -> 0.08 | AJ9: =K9*AI9 -> 1095.528 | AK9: =AJ9+K9 -> 14789.628 | AL9: =IFERROR(VALUE(SUBSTITUTE(SUBSTITUTE(SUBSTITUTE('Sales_RAW(BEFORE)'!AJ9,"$",""),"USD",""),",",".")),0) -> 2 | AM9: =SUBSTITUTE(SUBSTITUTE(PROPER('Sales_RAW(BEFORE)'!AK9), "Fed Ex", "FedEx"),"Fedex","FedEx") -> Usps | AN9: FX143647055 | AO9: =SUBSTITUTE('Sales_RAW(BEFORE)'!AM9,"kg","") -> 11.33 | AP9: =_xlfn.LET( _xlpm.raw, UPPER(TRIM('Sales_RAW(BEFORE)'!AN9)), _xlpm.clean, RIGHT(_xlpm.raw, 1), IF(OR(_xlpm.raw="", _xlpm.raw="null"), "N/A", _xlpm.clean) ) -> B | AQ9: 99 | AR9: {=_xlfn.LET( _xlpm.raw, LOWER(TRIM('Sales_RAW(BEFORE)'!AP9)), _xlfn.IFS( OR(_xlpm.raw="", _xlpm.raw="null"), "", _xlpm.raw="excellent", 5, _xlpm.raw="good", 4, _xlpm.raw="average", 3, _xlpm.raw="poor", 2, _xlpm.raw="terrible", 1, ISNUMBER(SEARCH("/", _xlpm.raw)), _xlfn.NUMBERVALUE(_xlfn.TEXTBEFORE(_xlpm.raw, "/")), TRUE, IFERROR(_xlfn.NUMBERVALUE(_xlpm.raw), "") ) )} -> 5 | AV9: =IF(IFERROR(VALUE(SUBSTITUTE(SUBSTITUTE(TRIM('Sales_RAW(BEFORE)'!AT9), "%", ""), ",", ".")), 0) > 1, IFERROR(VALUE(SUBSTITUTE(SUBSTITUTE(TRIM('Sales_RAW(BEFORE)'!AT9), "%", ""), ",", ".")), 0) / 100, IFERROR(VALUE(SUBSTITUTE(SUBSTITUTE(TRIM('Sales_RAW(BEFORE)'!AT9), "%", ""), ",", ".")), 0)) -> 0.15 | AW9: =BA9*(_xlfn.XLOOKUP(N9,Employees!$A$2:$A$26,Employees!$E$2:$E$26,2)) -> 332.76663 | AX9: =PROPER('Sales_RAW(BEFORE)'!AV9) -> Laura Brown | AY9: =AX9 -> Laura Brown | BA9: =AK9*(1-(_xlfn.XLOOKUP(G9, Exchange_Rates!$B$8:$F$8, Exchange_Rates!$B$9:$F$9, 0)+J9)) -> 11092.221 | BB9: {=_xlfn.LET( _xlpm.raw_dt, SUBSTITUTE(TRIM(C9), ".", "/"), _xlpm.dt, IFERROR(DATEVALUE(_xlpm.raw_dt), C9), _xlpm.p_code, TRIM(E9), _xlpm.w_text, LOWER(_xlfn.XLOOKUP(_xlpm.p_code, Product_List!$B$2:$B$61, Product_List!$F$2:$F$61, "24")), _xlpm.m_count, _xlfn.IFS( ISNUMBER(SEARCH("36", _xlpm.w_text)), 36, ISNUMBER(SEARCH("3 yr", _xlpm.w_text)), 36, ISNUMBER(SEARCH("12", _xlpm.w_text)), 12, ISNUMBER(SEARCH("1 yr", _xlpm.w_text)), 12, TRUE, 24 ), IFERROR(EDATE(_xlpm.dt, _xlpm.m_count), "Proveri datum") )} -> 47002 | BC9: =BA9*AV9 -> 1663.8332
A10: TR-2025006 | B10: 45767 | C10: 45752 | D10: ="P-" & TEXT(VALUE(SUBSTITUTE(SUBSTITUTE(SUBSTITUTE(UPPER(TRIM('Sales_RAW(BEFORE)'!D10)), "P", ""), "-", ""), "_", "")),"000") -> P-053 | E10: =VLOOKUP(D10,Product_List!$A$2:$B$61,2,FALSE) -> Monitor Basic 53 | F10: =_xlfn.XLOOKUP(E10,Product_List!$B$2:$B$61,Product_List!$E$2:$E$61,2) -> Global Distrib | G10: =VLOOKUP(E10,Product_List!$B$2:$C$61,2,FALSE) -> Equipment | H10: =SUBSTITUTE(SUBSTITUTE('Sales_RAW(BEFORE)'!G10,"kom",""),".","") -> 30 | I10: =VLOOKUP(E10,Product_List!$B$2:$D$61,3,FALSE) -> 553.22 | J10: =IF(IFERROR(VALUE(SUBSTITUTE(SUBSTITUTE(TRIM('Sales_RAW(BEFORE)'!I10), "%", ""), ",", ".")), 0) > 1, IFERROR(VALUE(SUBSTITUTE(SUBSTITUTE(TRIM('Sales_RAW(BEFORE)'!I10), "%", ""), ",", ".")), 0) / 100, IFERROR(VALUE(SUBSTITUTE(SUBSTITUTE(TRIM('Sales_RAW(BEFORE)'!I10), "%", ""), ",", ".")), 0)) -> 0.1 | K10: =IFERROR(H10*I10,0) -> 16596.6 | L10: {=_xlfn.LET( _xlpm.valuta, UPPER(TRIM('Sales_RAW(BEFORE)'!K10)), _xlfn.IFS( _xlpm.valuta = "", "", OR(_xlpm.valuta = "USD", _xlpm.valuta = "$"), "$", OR(_xlpm.valuta = "EUR", _xlpm.valuta = "€"), "€", TRUE, _xlpm.valuta ) )} -> $ | M10: ="E" & TEXT(VALUE(SUBSTITUTE(SUBSTITUTE(SUBSTITUTE(UPPER(TRIM('Sales_RAW(BEFORE)'!L10)), "EMP", ""), "E", ""), "-", "")),"000") -> E008 | N10: =_xlfn.XLOOKUP(M10,Employees!$D$2:$D$26,Employees!$A$2:$A$26) -> Michael Williams | O10: =_xlfn.XLOOKUP(N10,Employees!$A$2:$A$26,Employees!$C$2:$C$26,2) -> Wholesale | P10: =PROPER('Sales_RAW(BEFORE)'!N10) -> North | Q10: =VLOOKUP(N10,Employees!$A$2:$B$26,2,FALSE) -> New York | R10: =PROPER('Sales_RAW(BEFORE)'!P10) -> Vortex Inc | S10: =SUBSTITUTE(SUBSTITUTE('Sales_RAW(BEFORE)'!Q10,"EIN",""),":","") -> 862110984 | T10: chris.gmail.com | U10: +1 965 751 2985 | V10: 581 Jones Ave | W10: 34299 | X10: USA | Y10: =PROPER('Sales_RAW(BEFORE)'!W10) -> Wire Transfer | Z10: =PROPER('Sales_RAW(BEFORE)'!X10) -> Delivered | AA10: {=_xlfn.LET( _xlpm.val, TRIM(LOWER('Sales_RAW(BEFORE)'!Y10)), _xlfn.IFS( OR(_xlpm.val="yes", _xlpm.val="paid"), "Paid", OR(_xlpm.val="no", _xlpm.val="unpaid"), "Unpaid", OR(_xlpm.val="partial", _xlpm.val="partial paid"), "Partial", _xlpm.val="", "", TRUE, 'Sales_RAW(BEFORE)'!AY10 ) )} -> Paid | AB10: INV/2025/0006 | AC10: =PROPER('Sales_RAW(BEFORE)'!AA10) -> Web | AD10: =SUBSTITUTE(SUBSTITUTE(SUBSTITUTE(SUBSTITUTE('Sales_RAW(BEFORE)'!AB10,"st",""),"q",""),"Q",""),"uarter","") -> 1 | AE10: =TEXT(IFERROR(DATEVALUE('Sales_RAW(BEFORE)'!AC10 & " 1"), IFERROR(DATE(2025, 'Sales_RAW(BEFORE)'!AC10, 1), 'Sales_RAW(BEFORE)'!AC10)), "mmmm") -> April | AF10: =_xlfn.LET( _xlpm.raw, TRIM(SUBSTITUTE('Sales_RAW(BEFORE)'!AD10, "'", "")), _xlpm.num, IFERROR(VALUE(_xlpm.raw), 0), IF(_xlpm.num < 100, 2000 + _xlpm.num, _xlpm.num) ) -> 2025 | AG10: =PROPER('Sales_RAW(BEFORE)'!AE10) -> 15 | AH10: {=_xlfn.LET( _xlpm.val, LOWER(TRIM('Sales_RAW(BEFORE)'!AF10)), _xlfn.IFS( OR(_xlpm.val="", _xlpm.val="null", _xlpm.val="N/A", _xlpm.val="-", _xlpm.val="#N/A"), 0, ISNUMBER('Sales_RAW(BEFORE)'!AF10), 'Sales_RAW(BEFORE)'!AF10, TRUE, IFERROR(_xlfn.NUMBERVALUE(_xlpm.val), 0) ) )} -> 0 | AI10: =IF(IFERROR(VALUE(SUBSTITUTE(SUBSTITUTE(TRIM('Sales_RAW(BEFORE)'!AG10), "%", ""), ",", ".")), 0) > 1, IFERROR(VALUE(SUBSTITUTE(SUBSTITUTE(TRIM('Sales_RAW(BEFORE)'!AG10), "%", ""), ",", ".")), 0) / 100, IFERROR(VALUE(SUBSTITUTE(SUBSTITUTE(TRIM('Sales_RAW(BEFORE)'!AG10), "%", ""), ",", ".")), 0)) -> 0.08 | AJ10: =K10*AI10 -> 1327.728 | AK10: =AJ10+K10 -> 17924.328 | AL10: =IFERROR(VALUE(SUBSTITUTE(SUBSTITUTE(SUBSTITUTE('Sales_RAW(BEFORE)'!AJ10,"$",""),"USD",""),",",".")),0) -> 25.37 | AM10: =SUBSTITUTE(SUBSTITUTE(PROPER('Sales_RAW(BEFORE)'!AK10), "Fed Ex", "FedEx"),"Fedex","FedEx") -> FedEx | AN10: DH598125683 | AO10: =SUBSTITUTE('Sales_RAW(BEFORE)'!AM10,"kg","") -> 29.73 | AP10: =_xlfn.LET( _xlpm.raw, UPPER(TRIM('Sales_RAW(BEFORE)'!AN10)), _xlpm.clean, RIGHT(_xlpm.raw, 1), IF(OR(_xlpm.raw="", _xlpm.raw="null"), "N/A", _xlpm.clean) ) -> B | AQ10: 468 | AR10: {=_xlfn.LET( _xlpm.raw, LOWER(TRIM('Sales_RAW(BEFORE)'!AP10)), _xlfn.IFS( OR(_xlpm.raw="", _xlpm.raw="null"), "", _xlpm.raw="excellent", 5, _xlpm.raw="good", 4, _xlpm.raw="average", 3, _xlpm.raw="poor", 2, _xlpm.raw="terrible", 1, ISNUMBER(SEARCH("/", _xlpm.raw)), _xlfn.NUMBERVALUE(_xlfn.TEXTBEFORE(_xlpm.raw, "/")), TRUE, IFERROR(_xlfn.NUMBERVALUE(_xlpm.raw), "") ) )} -> 5 | AV10: =IF(IFERROR(VALUE(SUBSTITUTE(SUBSTITUTE(TRIM('Sales_RAW(BEFORE)'!AT10), "%", ""), ",", ".")), 0) > 1, IFERROR(VALUE(SUBSTITUTE(SUBSTITUTE(TRIM('Sales_RAW(BEFORE)'!AT10), "%", ""), ",", ".")), 0) / 100, IFERROR(VALUE(SUBSTITUTE(SUBSTITUTE(TRIM('Sales_RAW(BEFORE)'!AT10), "%", ""), ",", ".")), 0)) -> 0.18 | AW10: =BA10*(_xlfn.XLOOKUP(N10,Employees!$A$2:$A$26,Employees!$E$2:$E$26,2)) -> 716.97312 | AX10: =PROPER('Sales_RAW(BEFORE)'!AV10) -> Chris Davis | AY10: =AX10 -> Chris Davis | BA10: =AK10*(1-(_xlfn.XLOOKUP(G10, Exchange_Rates!$B$8:$F$8, Exchange_Rates!$B$9:$F$9, 0)+J10)) -> 14339.462 | BB10: {=_xlfn.LET( _xlpm.raw_dt, SUBSTITUTE(TRIM(C10), ".", "/"), _xlpm.dt, IFERROR(DATEVALUE(_xlpm.raw_dt), C10), _xlpm.p_code, TRIM(E10), _xlpm.w_text, LOWER(_xlfn.XLOOKUP(_xlpm.p_code, Product_List!$B$2:$B$61, Product_List!$F$2:$F$61, "24")), _xlpm.m_count, _xlfn.IFS( ISNUMBER(SEARCH("36", _xlpm.w_text)), 36, ISNUMBER(SEARCH("3 yr", _xlpm.w_text)), 36, ISNUMBER(SEARCH("12", _xlpm.w_text)), 12, ISNUMBER(SEARCH("1 yr", _xlpm.w_text)), 12, TRUE, 24 ), IFERROR(EDATE(_xlpm.dt, _xlpm.m_count), "Proveri datum") )} -> 46482 | BC10: =BA10*AV10 -> 2581.1032
A11: TR-2025118 | B11: 46187 | C11: 46193 | D11: ="P-" & TEXT(VALUE(SUBSTITUTE(SUBSTITUTE(SUBSTITUTE(UPPER(TRIM('Sales_RAW(BEFORE)'!D11)), "P", ""), "-", ""), "_", "")),"000") -> P-004 | E11: =VLOOKUP(D11,Product_List!$A$2:$B$61,2,FALSE) -> Printer Plus 4 | F11: =_xlfn.XLOOKUP(E11,Product_List!$B$2:$B$61,Product_List!$E$2:$E$61,2) -> OfficeHub | G11: =VLOOKUP(E11,Product_List!$B$2:$C$61,2,FALSE) -> Electronics | H11: =SUBSTITUTE(SUBSTITUTE('Sales_RAW(BEFORE)'!G11,"kom",""),".","") -> 7 | I11: =VLOOKUP(E11,Product_List!$B$2:$D$61,3,FALSE) -> 364.79 | J11: =IF(IFERROR(VALUE(SUBSTITUTE(SUBSTITUTE(TRIM('Sales_RAW(BEFORE)'!I11), "%", ""), ",", ".")), 0) > 1, IFERROR(VALUE(SUBSTITUTE(SUBSTITUTE(TRIM('Sales_RAW(BEFORE)'!I11), "%", ""), ",", ".")), 0) / 100, IFERROR(VALUE(SUBSTITUTE(SUBSTITUTE(TRIM('Sales_RAW(BEFORE)'!I11), "%", ""), ",", ".")), 0)) -> 0.1 | K11: =IFERROR(H11*I11,0) -> 2553.53 | L11: {=_xlfn.LET( _xlpm.valuta, UPPER(TRIM('Sales_RAW(BEFORE)'!K11)), _xlfn.IFS( _xlpm.valuta = "", "", OR(_xlpm.valuta = "USD", _xlpm.valuta = "$"), "$", OR(_xlpm.valuta = "EUR", _xlpm.valuta = "€"), "€", TRUE, _xlpm.valuta ) )} -> $ | M11: ="E" & TEXT(VALUE(SUBSTITUTE(SUBSTITUTE(SUBSTITUTE(UPPER(TRIM('Sales_RAW(BEFORE)'!L11)), "EMP", ""), "E", ""), "-", "")),"000") -> E015 | N11: =_xlfn.XLOOKUP(M11,Employees!$D$2:$D$26,Employees!$A$2:$A$26) -> Sarah Jones | O11: =_xlfn.XLOOKUP(N11,Employees!$A$2:$A$26,Employees!$C$2:$C$26,2) -> Wholesale | P11: =PROPER('Sales_RAW(BEFORE)'!N11) -> South | Q11: =VLOOKUP(N11,Employees!$A$2:$B$26,2,FALSE) -> Boston | R11: =PROPER('Sales_RAW(BEFORE)'!P11) -> Stark Inc. | S11: =SUBSTITUTE(SUBSTITUTE('Sales_RAW(BEFORE)'!Q11,"EIN",""),":","") -> 986739414 | T11: sophia.gmail.com | U11: 348.471.3029 | V11: 450 Brown St. | W11: 58661 | X11: USA | Y11: =PROPER('Sales_RAW(BEFORE)'!W11) -> Credit Card | Z11: =PROPER('Sales_RAW(BEFORE)'!X11) -> Delivered | AA11: {=_xlfn.LET( _xlpm.val, TRIM(LOWER('Sales_RAW(BEFORE)'!Y11)), _xlfn.IFS( OR(_xlpm.val="yes", _xlpm.val="paid"), "Paid", OR(_xlpm.val="no", _xlpm.val="unpaid"), "Unpaid", OR(_xlpm.val="partial", _xlpm.val="partial paid"), "Partial", _xlpm.val="", "", TRUE, 'Sales_RAW(BEFORE)'!AY11 ) )} -> Paid | AB11: INV/2026/0118 | AC11: =PROPER('Sales_RAW(BEFORE)'!AA11) -> Online | AD11: =SUBSTITUTE(SUBSTITUTE(SUBSTITUTE(SUBSTITUTE('Sales_RAW(BEFORE)'!AB11,"st",""),"q",""),"Q",""),"uarter","") -> 3 | AE11: =TEXT(IFERROR(DATEVALUE('Sales_RAW(BEFORE)'!AC11 & " 1"), IFERROR(DATE(2025, 'Sales_RAW(BEFORE)'!AC11, 1), 'Sales_RAW(BEFORE)'!AC11)), "mmmm") -> June | AF11: =_xlfn.LET( _xlpm.raw, TRIM(SUBSTITUTE('Sales_RAW(BEFORE)'!AD11, "'", "")), _xlpm.num, IFERROR(VALUE(_xlpm.raw), 0), IF(_xlpm.num < 100, 2000 + _xlpm.num, _xlpm.num) ) -> 2026 | AG11: =PROPER('Sales_RAW(BEFORE)'!AE11) -> 15 | AH11: {=_xlfn.LET( _xlpm.val, LOWER(TRIM('Sales_RAW(BEFORE)'!AF11)), _xlfn.IFS( OR(_xlpm.val="", _xlpm.val="null", _xlpm.val="N/A", _xlpm.val="-", _xlpm.val="#N/A"), 0, ISNUMBER('Sales_RAW(BEFORE)'!AF11), 'Sales_RAW(BEFORE)'!AF11, TRUE, IFERROR(_xlfn.NUMBERVALUE(_xlpm.val), 0) ) )} -> 34 | AI11: =IF(IFERROR(VALUE(SUBSTITUTE(SUBSTITUTE(TRIM('Sales_RAW(BEFORE)'!AG11), "%", ""), ",", ".")), 0) > 1, IFERROR(VALUE(SUBSTITUTE(SUBSTITUTE(TRIM('Sales_RAW(BEFORE)'!AG11), "%", ""), ",", ".")), 0) / 100, IFERROR(VALUE(SUBSTITUTE(SUBSTITUTE(TRIM('Sales_RAW(BEFORE)'!AG11), "%", ""), ",", ".")), 0)) -> 0.08 | AJ11: =K11*AI11 -> 204.2824 | AK11: =AJ11+K11 -> 2757.8124 | AL11: =IFERROR(VALUE(SUBSTITUTE(SUBSTITUTE(SUBSTITUTE('Sales_RAW(BEFORE)'!AJ11,"$",""),"USD",""),",",".")),0) -> 40.91 | AM11: =SUBSTITUTE(SUBSTITUTE(PROPER('Sales_RAW(BEFORE)'!AK11), "Fed Ex", "FedEx"),"Fedex","FedEx") -> Dhl | AN11: 1Z412227285 | AO11: =SUBSTITUTE('Sales_RAW(BEFORE)'!AM11,"kg","") -> 22,73 | AP11: =_xlfn.LET( _xlpm.raw, UPPER(TRIM('Sales_RAW(BEFORE)'!AN11)), _xlpm.clean, RIGHT(_xlpm.raw, 1), IF(OR(_xlpm.raw="", _xlpm.raw="null"), "N/A", _xlpm.clean) ) -> C | AQ11: 56 | AR11: {=_xlfn.LET( _xlpm.raw, LOWER(TRIM('Sales_RAW(BEFORE)'!AP11)), _xlfn.IFS( OR(_xlpm.raw="", _xlpm.raw="null"), "", _xlpm.raw="excellent", 5, _xlpm.raw="good", 4, _xlpm.raw="average", 3, _xlpm.raw="poor", 2, _xlpm.raw="terrible", 1, ISNUMBER(SEARCH("/", _xlpm.raw)), _xlfn.NUMBERVALUE(_xlfn.TEXTBEFORE(_xlpm.raw, "/")), TRUE, IFERROR(_xlfn.NUMBERVALUE(_xlpm.raw), "") ) )} -> 5 | AV11: =IF(IFERROR(VALUE(SUBSTITUTE(SUBSTITUTE(TRIM('Sales_RAW(BEFORE)'!AT11), "%", ""), ",", ".")), 0) > 1, IFERROR(VALUE(SUBSTITUTE(SUBSTITUTE(TRIM('Sales_RAW(BEFORE)'!AT11), "%", ""), ",", ".")), 0) / 100, IFERROR(VALUE(SUBSTITUTE(SUBSTITUTE(TRIM('Sales_RAW(BEFORE)'!AT11), "%", ""), ",", ".")), 0)) -> 0.15 | AW11: =BA11*(_xlfn.XLOOKUP(N11,Employees!$A$2:$A$26,Employees!$E$2:$E$26,2)) -> 66.187498 | AX11: =PROPER('Sales_RAW(BEFORE)'!AV11) -> Sophia Johnson | AY11: =AX11 -> Sophia Johnson | BA11: =AK11*(1-(_xlfn.XLOOKUP(G11, Exchange_Rates!$B$8:$F$8, Exchange_Rates!$B$9:$F$9, 0)+J11)) -> 2206.2499 | BB11: {=_xlfn.LET( _xlpm.raw_dt, SUBSTITUTE(TRIM(C11), ".", "/"), _xlpm.dt, IFERROR(DATEVALUE(_xlpm.raw_dt), C11), _xlpm.p_code, TRIM(E11), _xlpm.w_text, LOWER(_xlfn.XLOOKUP(_xlpm.p_code, Product_List!$B$2:$B$61, Product_List!$F$2:$F$61, "24")), _xlpm.m_count, _xlfn.IFS( ISNUMBER(SEARCH("36", _xlpm.w_text)), 36, ISNUMBER(SEARCH("3 yr", _xlpm.w_text)), 36, ISNUMBER(SEARCH("12", _xlpm.w_text)), 12, ISNUMBER(SEARCH("1 yr", _xlpm.w_text)), 12, TRUE, 24 ), IFERROR(EDATE(_xlpm.dt, _xlpm.m_count), "Proveri datum") )} -> 46924 | BC11: =BA11*AV11 -> 330.93749
A12: TR-2025007 | B12: 45664 | C12: 45670 | D12: ="P-" & TEXT(VALUE(SUBSTITUTE(SUBSTITUTE(SUBSTITUTE(UPPER(TRIM('Sales_RAW(BEFORE)'!D12)), "P", ""), "-", ""), "_", "")),"000") -> P-039 | E12: =VLOOKUP(D12,Product_List!$A$2:$B$61,2,FALSE) -> Cable Plus 39 | F12: =_xlfn.XLOOKUP(E12,Product_List!$B$2:$B$61,Product_List!$E$2:$E$61,2) -> TechSupply Co | G12: =VLOOKUP(E12,Product_List!$B$2:$C$61,2,FALSE) -> Software | H12: =SUBSTITUTE(SUBSTITUTE('Sales_RAW(BEFORE)'!G12,"kom",""),".","") -> 39 | I12: =VLOOKUP(E12,Product_List!$B$2:$D$61,3,FALSE) -> 601.47 | J12: =IF(IFERROR(VALUE(SUBSTITUTE(SUBSTITUTE(TRIM('Sales_RAW(BEFORE)'!I12), "%", ""), ",", ".")), 0) > 1, IFERROR(VALUE(SUBSTITUTE(SUBSTITUTE(TRIM('Sales_RAW(BEFORE)'!I12), "%", ""), ",", ".")), 0) / 100, IFERROR(VALUE(SUBSTITUTE(SUBSTITUTE(TRIM('Sales_RAW(BEFORE)'!I12), "%", ""), ",", ".")), 0)) -> 0.05 | K12: =IFERROR(H12*I12,0) -> 23457.33 | L12: {=_xlfn.LET( _xlpm.valuta, UPPER(TRIM('Sales_RAW(BEFORE)'!K12)), _xlfn.IFS( _xlpm.valuta = "", "", OR(_xlpm.valuta = "USD", _xlpm.valuta = "$"), "$", OR(_xlpm.valuta = "EUR", _xlpm.valuta = "€"), "€", TRUE, _xlpm.valuta ) )} -> $ | M12: ="E" & TEXT(VALUE(SUBSTITUTE(SUBSTITUTE(SUBSTITUTE(UPPER(TRIM('Sales_RAW(BEFORE)'!L12)), "EMP", ""), "E", ""), "-", "")),"000") -> E009 | N12: =_xlfn.XLOOKUP(M12,Employees!$D$2:$D$26,Employees!$A$2:$A$26) -> Olivia Wilson | O12: =_xlfn.XLOOKUP(N12,Employees!$A$2:$A$26,Employees!$C$2:$C$26,2) -> Wholesale | P12: =PROPER('Sales_RAW(BEFORE)'!N12) -> North | Q12: =VLOOKUP(N12,Employees!$A$2:$B$26,2,FALSE) -> Miami | R12: =PROPER('Sales_RAW(BEFORE)'!P12) -> Initech Inc | S12: =SUBSTITUTE(SUBSTITUTE('Sales_RAW(BEFORE)'!Q12,"EIN",""),":","") -> 430278432 | T12: emma.gmail.com | U12: 859.401.7401 | V12: 415 Brown Street | W12: 57906 | X12: USA | Y12: =PROPER('Sales_RAW(BEFORE)'!W12) -> Credit Card | Z12: =PROPER('Sales_RAW(BEFORE)'!X12) -> Delivered | AA12: {=_xlfn.LET( _xlpm.val, TRIM(LOWER('Sales_RAW(BEFORE)'!Y12)), _xlfn.IFS( OR(_xlpm.val="yes", _xlpm.val="paid"), "Paid", OR(_xlpm.val="no", _xlpm.val="unpaid"), "Unpaid", OR(_xlpm.val="partial", _xlpm.val="partial paid"), "Partial", _xlpm.val="", "", TRUE, 'Sales_RAW(BEFORE)'!AY12 ) )} -> Partial | AB12: INV/2025/0007 | AC12: =PROPER('Sales_RAW(BEFORE)'!AA12) -> Online | AD12: =SUBSTITUTE(SUBSTITUTE(SUBSTITUTE(SUBSTITUTE('Sales_RAW(BEFORE)'!AB12,"st",""),"q",""),"Q",""),"uarter","") -> 1 | AE12: =TEXT(IFERROR(DATEVALUE('Sales_RAW(BEFORE)'!AC12 & " 1"), IFERROR(DATE(2025, 'Sales_RAW(BEFORE)'!AC12, 1), 'Sales_RAW(BEFORE)'!AC12)), "mmmm") -> January | AF12: =_xlfn.LET( _xlpm.raw, TRIM(SUBSTITUTE('Sales_RAW(BEFORE)'!AD12, "'", "")), _xlpm.num, IFERROR(VALUE(_xlpm.raw), 0), IF(_xlpm.num < 100, 2000 + _xlpm.num, _xlpm.num) ) -> 2025 | AG12: =PROPER('Sales_RAW(BEFORE)'!AE12) -> 15 | AH12: {=_xlfn.LET( _xlpm.val, LOWER(TRIM('Sales_RAW(BEFORE)'!AF12)), _xlfn.IFS( OR(_xlpm.val="", _xlpm.val="null", _xlpm.val="N/A", _xlpm.val="-", _xlpm.val="#N/A"), 0, ISNUMBER('Sales_RAW(BEFORE)'!AF12), 'Sales_RAW(BEFORE)'!AF12, TRUE, IFERROR(_xlfn.NUMBERVALUE(_xlpm.val), 0) ) )} -> 0 | AI12: =IF(IFERROR(VALUE(SUBSTITUTE(SUBSTITUTE(TRIM('Sales_RAW(BEFORE)'!AG12), "%", ""), ",", ".")), 0) > 1, IFERROR(VALUE(SUBSTITUTE(SUBSTITUTE(TRIM('Sales_RAW(BEFORE)'!AG12), "%", ""), ",", ".")), 0) / 100, IFERROR(VALUE(SUBSTITUTE(SUBSTITUTE(TRIM('Sales_RAW(BEFORE)'!AG12), "%", ""), ",", ".")), 0)) -> 0.08 | AJ12: =K12*AI12 -> 1876.5864 | AK12: =AJ12+K12 -> 25333.916 | AL12: =IFERROR(VALUE(SUBSTITUTE(SUBSTITUTE(SUBSTITUTE('Sales_RAW(BEFORE)'!AJ12,"$",""),"USD",""),",",".")),0) -> 4.45 | AM12: =SUBSTITUTE(SUBSTITUTE(PROPER('Sales_RAW(BEFORE)'!AK12), "Fed Ex", "FedEx"),"Fedex","FedEx") -> Usps | AN12: DH284346077 | AO12: =SUBSTITUTE('Sales_RAW(BEFORE)'!AM12,"kg","") -> 4.46 | AP12: =_xlfn.LET( _xlpm.raw, UPPER(TRIM('Sales_RAW(BEFORE)'!AN12)), _xlpm.clean, RIGHT(_xlpm.raw, 1), IF(OR(_xlpm.raw="", _xlpm.raw="null"), "N/A", _xlpm.clean) ) -> A | AQ12: 196 | AR12: {=_xlfn.LET( _xlpm.raw, LOWER(TRIM('Sales_RAW(BEFORE)'!AP12)), _xlfn.IFS( OR(_xlpm.raw="", _xlpm.raw="null"), "", _xlpm.raw="excellent", 5, _xlpm.raw="good", 4, _xlpm.raw="average", 3, _xlpm.raw="poor", 2, _xlpm.raw="terrible", 1, ISNUMBER(SEARCH("/", _xlpm.raw)), _xlfn.NUMBERVALUE(_xlfn.TEXTBEFORE(_xlpm.raw, "/")), TRUE, IFERROR(_xlfn.NUMBERVALUE(_xlpm.raw), "") ) )} -> 4 | AV12: =IF(IFERROR(VALUE(SUBSTITUTE(SUBSTITUTE(TRIM('Sales_RAW(BEFORE)'!AT12), "%", ""), ",", ".")), 0) > 1, IFERROR(VALUE(SUBSTITUTE(SUBSTITUTE(TRIM('Sales_RAW(BEFORE)'!AT12), "%", ""), ",", ".")), 0) / 100, IFERROR(VALUE(SUBSTITUTE(SUBSTITUTE(TRIM('Sales_RAW(BEFORE)'!AT12), "%", ""), ",", ".")), 0)) -> 0 | AW12: =BA12*(_xlfn.XLOOKUP(N12,Employees!$A$2:$A$26,Employees!$E$2:$E$26,2)) -> 608.01399 | AX12: =PROPER('Sales_RAW(BEFORE)'!AV12) -> Emma Anderson | AY12: =AX12 -> Emma Anderson | BA12: =AK12*(1-(_xlfn.XLOOKUP(G12, Exchange_Rates!$B$8:$F$8, Exchange_Rates!$B$9:$F$9, 0)+J12)) -> 20267.133 | BB12: {=_xlfn.LET( _xlpm.raw_dt, SUBSTITUTE(TRIM(C12), ".", "/"), _xlpm.dt, IFERROR(DATEVALUE(_xlpm.raw_dt), C12), _xlpm.p_code, TRIM(E12), _xlpm.w_text, LOWER(_xlfn.XLOOKUP(_xlpm.p_code, Product_List!$B$2:$B$61, Product_List!$F$2:$F$61, "24")), _xlpm.m_count, _xlfn.IFS( ISNUMBER(SEARCH("36", _xlpm.w_text)), 36, ISNUMBER(SEARCH("3 yr", _xlpm.w_text)), 36, ISNUMBER(SEARCH("12", _xlpm.w_text)), 12, ISNUMBER(SEARCH("1 yr", _xlpm.w_text)), 12, TRUE, 24 ), IFERROR(EDATE(_xlpm.dt, _xlpm.m_count), "Proveri datum") )} -> 46035 | BC12: =BA12*AV12 -> 0
A13: TR-2025008 | B13: 45858 | C13: 45867 | D13: ="P-" & TEXT(VALUE(SUBSTITUTE(SUBSTITUTE(SUBSTITUTE(UPPER(TRIM('Sales_RAW(BEFORE)'!D13)), "P", ""), "-", ""), "_", "")),"000") -> P-040 | E13: =VLOOKUP(D13,Product_List!$A$2:$B$61,2,FALSE) -> Monitor Plus 40 | F13: =_xlfn.XLOOKUP(E13,Product_List!$B$2:$B$61,Product_List!$E$2:$E$61,2) -> TechSupply Co | G13: =VLOOKUP(E13,Product_List!$B$2:$C$61,2,FALSE) -> Software | H13: =SUBSTITUTE(SUBSTITUTE('Sales_RAW(BEFORE)'!G13,"kom",""),".","") -> 31 | I13: =VLOOKUP(E13,Product_List!$B$2:$D$61,3,FALSE) -> 98.06 | J13: =IF(IFERROR(VALUE(SUBSTITUTE(SUBSTITUTE(TRIM('Sales_RAW(BEFORE)'!I13), "%", ""), ",", ".")), 0) > 1, IFERROR(VALUE(SUBSTITUTE(SUBSTITUTE(TRIM('Sales_RAW(BEFORE)'!I13), "%", ""), ",", ".")), 0) / 100, IFERROR(VALUE(SUBSTITUTE(SUBSTITUTE(TRIM('Sales_RAW(BEFORE)'!I13), "%", ""), ",", ".")), 0)) -> 0.05 | K13: =IFERROR(H13*I13,0) -> 3039.86 | L13: {=_xlfn.LET( _xlpm.valuta, UPPER(TRIM('Sales_RAW(BEFORE)'!K13)), _xlfn.IFS( _xlpm.valuta = "", "", OR(_xlpm.valuta = "USD", _xlpm.valuta = "$"), "$", OR(_xlpm.valuta = "EUR", _xlpm.valuta = "€"), "€", TRUE, _xlpm.valuta ) )} -> $ | M13: ="E" & TEXT(VALUE(SUBSTITUTE(SUBSTITUTE(SUBSTITUTE(UPPER(TRIM('Sales_RAW(BEFORE)'!L13)), "EMP", ""), "E", ""), "-", "")),"000") -> E013 | N13: =_xlfn.XLOOKUP(M13,Employees!$D$2:$D$26,Employees!$A$2:$A$26) -> Robert Williams | O13: =_xlfn.XLOOKUP(N13,Employees!$A$2:$A$26,Employees!$C$2:$C$26,2) -> Wholesale | P13: =PROPER('Sales_RAW(BEFORE)'!N13) -> West | Q13: =VLOOKUP(N13,Employees!$A$2:$B$26,2,FALSE) -> Houston | R13: =PROPER('Sales_RAW(BEFORE)'!P13) -> Globex Inc. | S13: =SUBSTITUTE(SUBSTITUTE('Sales_RAW(BEFORE)'!Q13,"EIN",""),":","") -> 579768106 | T13: michael.gmail.com | U13: 574.293.8241 | V13: 523 Smith Street | W13: 84419 | X13: USA | Y13: =PROPER('Sales_RAW(BEFORE)'!W13) -> Paypal | Z13: =PROPER('Sales_RAW(BEFORE)'!X13) -> Delivered | AA13: {=_xlfn.LET( _xlpm.val, TRIM(LOWER('Sales_RAW(BEFORE)'!Y13)), _xlfn.IFS( OR(_xlpm.val="yes", _xlpm.val="paid"), "Paid", OR(_xlpm.val="no", _xlpm.val="unpaid"), "Unpaid", OR(_xlpm.val="partial", _xlpm.val="partial paid"), "Partial", _xlpm.val="", "", TRUE, 'Sales_RAW(BEFORE)'!AY13 ) )} -> Paid | AB13: INV/2025/0008 | AC13: =PROPER('Sales_RAW(BEFORE)'!AA13) -> Online | AD13: =SUBSTITUTE(SUBSTITUTE(SUBSTITUTE(SUBSTITUTE('Sales_RAW(BEFORE)'!AB13,"st",""),"q",""),"Q",""),"uarter","") -> 3 | AE13: =TEXT(IFERROR(DATEVALUE('Sales_RAW(BEFORE)'!AC13 & " 1"), IFERROR(DATE(2025, 'Sales_RAW(BEFORE)'!AC13, 1), 'Sales_RAW(BEFORE)'!AC13)), "mmmm") -> July | AF13: =_xlfn.LET( _xlpm.raw, TRIM(SUBSTITUTE('Sales_RAW(BEFORE)'!AD13, "'", "")), _xlpm.num, IFERROR(VALUE(_xlpm.raw), 0), IF(_xlpm.num < 100, 2000 + _xlpm.num, _xlpm.num) ) -> 2025 | AG13: =PROPER('Sales_RAW(BEFORE)'!AE13) -> 15 | AH13: {=_xlfn.LET( _xlpm.val, LOWER(TRIM('Sales_RAW(BEFORE)'!AF13)), _xlfn.IFS( OR(_xlpm.val="", _xlpm.val="null", _xlpm.val="N/A", _xlpm.val="-", _xlpm.val="#N/A"), 0, ISNUMBER('Sales_RAW(BEFORE)'!AF13), 'Sales_RAW(BEFORE)'!AF13, TRUE, IFERROR(_xlfn.NUMBERVALUE(_xlpm.val), 0) ) )} -> 3 | AI13: =IF(IFERROR(VALUE(SUBSTITUTE(SUBSTITUTE(TRIM('Sales_RAW(BEFORE)'!AG13), "%", ""), ",", ".")), 0) > 1, IFERROR(VALUE(SUBSTITUTE(SUBSTITUTE(TRIM('Sales_RAW(BEFORE)'!AG13), "%", ""), ",", ".")), 0) / 100, IFERROR(VALUE(SUBSTITUTE(SUBSTITUTE(TRIM('Sales_RAW(BEFORE)'!AG13), "%", ""), ",", ".")), 0)) -> 0.08 | AJ13: =K13*AI13 -> 243.1888 | AK13: =AJ13+K13 -> 3283.0488 | AL13: =IFERROR(VALUE(SUBSTITUTE(SUBSTITUTE(SUBSTITUTE('Sales_RAW(BEFORE)'!AJ13,"$",""),"USD",""),",",".")),0) -> 10 | AM13: =SUBSTITUTE(SUBSTITUTE(PROPER('Sales_RAW(BEFORE)'!AK13), "Fed Ex", "FedEx"),"Fedex","FedEx") -> FedEx | AN13: DH946518213 | AO13: =SUBSTITUTE('Sales_RAW(BEFORE)'!AM13,"kg","") -> 25,01 | AP13: =_xlfn.LET( _xlpm.raw, UPPER(TRIM('Sales_RAW(BEFORE)'!AN13)), _xlpm.clean, RIGHT(_xlpm.raw, 1), IF(OR(_xlpm.raw="", _xlpm.raw="null"), "N/A", _xlpm.clean) ) -> B | AQ13: 81 | AR13: {=_xlfn.LET( _xlpm.raw, LOWER(TRIM('Sales_RAW(BEFORE)'!AP13)), _xlfn.IFS( OR(_xlpm.raw="", _xlpm.raw="null"), "", _xlpm.raw="excellent", 5, _xlpm.raw="good", 4, _xlpm.raw="average", 3, _xlpm.raw="poor", 2, _xlpm.raw="terrible", 1, ISNUMBER(SEARCH("/", _xlpm.raw)), _xlfn.NUMBERVALUE(_xlfn.TEXTBEFORE(_xlpm.raw, "/")), TRUE, IFERROR(_xlfn.NUMBERVALUE(_xlpm.raw), "") ) )} -> 5 | AV13: =IF(IFERROR(VALUE(SUBSTITUTE(SUBSTITUTE(TRIM('Sales_RAW(BEFORE)'!AT13), "%", ""), ",", ".")), 0) > 1, IFERROR(VALUE(SUBSTITUTE(SUBSTITUTE(TRIM('Sales_RAW(BEFORE)'!AT13), "%", ""), ",", ".")), 0) / 100, IFERROR(VALUE(SUBSTITUTE(SUBSTITUTE(TRIM('Sales_RAW(BEFORE)'!AT13), "%", ""), ",", ".")), 0)) -> 0.3 | AW13: =BA13*(_xlfn.XLOOKUP(N13,Employees!$A$2:$A$26,Employees!$E$2:$E$26,2)) -> 131.32195 | AX13: =PROPER('Sales_RAW(BEFORE)'!AV13) -> Michael Anderson | AY13: =AX13 -> Michael Anderson | BA13: =AK13*(1-(_xlfn.XLOOKUP(G13, Exchange_Rates!$B$8:$F$8, Exchange_Rates!$B$9:$F$9, 0)+J13)) -> 2626.439 | BB13: {=_xlfn.LET( _xlpm.raw_dt, SUBSTITUTE(TRIM(C13), ".", "/"), _xlpm.dt, IFERROR(DATEVALUE(_xlpm.raw_dt), C13), _xlpm.p_code, TRIM(E13), _xlpm.w_text, LOWER(_xlfn.XLOOKUP(_xlpm.p_code, Product_List!$B$2:$B$61, Product_List!$F$2:$F$61, "24")), _xlpm.m_count, _xlfn.IFS( ISNUMBER(SEARCH("36", _xlpm.w_text)), 36, ISNUMBER(SEARCH("3 yr", _xlpm.w_text)), 36, ISNUMBER(SEARCH("12", _xlpm.w_text)), 12, ISNUMBER(SEARCH("1 yr", _xlpm.w_text)), 12, TRUE, 24 ), IFERROR(EDATE(_xlpm.dt, _xlpm.m_count), "Proveri datum") )} -> 46597 | BC13: =BA13*AV13 -> 787.93171
A14: TR-2025009 | B14: 45861 | C14: 45864 | D14: ="P-" & TEXT(VALUE(SUBSTITUTE(SUBSTITUTE(SUBSTITUTE(UPPER(TRIM('Sales_RAW(BEFORE)'!D14)), "P", ""), "-", ""), "_", "")),"000") -> P-024 | E14: =VLOOKUP(D14,Product_List!$A$2:$B$61,2,FALSE) -> Chair Plus 24 | F14: =_xlfn.XLOOKUP(E14,Product_List!$B$2:$B$61,Product_List!$E$2:$E$61,2) -> TechSupply Co | G14: =VLOOKUP(E14,Product_List!$B$2:$C$61,2,FALSE) -> Electronics | H14: =SUBSTITUTE(SUBSTITUTE('Sales_RAW(BEFORE)'!G14,"kom",""),".","") -> 26 | I14: =VLOOKUP(E14,Product_List!$B$2:$D$61,3,FALSE) -> 95.7 | J14: =IF(IFERROR(VALUE(SUBSTITUTE(SUBSTITUTE(TRIM('Sales_RAW(BEFORE)'!I14), "%", ""), ",", ".")), 0) > 1, IFERROR(VALUE(SUBSTITUTE(SUBSTITUTE(TRIM('Sales_RAW(BEFORE)'!I14), "%", ""), ",", ".")), 0) / 100, IFERROR(VALUE(SUBSTITUTE(SUBSTITUTE(TRIM('Sales_RAW(BEFORE)'!I14), "%", ""), ",", ".")), 0)) -> 0.1 | K14: =IFERROR(H14*I14/Exchange_Rates!H2,0) -> 2664.0257 | L14: {=_xlfn.LET( _xlpm.valuta, UPPER(TRIM('Sales_RAW(BEFORE)'!K14)), _xlfn.IFS( _xlpm.valuta = "", "", OR(_xlpm.valuta = "USD", _xlpm.valuta = "$"), "$", OR(_xlpm.valuta = "EUR", _xlpm.valuta = "€"), "€", TRUE, _xlpm.valuta ) )} -> € | M14: ="E" & TEXT(VALUE(SUBSTITUTE(SUBSTITUTE(SUBSTITUTE(UPPER(TRIM('Sales_RAW(BEFORE)'!L14)), "EMP", ""), "E", ""), "-", "")),"000") -> E002 | N14: =_xlfn.XLOOKUP(M14,Employees!$D$2:$D$26,Employees!$A$2:$A$26) -> Sarah Wilson | O14: =_xlfn.XLOOKUP(N14,Employees!$A$2:$A$26,Employees!$C$2:$C$26,2) -> Online | P14: =PROPER('Sales_RAW(BEFORE)'!N14) -> East | Q14: =VLOOKUP(N14,Employees!$A$2:$B$26,2,FALSE) -> Los Angeles | R14: =PROPER('Sales_RAW(BEFORE)'!P14) -> Wayne Inc | S14: =SUBSTITUTE(SUBSTITUTE('Sales_RAW(BEFORE)'!Q14,"EIN",""),":","") -> 812640864 | T14: N/A | U14: (497) 830-8081 | V14: 628 Smith Street | W14: - | X14: USA | Y14: =PROPER('Sales_RAW(BEFORE)'!W14) -> Credit Card | Z14: =PROPER('Sales_RAW(BEFORE)'!X14) -> Delivered | AA14: {=_xlfn.LET( _xlpm.val, TRIM(LOWER('Sales_RAW(BEFORE)'!Y14)), _xlfn.IFS( OR(_xlpm.val="yes", _xlpm.val="paid"), "Paid", OR(_xlpm.val="no", _xlpm.val="unpaid"), "Unpaid", OR(_xlpm.val="partial", _xlpm.val="partial paid"), "Partial", _xlpm.val="", "", TRUE, 'Sales_RAW(BEFORE)'!AY14 ) )} -> Unpaid | AB14: INV/2025/0009 | AC14: =PROPER('Sales_RAW(BEFORE)'!AA14) -> Online | AD14: =SUBSTITUTE(SUBSTITUTE(SUBSTITUTE(SUBSTITUTE('Sales_RAW(BEFORE)'!AB14,"st",""),"q",""),"Q",""),"uarter","") -> 1 | AE14: =TEXT(IFERROR(DATEVALUE('Sales_RAW(BEFORE)'!AC14 & " 1"), IFERROR(DATE(2025, 'Sales_RAW(BEFORE)'!AC14, 1), 'Sales_RAW(BEFORE)'!AC14)), "mmmm") -> July | AF14: =_xlfn.LET( _xlpm.raw, TRIM(SUBSTITUTE('Sales_RAW(BEFORE)'!AD14, "'", "")), _xlpm.num, IFERROR(VALUE(_xlpm.raw), 0), IF(_xlpm.num < 100, 2000 + _xlpm.num, _xlpm.num) ) -> 2025 | AG14: =PROPER('Sales_RAW(BEFORE)'!AE14) -> Net 60 | AH14: {=_xlfn.LET( _xlpm.val, LOWER(TRIM('Sales_RAW(BEFORE)'!AF14)), _xlfn.IFS( OR(_xlpm.val="", _xlpm.val="null", _xlpm.val="N/A", _xlpm.val="-", _xlpm.val="#N/A"), 0, ISNUMBER('Sales_RAW(BEFORE)'!AF14), 'Sales_RAW(BEFORE)'!AF14, TRUE, IFERROR(_xlfn.NUMBERVALUE(_xlpm.val), 0) ) )} -> 0 | AI14: =IF(IFERROR(VALUE(SUBSTITUTE(SUBSTITUTE(TRIM('Sales_RAW(BEFORE)'!AG14), "%", ""), ",", ".")), 0) > 1, IFERROR(VALUE(SUBSTITUTE(SUBSTITUTE(TRIM('Sales_RAW(BEFORE)'!AG14), "%", ""), ",", ".")), 0) / 100, IFERROR(VALUE(SUBSTITUTE(SUBSTITUTE(TRIM('Sales_RAW(BEFORE)'!AG14), "%", ""), ",", ".")), 0)) -> 0.08 | AJ14: =K14*AI14 -> 213.12206 | AK14: =AJ14+K14 -> 2877.1478 | AL14: =IFERROR(VALUE(SUBSTITUTE(SUBSTITUTE(SUBSTITUTE('Sales_RAW(BEFORE)'!AJ14,"$",""),"USD",""),",",".")),0) -> 7.93 | AM14: =SUBSTITUTE(SUBSTITUTE(PROPER('Sales_RAW(BEFORE)'!AK14), "Fed Ex", "FedEx"),"Fedex","FedEx") -> FedEx | AN14: DH260323700 | AO14: =SUBSTITUTE('Sales_RAW(BEFORE)'!AM14,"kg","") -> 4,43 | AP14: =_xlfn.LET( _xlpm.raw, UPPER(TRIM('Sales_RAW(BEFORE)'!AN14)), _xlpm.clean, RIGHT(_xlpm.raw, 1), IF(OR(_xlpm.raw="", _xlpm.raw="null"), "N/A", _xlpm.clean) ) -> B | AQ14: 205 | AR14: {=_xlfn.LET( _xlpm.raw, LOWER(TRIM('Sales_RAW(BEFORE)'!AP14)), _xlfn.IFS( OR(_xlpm.raw="", _xlpm.raw="null"), "", _xlpm.raw="excellent", 5, _xlpm.raw="good", 4, _xlpm.raw="average", 3, _xlpm.raw="poor", 2, _xlpm.raw="terrible", 1, ISNUMBER(SEARCH("/", _xlpm.raw)), _xlfn.NUMBERVALUE(_xlfn.TEXTBEFORE(_xlpm.raw, "/")), TRUE, IFERROR(_xlfn.NUMBERVALUE(_xlpm.raw), "") ) )} -> 1 | AS14: late delivery!! | AT14: Yes | AV14: =IF(IFERROR(VALUE(SUBSTITUTE(SUBSTITUTE(TRIM('Sales_RAW(BEFORE)'!AT14), "%", ""), ",", ".")), 0) > 1, IFERROR(VALUE(SUBSTITUTE(SUBSTITUTE(TRIM('Sales_RAW(BEFORE)'!AT14), "%", ""), ",", ".")), 0) / 100, IFERROR(VALUE(SUBSTITUTE(SUBSTITUTE(TRIM('Sales_RAW(BEFORE)'!AT14), "%", ""), ",", ".")), 0)) -> 0.3 | AW14: =BA14*(_xlfn.XLOOKUP(N14,Employees!$A$2:$A$26,Employees!$E$2:$E$26,2)) -> 69.051546 | AX14: =PROPER('Sales_RAW(BEFORE)'!AV14) -> Michael Jones | AY14: =AX14 -> Michael Jones | BA14: =AK14*(1-(_xlfn.XLOOKUP(G14, Exchange_Rates!$B$8:$F$8, Exchange_Rates!$B$9:$F$9, 0)+J14)) -> 2301.7182 | BB14: {=_xlfn.LET( _xlpm.raw_dt, SUBSTITUTE(TRIM(C14), ".", "/"), _xlpm.dt, IFERROR(DATEVALUE(_xlpm.raw_dt), C14), _xlpm.p_code, TRIM(E14), _xlpm.w_text, LOWER(_xlfn.XLOOKUP(_xlpm.p_code, Product_List!$B$2:$B$61, Product_List!$F$2:$F$61, "24")), _xlpm.m_count, _xlfn.IFS( ISNUMBER(SEARCH("36", _xlpm.w_text)), 36, ISNUMBER(SEARCH("3 yr", _xlpm.w_text)), 36, ISNUMBER(SEARCH("12", _xlpm.w_text)), 12, ISNUMBER(SEARCH("1 yr", _xlpm.w_text)), 12, TRUE, 24 ), IFERROR(EDATE(_xlpm.dt, _xlpm.m_count), "Proveri datum") )} -> 46594 | BC14: =BA14*AV14 -> 690.51546
A15: TR-2025010 | B15: 45703 | C15: null | D15: ="P-" & TEXT(VALUE(SUBSTITUTE(SUBSTITUTE(SUBSTITUTE(UPPER(TRIM('Sales_RAW(BEFORE)'!D15)), "P", ""), "-", ""), "_", "")),"000") -> P-058 | E15: =VLOOKUP(D15,Product_List!$A$2:$B$61,2,FALSE) -> Laptop Pro 58 | F15: =_xlfn.XLOOKUP(E15,Product_List!$B$2:$B$61,Product_List!$E$2:$E$61,2) -> Global Distrib | G15: =VLOOKUP(E15,Product_List!$B$2:$C$61,2,FALSE) -> Furniture | H15: =SUBSTITUTE(SUBSTITUTE('Sales_RAW(BEFORE)'!G15,"kom",""),".","") -> 35 | I15: =VLOOKUP(E15,Product_List!$B$2:$D$61,3,FALSE) -> 711 | J15: =IF(IFERROR(VALUE(SUBSTITUTE(SUBSTITUTE(TRIM('Sales_RAW(BEFORE)'!I15), "%", ""), ",", ".")), 0) > 1, IFERROR(VALUE(SUBSTITUTE(SUBSTITUTE(TRIM('Sales_RAW(BEFORE)'!I15), "%", ""), ",", ".")), 0) / 100, IFERROR(VALUE(SUBSTITUTE(SUBSTITUTE(TRIM('Sales_RAW(BEFORE)'!I15), "%", ""), ",", ".")), 0)) -> 0 | K15: =(H15*I15)/(HLOOKUP(AE15,Exchange_Rates!$B$1:$M$2,2,FALSE)) -> 26931.818 | L15: {=_xlfn.LET( _xlpm.valuta, UPPER(TRIM('Sales_RAW(BEFORE)'!K15)), _xlfn.IFS( _xlpm.valuta = "", "", OR(_xlpm.valuta = "USD", _xlpm.valuta = "$"), "$", OR(_xlpm.valuta = "EUR", _xlpm.valuta = "€"), "€", TRUE, _xlpm.valuta ) )} -> € | M15: ="E" & TEXT(VALUE(SUBSTITUTE(SUBSTITUTE(SUBSTITUTE(UPPER(TRIM('Sales_RAW(BEFORE)'!L15)), "EMP", ""), "E", ""), "-", "")),"000") -> E001 | N15: =_xlfn.XLOOKUP(M15,Employees!$D$2:$D$26,Employees!$A$2:$A$26) -> Sarah Wilson | O15: =_xlfn.XLOOKUP(N15,Employees!$A$2:$A$26,Employees!$C$2:$C$26,2) -> Online | P15: =PROPER('Sales_RAW(BEFORE)'!N15) -> South | Q15: =VLOOKUP(N15,Employees!$A$2:$B$26,2,FALSE) -> Los Angeles | R15: =PROPER('Sales_RAW(BEFORE)'!P15) -> Globex Inc | S15: =SUBSTITUTE(SUBSTITUTE('Sales_RAW(BEFORE)'!Q15,"EIN",""),":","") -> 460257622 | T15: john.company.com | U15: (851) 767-8144 | V15: 902 Taylor Street | W15: 23252 | X15: USA | Y15: =PROPER('Sales_RAW(BEFORE)'!W15) -> Paypal | Z15: =PROPER('Sales_RAW(BEFORE)'!X15) -> Delivered | AA15: {=_xlfn.LET( _xlpm.val, TRIM(LOWER('Sales_RAW(BEFORE)'!Y15)), _xlfn.IFS( OR(_xlpm.val="yes", _xlpm.val="paid"), "Paid", OR(_xlpm.val="no", _xlpm.val="unpaid"), "Unpaid", OR(_xlpm.val="partial", _xlpm.val="partial paid"), "Partial", _xlpm.val="", "", TRUE, 'Sales_RAW(BEFORE)'!AY15 ) )} -> Paid | AB15: INV/2025/0010 | AC15: =PROPER('Sales_RAW(BEFORE)'!AA15) -> Store | AD15: =SUBSTITUTE(SUBSTITUTE(SUBSTITUTE(SUBSTITUTE('Sales_RAW(BEFORE)'!AB15,"st",""),"q",""),"Q",""),"uarter","") -> 1 | AE15: =TEXT(IFERROR(DATEVALUE('Sales_RAW(BEFORE)'!AC15 & " 1"), IFERROR(DATE(2025, 'Sales_RAW(BEFORE)'!AC15, 1), 'Sales_RAW(BEFORE)'!AC15)), "mmmm") -> February | AF15: =_xlfn.LET( _xlpm.raw, TRIM(SUBSTITUTE('Sales_RAW(BEFORE)'!AD15, "'", "")), _xlpm.num, IFERROR(VALUE(_xlpm.raw), 0), IF(_xlpm.num < 100, 2000 + _xlpm.num, _xlpm.num) ) -> 2025 | AG15: =PROPER('Sales_RAW(BEFORE)'!AE15) -> 15 | AH15: {=_xlfn.LET( _xlpm.val, LOWER(TRIM('Sales_RAW(BEFORE)'!AF15)), _xlfn.IFS( OR(_xlpm.val="", _xlpm.val="null", _xlpm.val="N/A", _xlpm.val="-", _xlpm.val="#N/A"), 0, ISNUMBER('Sales_RAW(BEFORE)'!AF15), 'Sales_RAW(BEFORE)'!AF15, TRUE, IFERROR(_xlfn.NUMBERVALUE(_xlpm.val), 0) ) )} -> 48 | AI15: =IF(IFERROR(VALUE(SUBSTITUTE(SUBSTITUTE(TRIM('Sales_RAW(BEFORE)'!AG15), "%", ""), ",", ".")), 0) > 1, IFERROR(VALUE(SUBSTITUTE(SUBSTITUTE(TRIM('Sales_RAW(BEFORE)'!AG15), "%", ""), ",", ".")), 0) / 100, IFERROR(VALUE(SUBSTITUTE(SUBSTITUTE(TRIM('Sales_RAW(BEFORE)'!AG15), "%", ""), ",", ".")), 0)) -> 0.08 | AJ15: =K15*AI15 -> 2154.5455 | AK15: =AJ15+K15 -> 29086.364 | AL15: =IFERROR(VALUE(SUBSTITUTE(SUBSTITUTE(SUBSTITUTE('Sales_RAW(BEFORE)'!AJ15,"$",""),"USD",""),",",".")),0) -> 23.61 | AM15: =SUBSTITUTE(SUBSTITUTE(PROPER('Sales_RAW(BEFORE)'!AK15), "Fed Ex", "FedEx"),"Fedex","FedEx") -> FedEx | AN15: FX878058375 | AO15: =SUBSTITUTE('Sales_RAW(BEFORE)'!AM15,"kg","") -> 26.6 | AP15: =_xlfn.LET( _xlpm.raw, UPPER(TRIM('Sales_RAW(BEFORE)'!AN15)), _xlpm.clean, RIGHT(_xlpm.raw, 1), IF(OR(_xlpm.raw="", _xlpm.raw="null"), "N/A", _xlpm.clean) ) -> C | AQ15: 299 | AR15: {=_xlfn.LET( _xlpm.raw, LOWER(TRIM('Sales_RAW(BEFORE)'!AP15)), _xlfn.IFS( OR(_xlpm.raw="", _xlpm.raw="null"), "", _xlpm.raw="excellent", 5, _xlpm.raw="good", 4, _xlpm.raw="average", 3, _xlpm.raw="poor", 2, _xlpm.raw="terrible", 1, ISNUMBER(SEARCH("/", _xlpm.raw)), _xlfn.NUMBERVALUE(_xlfn.TEXTBEFORE(_xlpm.raw, "/")), TRUE, IFERROR(_xlfn.NUMBERVALUE(_xlpm.raw), "") ) )} -> 3 | AV15: =IF(IFERROR(VALUE(SUBSTITUTE(SUBSTITUTE(TRIM('Sales_RAW(BEFORE)'!AT15), "%", ""), ",", ".")), 0) > 1, IFERROR(VALUE(SUBSTITUTE(SUBSTITUTE(TRIM('Sales_RAW(BEFORE)'!AT15), "%", ""), ",", ".")), 0) / 100, IFERROR(VALUE(SUBSTITUTE(SUBSTITUTE(TRIM('Sales_RAW(BEFORE)'!AT15), "%", ""), ",", ".")), 0)) -> 0.25 | AW15: =BA15*(_xlfn.XLOOKUP(N15,Employees!$A$2:$A$26,Employees!$E$2:$E$26,2)) -> 785.33182 | AX15: =PROPER('Sales_RAW(BEFORE)'!AV15) -> John Davis | AY15: =AX15 -> John Davis | BA15: =AK15*(1-(_xlfn.XLOOKUP(G15, Exchange_Rates!$B$8:$F$8, Exchange_Rates!$B$9:$F$9, 0)+J15)) -> 26177.727 | BB15: {=_xlfn.LET( _xlpm.raw_dt, SUBSTITUTE(TRIM(C15), ".", "/"), _xlpm.dt, IFERROR(DATEVALUE(_xlpm.raw_dt), C15), _xlpm.p_code, TRIM(E15), _xlpm.w_text, LOWER(_xlfn.XLOOKUP(_xlpm.p_code, Product_List!$B$2:$B$61, Product_List!$F$2:$F$61, "24")), _xlpm.m_count, _xlfn.IFS( ISNUMBER(SEARCH("36", _xlpm.w_text)), 36, ISNUMBER(SEARCH("3 yr", _xlpm.w_text)), 36, ISNUMBER(SEARCH("12", _xlpm.w_text)), 12, ISNUMBER(SEARCH("1 yr", _xlpm.w_text)), 12, TRUE, 24 ), IFERROR(EDATE(_xlpm.dt, _xlpm.m_count), "Empty") )} -> Empty | BC15: =BA15*AV15 -> 6544.4318
A16: TR-2025011 | B16: 45701 | C16: 45705 | D16: ="P-" & TEXT(VALUE(SUBSTITUTE(SUBSTITUTE(SUBSTITUTE(UPPER(TRIM('Sales_RAW(BEFORE)'!D16)), "P", ""), "-", ""), "_", "")),"000") -> P-009 | E16: =VLOOKUP(D16,Product_List!$A$2:$B$61,2,FALSE) -> Chair Plus 9 | F16: =_xlfn.XLOOKUP(E16,Product_List!$B$2:$B$61,Product_List!$E$2:$E$61,2) -> BestParts | G16: =VLOOKUP(E16,Product_List!$B$2:$C$61,2,FALSE) -> Office | H16: =SUBSTITUTE(SUBSTITUTE('Sales_RAW(BEFORE)'!G16,"kom",""),".","") -> 5 | I16: =VLOOKUP(E16,Product_List!$B$2:$D$61,3,FALSE) -> 813.33 | J16: =IF(IFERROR(VALUE(SUBSTITUTE(SUBSTITUTE(TRIM('Sales_RAW(BEFORE)'!I16), "%", ""), ",", ".")), 0) > 1, IFERROR(VALUE(SUBSTITUTE(SUBSTITUTE(TRIM('Sales_RAW(BEFORE)'!I16), "%", ""), ",", ".")), 0) / 100, IFERROR(VALUE(SUBSTITUTE(SUBSTITUTE(TRIM('Sales_RAW(BEFORE)'!I16), "%", ""), ",", ".")), 0)) -> 0.05 | K16: =IFERROR(H16*I16,0) -> 4066.65 | L16: {=_xlfn.LET( _xlpm.valuta, UPPER(TRIM('Sales_RAW(BEFORE)'!K16)), _xlfn.IFS( _xlpm.valuta = "", "", OR(_xlpm.valuta = "USD", _xlpm.valuta = "$"), "$", OR(_xlpm.valuta = "EUR", _xlpm.valuta = "€"), "€", TRUE, _xlpm.valuta ) )} -> $ | M16: ="E" & TEXT(VALUE(SUBSTITUTE(SUBSTITUTE(SUBSTITUTE(UPPER(TRIM('Sales_RAW(BEFORE)'!L16)), "EMP", ""), "E", ""), "-", "")),"000") -> E023 | N16: =_xlfn.XLOOKUP(M16,Employees!$D$2:$D$26,Employees!$A$2:$A$26) -> Laura Anderson | O16: =_xlfn.XLOOKUP(N16,Employees!$A$2:$A$26,Employees!$C$2:$C$26,2) -> Sales | P16: =PROPER('Sales_RAW(BEFORE)'!N16) -> North | Q16: =VLOOKUP(N16,Employees!$A$2:$B$26,2,FALSE) -> Seattle | R16: =PROPER('Sales_RAW(BEFORE)'!P16) -> Acme Ltd. | S16: =SUBSTITUTE(SUBSTITUTE('Sales_RAW(BEFORE)'!Q16,"EIN",""),":","") -> 640883830 | T16: emma.yahoo.com | U16: 555.680.1788 | V16: 580 Brown Street | W16: 76306 | X16: USA | Y16: =PROPER('Sales_RAW(BEFORE)'!W16) -> Wire Transfer | Z16: =PROPER('Sales_RAW(BEFORE)'!X16) -> Delivered | AA16: {=_xlfn.LET( _xlpm.val, TRIM(LOWER('Sales_RAW(BEFORE)'!Y16)), _xlfn.IFS( OR(_xlpm.val="yes", _xlpm.val="paid"), "Paid", OR(_xlpm.val="no", _xlpm.val="unpaid"), "Unpaid", OR(_xlpm.val="partial", _xlpm.val="partial paid"), "Partial", _xlpm.val="", "", TRUE, 'Sales_RAW(BEFORE)'!AY16 ) )} -> Paid | AB16: INV/2025/0011 | AC16: =PROPER('Sales_RAW(BEFORE)'!AA16) -> Web | AD16: =SUBSTITUTE(SUBSTITUTE(SUBSTITUTE(SUBSTITUTE('Sales_RAW(BEFORE)'!AB16,"st",""),"q",""),"Q",""),"uarter","") -> 1 | AE16: =TEXT(IFERROR(DATEVALUE('Sales_RAW(BEFORE)'!AC16 & " 1"), IFERROR(DATE(2025, 'Sales_RAW(BEFORE)'!AC16, 1), 'Sales_RAW(BEFORE)'!AC16)), "mmmm") -> February | AF16: =_xlfn.LET( _xlpm.raw, TRIM(SUBSTITUTE('Sales_RAW(BEFORE)'!AD16, "'", "")), _xlpm.num, IFERROR(VALUE(_xlpm.raw), 0), IF(_xlpm.num < 100, 2000 + _xlpm.num, _xlpm.num) ) -> 2025 | AG16: =PROPER('Sales_RAW(BEFORE)'!AE16) -> Net 60 | AH16: {=_xlfn.LET( _xlpm.val, LOWER(TRIM('Sales_RAW(BEFORE)'!AF16)), _xlfn.IFS( OR(_xlpm.val="", _xlpm.val="null", _xlpm.val="N/A", _xlpm.val="-", _xlpm.val="#N/A"), 0, ISNUMBER('Sales_RAW(BEFORE)'!AF16), 'Sales_RAW(BEFORE)'!AF16, TRUE, IFERROR(_xlfn.NUMBERVALUE(_xlpm.val), 0) ) )} -> 0 | AI16: =IF(IFERROR(VALUE(SUBSTITUTE(SUBSTITUTE(TRIM('Sales_RAW(BEFORE)'!AG16), "%", ""), ",", ".")), 0) > 1, IFERROR(VALUE(SUBSTITUTE(SUBSTITUTE(TRIM('Sales_RAW(BEFORE)'!AG16), "%", ""), ",", ".")), 0) / 100, IFERROR(VALUE(SUBSTITUTE(SUBSTITUTE(TRIM('Sales_RAW(BEFORE)'!AG16), "%", ""), ",", ".")), 0)) -> 0.08 | AJ16: =K16*AI16 -> 325.332 | AK16: =AJ16+K16 -> 4391.982 | AL16: =IFERROR(VALUE(SUBSTITUTE(SUBSTITUTE(SUBSTITUTE('Sales_RAW(BEFORE)'!AJ16,"$",""),"USD",""),",",".")),0) -> 29.63 | AM16: =SUBSTITUTE(SUBSTITUTE(PROPER('Sales_RAW(BEFORE)'!AK16), "Fed Ex", "FedEx"),"Fedex","FedEx") -> Dhl | AN16: 1Z404652501 | AO16: =SUBSTITUTE('Sales_RAW(BEFORE)'!AM16,"kg","") -> 24.48 | AP16: =_xlfn.LET( _xlpm.raw, UPPER(TRIM('Sales_RAW(BEFORE)'!AN16)), _xlpm.clean, RIGHT(_xlpm.raw, 1), IF(OR(_xlpm.raw="", _xlpm.raw="null"), "N/A", _xlpm.clean) ) -> A | AQ16: 480 | AR16: {=_xlfn.LET( _xlpm.raw, LOWER(TRIM('Sales_RAW(BEFORE)'!AP16)), _xlfn.IFS( OR(_xlpm.raw="", _xlpm.raw="null"), "", _xlpm.raw="excellent", 5, _xlpm.raw="good", 4, _xlpm.raw="average", 3, _xlpm.raw="poor", 2, _xlpm.raw="terrible", 1, ISNUMBER(SEARCH("/", _xlpm.raw)), _xlfn.NUMBERVALUE(_xlfn.TEXTBEFORE(_xlpm.raw, "/")), TRUE, IFERROR(_xlfn.NUMBERVALUE(_xlpm.raw), "") ) )} -> 2 | AS16: complaint | AT16: Yes | AU16: Damaged | AV16: =IF(IFERROR(VALUE(SUBSTITUTE(SUBSTITUTE(TRIM('Sales_RAW(BEFORE)'!AT16), "%", ""), ",", ".")), 0) > 1, IFERROR(VALUE(SUBSTITUTE(SUBSTITUTE(TRIM('Sales_RAW(BEFORE)'!AT16), "%", ""), ",", ".")), 0) / 100, IFERROR(VALUE(SUBSTITUTE(SUBSTITUTE(TRIM('Sales_RAW(BEFORE)'!AT16), "%", ""), ",", ".")), 0)) -> 0.25 | AW16: =BA16*(_xlfn.XLOOKUP(N16,Employees!$A$2:$A$26,Employees!$E$2:$E$26,2)) -> 74.663694 | AX16: =PROPER('Sales_RAW(BEFORE)'!AV16) -> Emma Smith | AY16: =AX16 -> Emma Smith | BA16: =AK16*(1-(_xlfn.XLOOKUP(G16, Exchange_Rates!$B$8:$F$8, Exchange_Rates!$B$9:$F$9, 0)+J16)) -> 3733.1847 | BB16: {=_xlfn.LET( _xlpm.raw_dt, SUBSTITUTE(TRIM(C16), ".", "/"), _xlpm.dt, IFERROR(DATEVALUE(_xlpm.raw_dt), C16), _xlpm.p_code, TRIM(E16), _xlpm.w_text, LOWER(_xlfn.XLOOKUP(_xlpm.p_code, Product_List!$B$2:$B$61, Product_List!$F$2:$F$61, "24")), _xlpm.m_count, _xlfn.IFS( ISNUMBER(SEARCH("36", _xlpm.w_text)), 36, ISNUMBER(SEARCH("3 yr", _xlpm.w_text)), 36, ISNUMBER(SEARCH("12", _xlpm.w_text)), 12, ISNUMBER(SEARCH("1 yr", _xlpm.w_text)), 12, TRUE, 24 ), IFERROR(EDATE(_xlpm.dt, _xlpm.m_count), "Empty") )} -> 46800 | BC16: =BA16*AV16 -> 933.29617
A17: TR-2025012 | B17: 45683 | C17: 45686 | D17: ="P-" & TEXT(VALUE(SUBSTITUTE(SUBSTITUTE(SUBSTITUTE(UPPER(TRIM('Sales_RAW(BEFORE)'!D17)), "P", ""), "-", ""), "_", "")),"000") -> P-057 | E17: =VLOOKUP(D17,Product_List!$A$2:$B$61,2,FALSE) -> Keyboard X 57 | F17: =_xlfn.XLOOKUP(E17,Product_List!$B$2:$B$61,Product_List!$E$2:$E$61,2) -> BestParts | G17: =VLOOKUP(E17,Product_List!$B$2:$C$61,2,FALSE) -> Equipment | H17: =SUBSTITUTE(SUBSTITUTE('Sales_RAW(BEFORE)'!G17,"kom",""),".","") -> 14 | I17: =VLOOKUP(E17,Product_List!$B$2:$D$61,3,FALSE) -> 741.71 | J17: =IF(IFERROR(VALUE(SUBSTITUTE(SUBSTITUTE(TRIM('Sales_RAW(BEFORE)'!I17), "%", ""), ",", ".")), 0) > 1, IFERROR(VALUE(SUBSTITUTE(SUBSTITUTE(TRIM('Sales_RAW(BEFORE)'!I17), "%", ""), ",", ".")), 0) / 100, IFERROR(VALUE(SUBSTITUTE(SUBSTITUTE(TRIM('Sales_RAW(BEFORE)'!I17), "%", ""), ",", ".")), 0)) -> 0 | K17: =IFERROR(H17*I17,0) -> 10383.94 | L17: {=_xlfn.LET( _xlpm.valuta, UPPER(TRIM('Sales_RAW(BEFORE)'!K17)), _xlfn.IFS( _xlpm.valuta = "", "", OR(_xlpm.valuta = "USD", _xlpm.valuta = "$"), "$", OR(_xlpm.valuta = "EUR", _xlpm.valuta = "€"), "€", TRUE, _xlpm.valuta ) )} -> $ | M17: ="E" & TEXT(VALUE(SUBSTITUTE(SUBSTITUTE(SUBSTITUTE(UPPER(TRIM('Sales_RAW(BEFORE)'!L17)), "EMP", ""), "E", ""), "-", "")),"000") -> E021 | N17: =_xlfn.XLOOKUP(M17,Employees!$D$2:$D$26,Employees!$A$2:$A$26) -> Chris Williams | O17: =_xlfn.XLOOKUP(N17,Employees!$A$2:$A$26,Employees!$C$2:$C$26,2) -> Sales | P17: =PROPER('Sales_RAW(BEFORE)'!N17) -> West | Q17: =VLOOKUP(N17,Employees!$A$2:$B$26,2,FALSE) -> Boston | R17: =PROPER('Sales_RAW(BEFORE)'!P17) -> Umbrella Ltd. | S17: =SUBSTITUTE(SUBSTITUTE('Sales_RAW(BEFORE)'!Q17,"EIN",""),":","") -> 987473445 | T17: david.company.com | U17: (453) 940-6350 | V17: 265 Johnson St. | W17: 87232 | X17: USA | Y17: =PROPER('Sales_RAW(BEFORE)'!W17) -> Credit Card | Z17: =PROPER('Sales_RAW(BEFORE)'!X17) -> Delivered | AA17: {=_xlfn.LET( _xlpm.val, TRIM(LOWER('Sales_RAW(BEFORE)'!Y17)), _xlfn.IFS( OR(_xlpm.val="yes", _xlpm.val="paid"), "Paid", OR(_xlpm.val="no", _xlpm.val="unpaid"), "Unpaid", OR(_xlpm.val="partial", _xlpm.val="partial paid"), "Partial", _xlpm.val="", "", TRUE, 'Sales_RAW(BEFORE)'!AY17 ) )} -> Unpaid | AB17: INV/2025/0012 | AC17: =PROPER('Sales_RAW(BEFORE)'!AA17) -> Store | AD17: =SUBSTITUTE(SUBSTITUTE(SUBSTITUTE(SUBSTITUTE('Sales_RAW(BEFORE)'!AB17,"st",""),"q",""),"Q",""),"uarter","") -> 2 | AE17: =TEXT(IFERROR(DATEVALUE('Sales_RAW(BEFORE)'!AC17 & " 1"), IFERROR(DATE(2025, 'Sales_RAW(BEFORE)'!AC17, 1), 'Sales_RAW(BEFORE)'!AC17)), "mmmm") -> January | AF17: =_xlfn.LET( _xlpm.raw, TRIM(SUBSTITUTE('Sales_RAW(BEFORE)'!AD17, "'", "")), _xlpm.num, IFERROR(VALUE(_xlpm.raw), 0), IF(_xlpm.num < 100, 2000 + _xlpm.num, _xlpm.num) ) -> 2025 | AG17: =PROPER('Sales_RAW(BEFORE)'!AE17) -> Net 30 | AH17: {=_xlfn.LET( _xlpm.val, LOWER(TRIM('Sales_RAW(BEFORE)'!AF17)), _xlfn.IFS( OR(_xlpm.val="", _xlpm.val="null", _xlpm.val="N/A", _xlpm.val="-", _xlpm.val="#N/A"), 0, ISNUMBER('Sales_RAW(BEFORE)'!AF17), 'Sales_RAW(BEFORE)'!AF17, TRUE, IFERROR(_xlfn.NUMBERVALUE(_xlpm.val), 0) ) )} -> 81 | AI17: =IF(IFERROR(VALUE(SUBSTITUTE(SUBSTITUTE(TRIM('Sales_RAW(BEFORE)'!AG17), "%", ""), ",", ".")), 0) > 1, IFERROR(VALUE(SUBSTITUTE(SUBSTITUTE(TRIM('Sales_RAW(BEFORE)'!AG17), "%", ""), ",", ".")), 0) / 100, IFERROR(VALUE(SUBSTITUTE(SUBSTITUTE(TRIM('Sales_RAW(BEFORE)'!AG17), "%", ""), ",", ".")), 0)) -> 0.08 | AJ17: =K17*AI17 -> 830.7152 | AK17: =AJ17+K17 -> 11214.655 | AL17: =IFERROR(VALUE(SUBSTITUTE(SUBSTITUTE(SUBSTITUTE('Sales_RAW(BEFORE)'!AJ17,"$",""),"USD",""),",",".")),0) -> 10 | AM17: =SUBSTITUTE(SUBSTITUTE(PROPER('Sales_RAW(BEFORE)'!AK17), "Fed Ex", "FedEx"),"Fedex","FedEx") -> FedEx | AN17: FX949334392 | AO17: =SUBSTITUTE('Sales_RAW(BEFORE)'!AM17,"kg","") -> 6.8 | AP17: =_xlfn.LET( _xlpm.raw, UPPER(TRIM('Sales_RAW(BEFORE)'!AN17)), _xlpm.clean, RIGHT(_xlpm.raw, 1), IF(OR(_xlpm.raw="", _xlpm.raw="null"), "N/A", _xlpm.clean) ) -> B | AQ17: 11 | AR17: {=_xlfn.LET( _xlpm.raw, LOWER(TRIM('Sales_RAW(BEFORE)'!AP17)), _xlfn.IFS( OR(_xlpm.raw="", _xlpm.raw="null"), "", _xlpm.raw="excellent", 5, _xlpm.raw="good", 4, _xlpm.raw="average", 3, _xlpm.raw="poor", 2, _xlpm.raw="terrible", 1, ISNUMBER(SEARCH("/", _xlpm.raw)), _xlfn.NUMBERVALUE(_xlfn.TEXTBEFORE(_xlpm.raw, "/")), TRUE, IFERROR(_xlfn.NUMBERVALUE(_xlpm.raw), "") ) )} -> 5 | AV17: =IF(IFERROR(VALUE(SUBSTITUTE(SUBSTITUTE(TRIM('Sales_RAW(BEFORE)'!AT17), "%", ""), ",", ".")), 0) > 1, IFERROR(VALUE(SUBSTITUTE(SUBSTITUTE(TRIM('Sales_RAW(BEFORE)'!AT17), "%", ""), ",", ".")), 0) / 100, IFERROR(VALUE(SUBSTITUTE(SUBSTITUTE(TRIM('Sales_RAW(BEFORE)'!AT17), "%", ""), ",", ".")), 0)) -> 0 | AW17: =BA17*(_xlfn.XLOOKUP(N17,Employees!$A$2:$A$26,Employees!$E$2:$E$26,2)) -> 302.79569 | AX17: =PROPER('Sales_RAW(BEFORE)'!AV17) -> David Jones | AY17: =AX17 -> David Jones | BA17: =AK17*(1-(_xlfn.XLOOKUP(G17, Exchange_Rates!$B$8:$F$8, Exchange_Rates!$B$9:$F$9, 0)+J17)) -> 10093.19 | BB17: {=_xlfn.LET( _xlpm.raw_dt, SUBSTITUTE(TRIM(C17), ".", "/"), _xlpm.dt, IFERROR(DATEVALUE(_xlpm.raw_dt), C17), _xlpm.p_code, TRIM(E17), _xlpm.w_text, LOWER(_xlfn.XLOOKUP(_xlpm.p_code, Product_List!$B$2:$B$61, Product_List!$F$2:$F$61, "24")), _xlpm.m_count, _xlfn.IFS( ISNUMBER(SEARCH("36", _xlpm.w_text)), 36, ISNUMBER(SEARCH("3 yr", _xlpm.w_text)), 36, ISNUMBER(SEARCH("12", _xlpm.w_text)), 12, ISNUMBER(SEARCH("1 yr", _xlpm.w_text)), 12, TRUE, 24 ), IFERROR(EDATE(_xlpm.dt, _xlpm.m_count), "Empty") )} -> 46781 | BC17: =BA17*AV17 -> 0
A18: TR-2025013 | B18: 46122 | C18: =DATE(2026,4,22) -> 46134 | D18: ="P-" & TEXT(VALUE(SUBSTITUTE(SUBSTITUTE(SUBSTITUTE(UPPER(TRIM('Sales_RAW(BEFORE)'!D18)), "P", ""), "-", ""), "_", "")),"000") -> P-042 | E18: =VLOOKUP(D18,Product_List!$A$2:$B$61,2,FALSE) -> Desk Max 42 | F18: =_xlfn.XLOOKUP(E18,Product_List!$B$2:$B$61,Product_List!$E$2:$E$61,2) -> TechSupply Co | G18: =VLOOKUP(E18,Product_List!$B$2:$C$61,2,FALSE) -> Electronics | H18: =SUBSTITUTE(SUBSTITUTE('Sales_RAW(BEFORE)'!G18,"kom",""),".","") -> 21 | I18: =VLOOKUP(E18,Product_List!$B$2:$D$61,3,FALSE) -> 158.06 | J18: =IF(IFERROR(VALUE(SUBSTITUTE(SUBSTITUTE(TRIM('Sales_RAW(BEFORE)'!I18), "%", ""), ",", ".")), 0) > 1, IFERROR(VALUE(SUBSTITUTE(SUBSTITUTE(TRIM('Sales_RAW(BEFORE)'!I18), "%", ""), ",", ".")), 0) / 100, IFERROR(VALUE(SUBSTITUTE(SUBSTITUTE(TRIM('Sales_RAW(BEFORE)'!I18), "%", ""), ",", ".")), 0)) -> 0.1 | K18: =IFERROR(H18*I18,0) -> 3319.26 | L18: {=_xlfn.LET( _xlpm.valuta, UPPER(TRIM('Sales_RAW(BEFORE)'!K18)), _xlfn.IFS( _xlpm.valuta = "", "", OR(_xlpm.valuta = "USD", _xlpm.valuta = "$"), "$", OR(_xlpm.valuta = "EUR", _xlpm.valuta = "€"), "€", TRUE, _xlpm.valuta ) )} -> $ | M18: ="E" & TEXT(VALUE(SUBSTITUTE(SUBSTITUTE(SUBSTITUTE(UPPER(TRIM('Sales_RAW(BEFORE)'!L18)), "EMP", ""), "E", ""), "-", "")),"000") -> E004 | N18: =_xlfn.XLOOKUP(M18,Employees!$D$2:$D$26,Employees!$A$2:$A$26) -> Sophia Johnson | O18: =_xlfn.XLOOKUP(N18,Employees!$A$2:$A$26,Employees!$C$2:$C$26,2) -> Wholesale | P18: =PROPER('Sales_RAW(BEFORE)'!N18) -> North | Q18: =VLOOKUP(N18,Employees!$A$2:$B$26,2,FALSE) -> Houston | R18: =PROPER('Sales_RAW(BEFORE)'!P18) -> Umbrella Inc | S18: =SUBSTITUTE(SUBSTITUTE('Sales_RAW(BEFORE)'!Q18,"EIN",""),":","") -> 896834466 | T18: david.gmail.com | U18: +1 981 325 6824 | V18: 392 Davis Street | W18: 02744 | X18: USA | Y18: =PROPER('Sales_RAW(BEFORE)'!W18) -> Paypal | Z18: =PROPER('Sales_RAW(BEFORE)'!X18) -> Pending | AA18: {=_xlfn.LET( _xlpm.val, TRIM(LOWER('Sales_RAW(BEFORE)'!Y18)), _xlfn.IFS( OR(_xlpm.val="yes", _xlpm.val="paid"), "Paid", OR(_xlpm.val="no", _xlpm.val="unpaid"), "Unpaid", OR(_xlpm.val="partial", _xlpm.val="partial paid"), "Partial", _xlpm.val="", "", TRUE, 'Sales_RAW(BEFORE)'!AY18 ) )} -> Unpaid | AB18: INV/2026/0013 | AC18: =PROPER('Sales_RAW(BEFORE)'!AA18) -> Store | AD18: =SUBSTITUTE(SUBSTITUTE(SUBSTITUTE(SUBSTITUTE('Sales_RAW(BEFORE)'!AB18,"st",""),"q",""),"Q",""),"uarter","") -> 3 | AE18: =TEXT(IFERROR(DATEVALUE('Sales_RAW(BEFORE)'!AC18 & " 1"), IFERROR(DATE(2025, 'Sales_RAW(BEFORE)'!AC18, 1), 'Sales_RAW(BEFORE)'!AC18)), "mmmm") -> April | AF18: =_xlfn.LET( _xlpm.raw, TRIM(SUBSTITUTE('Sales_RAW(BEFORE)'!AD18, "'", "")), _xlpm.num, IFERROR(VALUE(_xlpm.raw), 0), IF(_xlpm.num < 100, 2000 + _xlpm.num, _xlpm.num) ) -> 2026 | AG18: =PROPER('Sales_RAW(BEFORE)'!AE18) -> 15 | AH18: {=_xlfn.LET( _xlpm.val, LOWER(TRIM('Sales_RAW(BEFORE)'!AF18)), _xlfn.IFS( OR(_xlpm.val="", _xlpm.val="null", _xlpm.val="N/A", _xlpm.val="-", _xlpm.val="#N/A"), 0, ISNUMBER('Sales_RAW(BEFORE)'!AF18), 'Sales_RAW(BEFORE)'!AF18, TRUE, IFERROR(_xlfn.NUMBERVALUE(_xlpm.val), 0) ) )} -> 38 | AI18: =IF(IFERROR(VALUE(SUBSTITUTE(SUBSTITUTE(TRIM('Sales_RAW(BEFORE)'!AG18), "%", ""), ",", ".")), 0) > 1, IFERROR(VALUE(SUBSTITUTE(SUBSTITUTE(TRIM('Sales_RAW(BEFORE)'!AG18), "%", ""), ",", ".")), 0) / 100, IFERROR(VALUE(SUBSTITUTE(SUBSTITUTE(TRIM('Sales_RAW(BEFORE)'!AG18), "%", ""), ",", ".")), 0)) -> 0.08 | AJ18: =K18*AI18 -> 265.5408 | AK18: =AJ18+K18 -> 3584.8008 | AL18: =IFERROR(VALUE(SUBSTITUTE(SUBSTITUTE(SUBSTITUTE('Sales_RAW(BEFORE)'!AJ18,"$",""),"USD",""),",",".")),0) -> 50 | AM18: =SUBSTITUTE(SUBSTITUTE(PROPER('Sales_RAW(BEFORE)'!AK18), "Fed Ex", "FedEx"),"Fedex","FedEx") -> FedEx | AN18: 1Z933875961 | AO18: =SUBSTITUTE('Sales_RAW(BEFORE)'!AM18,"kg","") -> 5,88 | AP18: =_xlfn.LET( _xlpm.raw, UPPER(TRIM('Sales_RAW(BEFORE)'!AN18)), _xlpm.clean, RIGHT(_xlpm.raw, 1), IF(OR(_xlpm.raw="", _xlpm.raw="null"), "N/A", _xlpm.clean) ) -> C | AQ18: 369 | AR18: {=_xlfn.LET( _xlpm.raw, LOWER(TRIM('Sales_RAW(BEFORE)'!AP18)), _xlfn.IFS( OR(_xlpm.raw="", _xlpm.raw="null"), "", _xlpm.raw="excellent", 5, _xlpm.raw="good", 4, _xlpm.raw="average", 3, _xlpm.raw="poor", 2, _xlpm.raw="terrible", 1, ISNUMBER(SEARCH("/", _xlpm.raw)), _xlfn.NUMBERVALUE(_xlfn.TEXTBEFORE(_xlpm.raw, "/")), TRUE, IFERROR(_xlfn.NUMBERVALUE(_xlpm.raw), "") ) )} -> 3 | AV18: =IF(IFERROR(VALUE(SUBSTITUTE(SUBSTITUTE(TRIM('Sales_RAW(BEFORE)'!AT18), "%", ""), ",", ".")), 0) > 1, IFERROR(VALUE(SUBSTITUTE(SUBSTITUTE(TRIM('Sales_RAW(BEFORE)'!AT18), "%", ""), ",", ".")), 0) / 100, IFERROR(VALUE(SUBSTITUTE(SUBSTITUTE(TRIM('Sales_RAW(BEFORE)'!AT18), "%", ""), ",", ".")), 0)) -> 0 | AW18: =BA18*(_xlfn.XLOOKUP(N18,Employees!$A$2:$A$26,Employees!$E$2:$E$26,2)) -> 143.39203 | AX18: =PROPER('Sales_RAW(BEFORE)'!AV18) -> David Johnson | AY18: =AX18 -> David Johnson | BA18: =AK18*(1-(_xlfn.XLOOKUP(G18, Exchange_Rates!$B$8:$F$8, Exchange_Rates!$B$9:$F$9, 0)+J18)) -> 2867.8406 | BB18: {=_xlfn.LET( _xlpm.raw_dt, SUBSTITUTE(TRIM(C18), ".", "/"), _xlpm.dt, IFERROR(DATEVALUE(_xlpm.raw_dt), C18), _xlpm.p_code, TRIM(E18), _xlpm.w_text, LOWER(_xlfn.XLOOKUP(_xlpm.p_code, Product_List!$B$2:$B$61, Product_List!$F$2:$F$61, "24")), _xlpm.m_count, _xlfn.IFS( ISNUMBER(SEARCH("36", _xlpm.w_text)), 36, ISNUMBER(SEARCH("3 yr", _xlpm.w_text)), 36, ISNUMBER(SEARCH("12", _xlpm.w_text)), 12, ISNUMBER(SEARCH("1 yr", _xlpm.w_text)), 12, TRUE, 24 ), IFERROR(EDATE(_xlpm.dt, _xlpm.m_count), "Empty") )} -> 47230 | BC18: =BA18*AV18 -> 0
A19: TR-2025014 | B19: 45917 | C19: =DATE(2025,9,21) -> 45921 | D19: ="P-" & TEXT(VALUE(SUBSTITUTE(SUBSTITUTE(SUBSTITUTE(UPPER(TRIM('Sales_RAW(BEFORE)'!D19)), "P", ""), "-", ""), "_", "")),"000") -> P-046 | E19: =VLOOKUP(D19,Product_List!$A$2:$B$61,2,FALSE) -> Chair Basic 46 | F19: =_xlfn.XLOOKUP(E19,Product_List!$B$2:$B$61,Product_List!$E$2:$E$61,2) -> Global Distrib | G19: =VLOOKUP(E19,Product_List!$B$2:$C$61,2,FALSE) -> Equipment | H19: =SUBSTITUTE(SUBSTITUTE('Sales_RAW(BEFORE)'!G19,"kom",""),".","") -> 12 | I19: =VLOOKUP(E19,Product_List!$B$2:$D$61,3,FALSE) -> 549.42 | J19: =IF(IFERROR(VALUE(SUBSTITUTE(SUBSTITUTE(TRIM('Sales_RAW(BEFORE)'!I19), "%", ""), ",", ".")), 0) > 1, IFERROR(VALUE(SUBSTITUTE(SUBSTITUTE(TRIM('Sales_RAW(BEFORE)'!I19), "%", ""), ",", ".")), 0) / 100, IFERROR(VALUE(SUBSTITUTE(SUBSTITUTE(TRIM('Sales_RAW(BEFORE)'!I19), "%", ""), ",", ".")), 0)) -> 0 | K19: =IFERROR(H19*I19,0) -> 6593.04 | L19: {=_xlfn.LET( _xlpm.valuta, UPPER(TRIM('Sales_RAW(BEFORE)'!K19)), _xlfn.IFS( _xlpm.valuta = "", "", OR(_xlpm.valuta = "USD", _xlpm.valuta = "$"), "$", OR(_xlpm.valuta = "EUR", _xlpm.valuta = "€"), "€", TRUE, _xlpm.valuta ) )} -> $ | M19: ="E" & TEXT(VALUE(SUBSTITUTE(SUBSTITUTE(SUBSTITUTE(UPPER(TRIM('Sales_RAW(BEFORE)'!L19)), "EMP", ""), "E", ""), "-", "")),"000") -> E013 | N19: =_xlfn.XLOOKUP(M19,Employees!$D$2:$D$26,Employees!$A$2:$A$26) -> Robert Williams | O19: =_xlfn.XLOOKUP(N19,Employees!$A$2:$A$26,Employees!$C$2:$C$26,2) -> Wholesale | P19: =PROPER('Sales_RAW(BEFORE)'!N19) -> South | Q19: =VLOOKUP(N19,Employees!$A$2:$B$26,2,FALSE) -> Houston | R19: =PROPER('Sales_RAW(BEFORE)'!P19) -> Vortex Inc | S19: =SUBSTITUTE(SUBSTITUTE('Sales_RAW(BEFORE)'!Q19,"EIN",""),":","") -> 280294956 | T19: laura.company.com | U19: 743.280.8185 | V19: 904 Johnson Street | W19: 35667 | X19: USA | Y19: =PROPER('Sales_RAW(BEFORE)'!W19) -> Wire Transfer | Z19: =PROPER('Sales_RAW(BEFORE)'!X19) -> Cancelled | AA19: {=_xlfn.LET( _xlpm.val, TRIM(LOWER('Sales_RAW(BEFORE)'!Y19)), _xlfn.IFS( OR(_xlpm.val="yes", _xlpm.val="paid"), "Paid", OR(_xlpm.val="no", _xlpm.val="unpaid"), "Unpaid", OR(_xlpm.val="partial", _xlpm.val="partial paid"), "Partial", _xlpm.val="", "", TRUE, 'Sales_RAW(BEFORE)'!AY19 ) )} -> Paid | AB19: INV/2025/0014 | AC19: =PROPER('Sales_RAW(BEFORE)'!AA19) -> Online | AD19: =SUBSTITUTE(SUBSTITUTE(SUBSTITUTE(SUBSTITUTE('Sales_RAW(BEFORE)'!AB19,"st",""),"q",""),"Q",""),"uarter","") -> 2 | AE19: =TEXT(IFERROR(DATEVALUE('Sales_RAW(BEFORE)'!AC19 & " 1"), IFERROR(DATE(2025, 'Sales_RAW(BEFORE)'!AC19, 1), 'Sales_RAW(BEFORE)'!AC19)), "mmmm") -> September | AF19: =_xlfn.LET( _xlpm.raw, TRIM(SUBSTITUTE('Sales_RAW(BEFORE)'!AD19, "'", "")), _xlpm.num, IFERROR(VALUE(_xlpm.raw), 0), IF(_xlpm.num < 100, 2000 + _xlpm.num, _xlpm.num) ) -> 2025 | AG19: =PROPER('Sales_RAW(BEFORE)'!AE19) -> Immediate | AH19: {=_xlfn.LET( _xlpm.val, LOWER(TRIM('Sales_RAW(BEFORE)'!AF19)), _xlfn.IFS( OR(_xlpm.val="", _xlpm.val="null", _xlpm.val="N/A", _xlpm.val="-", _xlpm.val="#N/A"), 0, ISNUMBER('Sales_RAW(BEFORE)'!AF19), 'Sales_RAW(BEFORE)'!AF19, TRUE, IFERROR(_xlfn.NUMBERVALUE(_xlpm.val), 0) ) )} -> 31 | AI19: =IF(IFERROR(VALUE(SUBSTITUTE(SUBSTITUTE(TRIM('Sales_RAW(BEFORE)'!AG19), "%", ""), ",", ".")), 0) > 1, IFERROR(VALUE(SUBSTITUTE(SUBSTITUTE(TRIM('Sales_RAW(BEFORE)'!AG19), "%", ""), ",", ".")), 0) / 100, IFERROR(VALUE(SUBSTITUTE(SUBSTITUTE(TRIM('Sales_RAW(BEFORE)'!AG19), "%", ""), ",", ".")), 0)) -> 0.08 | AJ19: =K19*AI19 -> 527.4432 | AK19: =AJ19+K19 -> 7120.4832 | AL19: =IFERROR(VALUE(SUBSTITUTE(SUBSTITUTE(SUBSTITUTE('Sales_RAW(BEFORE)'!AJ19,"$",""),"USD",""),",",".")),0) -> 8.02 | AM19: =SUBSTITUTE(SUBSTITUTE(PROPER('Sales_RAW(BEFORE)'!AK19), "Fed Ex", "FedEx"),"Fedex","FedEx") -> Dhl | AN19: FX814361021 | AO19: =SUBSTITUTE('Sales_RAW(BEFORE)'!AM19,"kg","") -> 12,83 | AP19: =_xlfn.LET( _xlpm.raw, UPPER(TRIM('Sales_RAW(BEFORE)'!AN19)), _xlpm.clean, RIGHT(_xlpm.raw, 1), IF(OR(_xlpm.raw="", _xlpm.raw="null"), "N/A", _xlpm.clean) ) -> A | AQ19: 92 | AR19: {=_xlfn.LET( _xlpm.raw, LOWER(TRIM('Sales_RAW(BEFORE)'!AP19)), _xlfn.IFS( OR(_xlpm.raw="", _xlpm.raw="null"), "", _xlpm.raw="excellent", 5, _xlpm.raw="good", 4, _xlpm.raw="average", 3, _xlpm.raw="poor", 2, _xlpm.raw="terrible", 1, ISNUMBER(SEARCH("/", _xlpm.raw)), _xlfn.NUMBERVALUE(_xlfn.TEXTBEFORE(_xlpm.raw, "/")), TRUE, IFERROR(_xlfn.NUMBERVALUE(_xlpm.raw), "") ) )} -> 1 | AS19: complaint | AT19: Yes | AU19: Wrong item | AV19: =IF(IFERROR(VALUE(SUBSTITUTE(SUBSTITUTE(TRIM('Sales_RAW(BEFORE)'!AT19), "%", ""), ",", ".")), 0) > 1, IFERROR(VALUE(SUBSTITUTE(SUBSTITUTE(TRIM('Sales_RAW(BEFORE)'!AT19), "%", ""), ",", ".")), 0) / 100, IFERROR(VALUE(SUBSTITUTE(SUBSTITUTE(TRIM('Sales_RAW(BEFORE)'!AT19), "%", ""), ",", ".")), 0)) -> 0.3 | AW19: =BA19*(_xlfn.XLOOKUP(N19,Employees!$A$2:$A$26,Employees!$E$2:$E$26,2)) -> 320.42174 | AX19: =PROPER('Sales_RAW(BEFORE)'!AV19) -> Laura Smith | AY19: =AX19 -> Laura Smith | BA19: =AK19*(1-(_xlfn.XLOOKUP(G19, Exchange_Rates!$B$8:$F$8, Exchange_Rates!$B$9:$F$9, 0)+J19)) -> 6408.4349 | BB19: {=_xlfn.LET( _xlpm.raw_dt, SUBSTITUTE(TRIM(C19), ".", "/"), _xlpm.dt, IFERROR(DATEVALUE(_xlpm.raw_dt), C19), _xlpm.p_code, TRIM(E19), _xlpm.w_text, LOWER(_xlfn.XLOOKUP(_xlpm.p_code, Product_List!$B$2:$B$61, Product_List!$F$2:$F$61, "24")), _xlpm.m_count, _xlfn.IFS( ISNUMBER(SEARCH("36", _xlpm.w_text)), 36, ISNUMBER(SEARCH("3 yr", _xlpm.w_text)), 36, ISNUMBER(SEARCH("12", _xlpm.w_text)), 12, ISNUMBER(SEARCH("1 yr", _xlpm.w_text)), 12, TRUE, 24 ), IFERROR(EDATE(_xlpm.dt, _xlpm.m_count), "Empty") )} -> 47017 | BC19: =BA19*AV19 -> 1922.5305
A20: TR-2025015 | B20: 45787 | C20: 45796 | D20: ="P-" & TEXT(VALUE(SUBSTITUTE(SUBSTITUTE(SUBSTITUTE(UPPER(TRIM('Sales_RAW(BEFORE)'!D20)), "P", ""), "-", ""), "_", "")),"000") -> P-046 | E20: =VLOOKUP(D20,Product_List!$A$2:$B$61,2,FALSE) -> Chair Basic 46 | F20: =_xlfn.XLOOKUP(E20,Product_List!$B$2:$B$61,Product_List!$E$2:$E$61,2) -> Global Distrib | G20: =VLOOKUP(E20,Product_List!$B$2:$C$61,2,FALSE) -> Equipment | H20: =SUBSTITUTE(SUBSTITUTE('Sales_RAW(BEFORE)'!G20,"kom",""),".","") -> 7 | I20: =VLOOKUP(E20,Product_List!$B$2:$D$61,3,FALSE) -> 549.42 | J20: =IF(IFERROR(VALUE(SUBSTITUTE(SUBSTITUTE(TRIM('Sales_RAW(BEFORE)'!I20), "%", ""), ",", ".")), 0) > 1, IFERROR(VALUE(SUBSTITUTE(SUBSTITUTE(TRIM('Sales_RAW(BEFORE)'!I20), "%", ""), ",", ".")), 0) / 100, IFERROR(VALUE(SUBSTITUTE(SUBSTITUTE(TRIM('Sales_RAW(BEFORE)'!I20), "%", ""), ",", ".")), 0)) -> 0.05 | K20: =IFERROR(H20*I20,0) -> 3845.94 | L20: {=_xlfn.LET( _xlpm.valuta, UPPER(TRIM('Sales_RAW(BEFORE)'!K20)), _xlfn.IFS( _xlpm.valuta = "", "", OR(_xlpm.valuta = "USD", _xlpm.valuta = "$"), "$", OR(_xlpm.valuta = "EUR", _xlpm.valuta = "€"), "€", TRUE, _xlpm.valuta ) )} -> $ | M20: ="E" & TEXT(VALUE(SUBSTITUTE(SUBSTITUTE(SUBSTITUTE(UPPER(TRIM('Sales_RAW(BEFORE)'!L20)), "EMP", ""), "E", ""), "-", "")),"000") -> E014 | N20: =_xlfn.XLOOKUP(M20,Employees!$D$2:$D$26,Employees!$A$2:$A$26) -> Sophia Brown | O20: =_xlfn.XLOOKUP(N20,Employees!$A$2:$A$26,Employees!$C$2:$C$26,2) -> Online | P20: =PROPER('Sales_RAW(BEFORE)'!N20) -> West | Q20: =VLOOKUP(N20,Employees!$A$2:$B$26,2,FALSE) -> New York | R20: =PROPER('Sales_RAW(BEFORE)'!P20) -> Initech Llc | S20: =SUBSTITUTE(SUBSTITUTE('Sales_RAW(BEFORE)'!Q20,"EIN",""),":","") -> 753571200 | T20: sophia.company.com | U20: 417.240.8501 | V20: 781 Williams Street | W20: 87981 | X20: USA | Y20: =PROPER('Sales_RAW(BEFORE)'!W20) -> Wire Transfer | Z20: =PROPER('Sales_RAW(BEFORE)'!X20) -> Delivered | AA20: {=_xlfn.LET( _xlpm.val, TRIM(LOWER('Sales_RAW(BEFORE)'!Y20)), _xlfn.IFS( OR(_xlpm.val="yes", _xlpm.val="paid"), "Paid", OR(_xlpm.val="no", _xlpm.val="unpaid"), "Unpaid", OR(_xlpm.val="partial", _xlpm.val="partial paid"), "Partial", _xlpm.val="", "", TRUE, 'Sales_RAW(BEFORE)'!AY20 ) )} -> Unpaid | AB20: INV/2025/0015 | AC20: =PROPER('Sales_RAW(BEFORE)'!AA20) -> Online | AD20: =SUBSTITUTE(SUBSTITUTE(SUBSTITUTE(SUBSTITUTE('Sales_RAW(BEFORE)'!AB20,"st",""),"q",""),"Q",""),"uarter","") -> 1 | AE20: =TEXT(IFERROR(DATEVALUE('Sales_RAW(BEFORE)'!AC20 & " 1"), IFERROR(DATE(2025, 'Sales_RAW(BEFORE)'!AC20, 1), 'Sales_RAW(BEFORE)'!AC20)), "mmmm") -> May | AF20: =_xlfn.LET( _xlpm.raw, TRIM(SUBSTITUTE('Sales_RAW(BEFORE)'!AD20, "'", "")), _xlpm.num, IFERROR(VALUE(_xlpm.raw), 0), IF(_xlpm.num < 100, 2000 + _xlpm.num, _xlpm.num) ) -> 2025 | AG20: =PROPER('Sales_RAW(BEFORE)'!AE20) -> Net 60 | AH20: {=_xlfn.LET( _xlpm.val, LOWER(TRIM('Sales_RAW(BEFORE)'!AF20)), _xlfn.IFS( OR(_xlpm.val="", _xlpm.val="null", _xlpm.val="N/A", _xlpm.val="-", _xlpm.val="#N/A"), 0, ISNUMBER('Sales_RAW(BEFORE)'!AF20), 'Sales_RAW(BEFORE)'!AF20, TRUE, IFERROR(_xlfn.NUMBERVALUE(_xlpm.val), 0) ) )} -> 0 | AI20: =IF(IFERROR(VALUE(SUBSTITUTE(SUBSTITUTE(TRIM('Sales_RAW(BEFORE)'!AG20), "%", ""), ",", ".")), 0) > 1, IFERROR(VALUE(SUBSTITUTE(SUBSTITUTE(TRIM('Sales_RAW(BEFORE)'!AG20), "%", ""), ",", ".")), 0) / 100, IFERROR(VALUE(SUBSTITUTE(SUBSTITUTE(TRIM('Sales_RAW(BEFORE)'!AG20), "%", ""), ",", ".")), 0)) -> 0.08 | AJ20: =K20*AI20 -> 307.6752 | AK20: =AJ20+K20 -> 4153.6152 | AL20: =IFERROR(VALUE(SUBSTITUTE(SUBSTITUTE(SUBSTITUTE('Sales_RAW(BEFORE)'!AJ20,"$",""),"USD",""),",",".")),0) -> 1.02 | AM20: =SUBSTITUTE(SUBSTITUTE(PROPER('Sales_RAW(BEFORE)'!AK20), "Fed Ex", "FedEx"),"Fedex","FedEx") -> FedEx | AN20: FX709356414 | AO20: =SUBSTITUTE('Sales_RAW(BEFORE)'!AM20,"kg","") -> 24.8 | AP20: =_xlfn.LET( _xlpm.raw, UPPER(TRIM('Sales_RAW(BEFORE)'!AN20)), _xlpm.clean, RIGHT(_xlpm.raw, 1), IF(OR(_xlpm.raw="", _xlpm.raw="null"), "N/A", _xlpm.clean) ) -> C | AQ20: 356 | AV20: =IF(IFERROR(VALUE(SUBSTITUTE(SUBSTITUTE(TRIM('Sales_RAW(BEFORE)'!AT20), "%", ""), ",", ".")), 0) > 1, IFERROR(VALUE(SUBSTITUTE(SUBSTITUTE(TRIM('Sales_RAW(BEFORE)'!AT20), "%", ""), ",", ".")), 0) / 100, IFERROR(VALUE(SUBSTITUTE(SUBSTITUTE(TRIM('Sales_RAW(BEFORE)'!AT20), "%", ""), ",", ".")), 0)) -> 0.15 | AW20: =BA20*(_xlfn.XLOOKUP(N20,Employees!$A$2:$A$26,Employees!$E$2:$E$26,2)) -> 105.91719 | AX20: =PROPER('Sales_RAW(BEFORE)'!AV20) -> Sophia Miller | AY20: =AX20 -> Sophia Miller | BA20: =AK20*(1-(_xlfn.XLOOKUP(G20, Exchange_Rates!$B$8:$F$8, Exchange_Rates!$B$9:$F$9, 0)+J20)) -> 3530.5729 | BB20: {=_xlfn.LET( _xlpm.raw_dt, SUBSTITUTE(TRIM(C20), ".", "/"), _xlpm.dt, IFERROR(DATEVALUE(_xlpm.raw_dt), C20), _xlpm.p_code, TRIM(E20), _xlpm.w_text, LOWER(_xlfn.XLOOKUP(_xlpm.p_code, Product_List!$B$2:$B$61, Product_List!$F$2:$F$61, "24")), _xlpm.m_count, _xlfn.IFS( ISNUMBER(SEARCH("36", _xlpm.w_text)), 36, ISNUMBER(SEARCH("3 yr", _xlpm.w_text)), 36, ISNUMBER(SEARCH("12", _xlpm.w_text)), 12, ISNUMBER(SEARCH("1 yr", _xlpm.w_text)), 12, TRUE, 24 ), IFERROR(EDATE(_xlpm.dt, _xlpm.m_count), "Empty") )} -> 46892 | BC20: =BA20*AV20 -> 529.58594
A21: TR-2025016 | B21: 45673 | C21: 45687 | D21: ="P-" & TEXT(VALUE(SUBSTITUTE(SUBSTITUTE(SUBSTITUTE(UPPER(TRIM('Sales_RAW(BEFORE)'!D21)), "P", ""), "-", ""), "_", "")),"000") -> P-014 | E21: =VLOOKUP(D21,Product_List!$A$2:$B$61,2,FALSE) -> License Max 14 | F21: =_xlfn.XLOOKUP(E21,Product_List!$B$2:$B$61,Product_List!$E$2:$E$61,2) -> OfficeHub | G21: =VLOOKUP(E21,Product_List!$B$2:$C$61,2,FALSE) -> Software | H21: =SUBSTITUTE(SUBSTITUTE('Sales_RAW(BEFORE)'!G21,"kom",""),".","") -> 1 | I21: =VLOOKUP(E21,Product_List!$B$2:$D$61,3,FALSE) -> 1166.96 | J21: =IF(IFERROR(VALUE(SUBSTITUTE(SUBSTITUTE(TRIM('Sales_RAW(BEFORE)'!I21), "%", ""), ",", ".")), 0) > 1, IFERROR(VALUE(SUBSTITUTE(SUBSTITUTE(TRIM('Sales_RAW(BEFORE)'!I21), "%", ""), ",", ".")), 0) / 100, IFERROR(VALUE(SUBSTITUTE(SUBSTITUTE(TRIM('Sales_RAW(BEFORE)'!I21), "%", ""), ",", ".")), 0)) -> 0.1 | K21: =IFERROR(H21*I21,0) -> 1166.96 | L21: {=_xlfn.LET( _xlpm.valuta, UPPER(TRIM('Sales_RAW(BEFORE)'!K21)), _xlfn.IFS( _xlpm.valuta = "", "", OR(_xlpm.valuta = "USD", _xlpm.valuta = "$"), "$", OR(_xlpm.valuta = "EUR", _xlpm.valuta = "€"), "€", TRUE, _xlpm.valuta ) )} -> $ | M21: ="E" & TEXT(VALUE(SUBSTITUTE(SUBSTITUTE(SUBSTITUTE(UPPER(TRIM('Sales_RAW(BEFORE)'!L21)), "EMP", ""), "E", ""), "-", "")),"000") -> E005 | N21: =_xlfn.XLOOKUP(M21,Employees!$D$2:$D$26,Employees!$A$2:$A$26) -> Laura Williams | O21: =_xlfn.XLOOKUP(N21,Employees!$A$2:$A$26,Employees!$C$2:$C$26,2) -> Online | P21: =PROPER('Sales_RAW(BEFORE)'!N21) -> North | Q21: =VLOOKUP(N21,Employees!$A$2:$B$26,2,FALSE) -> Houston | R21: =PROPER('Sales_RAW(BEFORE)'!P21) -> Vortex Inc. | S21: =SUBSTITUTE(SUBSTITUTE('Sales_RAW(BEFORE)'!Q21,"EIN",""),":","") -> 517630478 | T21: john.yahoo.com | U21: (369) 698-1979 | V21: 990 Johnson Ave | W21: 85526 | X21: USA | Y21: =PROPER('Sales_RAW(BEFORE)'!W21) -> Wire Transfer | Z21: =PROPER('Sales_RAW(BEFORE)'!X21) -> Cancelled | AA21: {=_xlfn.LET( _xlpm.val, TRIM(LOWER('Sales_RAW(BEFORE)'!Y21)), _xlfn.IFS( OR(_xlpm.val="yes", _xlpm.val="paid"), "Paid", OR(_xlpm.val="no", _xlpm.val="unpaid"), "Unpaid", OR(_xlpm.val="partial", _xlpm.val="partial paid"), "Partial", _xlpm.val="", "", TRUE, 'Sales_RAW(BEFORE)'!AY21 ) )} -> Partial | AB21: INV/2025/0016 | AC21: =PROPER('Sales_RAW(BEFORE)'!AA21) -> Store | AD21: =SUBSTITUTE(SUBSTITUTE(SUBSTITUTE(SUBSTITUTE('Sales_RAW(BEFORE)'!AB21,"st",""),"q",""),"Q",""),"uarter","") -> 3 | AE21: =TEXT(IFERROR(DATEVALUE('Sales_RAW(BEFORE)'!AC21 & " 1"), IFERROR(DATE(2025, 'Sales_RAW(BEFORE)'!AC21, 1), 'Sales_RAW(BEFORE)'!AC21)), "mmmm") -> January | AF21: =_xlfn.LET( _xlpm.raw, TRIM(SUBSTITUTE('Sales_RAW(BEFORE)'!AD21, "'", "")), _xlpm.num, IFERROR(VALUE(_xlpm.raw), 0), IF(_xlpm.num < 100, 2000 + _xlpm.num, _xlpm.num) ) -> 2025 | AG21: =PROPER('Sales_RAW(BEFORE)'!AE21) -> Net 60 | AH21: {=_xlfn.LET( _xlpm.val, LOWER(TRIM('Sales_RAW(BEFORE)'!AF21)), _xlfn.IFS( OR(_xlpm.val="", _xlpm.val="null", _xlpm.val="N/A", _xlpm.val="-", _xlpm.val="#N/A"), 0, ISNUMBER('Sales_RAW(BEFORE)'!AF21), 'Sales_RAW(BEFORE)'!AF21, TRUE, IFERROR(_xlfn.NUMBERVALUE(_xlpm.val), 0) ) )} -> 7 | AI21: =IF(IFERROR(VALUE(SUBSTITUTE(SUBSTITUTE(TRIM('Sales_RAW(BEFORE)'!AG21), "%", ""), ",", ".")), 0) > 1, IFERROR(VALUE(SUBSTITUTE(SUBSTITUTE(TRIM('Sales_RAW(BEFORE)'!AG21), "%", ""), ",", ".")), 0) / 100, IFERROR(VALUE(SUBSTITUTE(SUBSTITUTE(TRIM('Sales_RAW(BEFORE)'!AG21), "%", ""), ",", ".")), 0)) -> 0.08 | AJ21: =K21*AI21 -> 93.3568 | AK21: =AJ21+K21 -> 1260.3168 | AL21: =IFERROR(VALUE(SUBSTITUTE(SUBSTITUTE(SUBSTITUTE('Sales_RAW(BEFORE)'!AJ21,"$",""),"USD",""),",",".")),0) -> 43.48 | AM21: =SUBSTITUTE(SUBSTITUTE(PROPER('Sales_RAW(BEFORE)'!AK21), "Fed Ex", "FedEx"),"Fedex","FedEx") -> FedEx | AN21: DH994024254 | AO21: =SUBSTITUTE('Sales_RAW(BEFORE)'!AM21,"kg","") -> 12.9 | AP21: =_xlfn.LET( _xlpm.raw, UPPER(TRIM('Sales_RAW(BEFORE)'!AN21)), _xlpm.clean, RIGHT(_xlpm.raw, 1), IF(OR(_xlpm.raw="", _xlpm.raw="null"), "N/A", _xlpm.clean) ) -> B | AQ21: 350 | AR21: {=_xlfn.LET( _xlpm.raw, LOWER(TRIM('Sales_RAW(BEFORE)'!AP21)), _xlfn.IFS( OR(_xlpm.raw="", _xlpm.raw="null"), "", _xlpm.raw="excellent", 5, _xlpm.raw="good", 4, _xlpm.raw="average", 3, _xlpm.raw="poor", 2, _xlpm.raw="terrible", 1, ISNUMBER(SEARCH("/", _xlpm.raw)), _xlfn.NUMBERVALUE(_xlfn.TEXTBEFORE(_xlpm.raw, "/")), TRUE, IFERROR(_xlfn.NUMBERVALUE(_xlpm.raw), "") ) )} -> 4 | AV21: =IF(IFERROR(VALUE(SUBSTITUTE(SUBSTITUTE(TRIM('Sales_RAW(BEFORE)'!AT21), "%", ""), ",", ".")), 0) > 1, IFERROR(VALUE(SUBSTITUTE(SUBSTITUTE(TRIM('Sales_RAW(BEFORE)'!AT21), "%", ""), ",", ".")), 0) / 100, IFERROR(VALUE(SUBSTITUTE(SUBSTITUTE(TRIM('Sales_RAW(BEFORE)'!AT21), "%", ""), ",", ".")), 0)) -> 0.25 | AW21: =BA21*(_xlfn.XLOOKUP(N21,Employees!$A$2:$A$26,Employees!$E$2:$E$26,2)) -> 28.357128 | AX21: =PROPER('Sales_RAW(BEFORE)'!AV21) -> John Johnson | AY21: =AX21 -> John Johnson | BA21: =AK21*(1-(_xlfn.XLOOKUP(G21, Exchange_Rates!$B$8:$F$8, Exchange_Rates!$B$9:$F$9, 0)+J21)) -> 945.2376 | BB21: {=_xlfn.LET( _xlpm.raw_dt, SUBSTITUTE(TRIM(C21), ".", "/"), _xlpm.dt, IFERROR(DATEVALUE(_xlpm.raw_dt), C21), _xlpm.p_code, TRIM(E21), _xlpm.w_text, LOWER(_xlfn.XLOOKUP(_xlpm.p_code, Product_List!$B$2:$B$61, Product_List!$F$2:$F$61, "24")), _xlpm.m_count, _xlfn.IFS( ISNUMBER(SEARCH("36", _xlpm.w_text)), 36, ISNUMBER(SEARCH("3 yr", _xlpm.w_text)), 36, ISNUMBER(SEARCH("12", _xlpm.w_text)), 12, ISNUMBER(SEARCH("1 yr", _xlpm.w_text)), 12, TRUE, 24 ), IFERROR(EDATE(_xlpm.dt, _xlpm.m_count), "Empty") )} -> 46782 | BC21: =BA21*AV21 -> 236.3094
A22: TR-2025017 | B22: 46273 | C22: 46252 | D22: ="P-" & TEXT(VALUE(SUBSTITUTE(SUBSTITUTE(SUBSTITUTE(UPPER(TRIM('Sales_RAW(BEFORE)'!D22)), "P", ""), "-", ""), "_", "")),"000") -> P-054 | E22: =VLOOKUP(D22,Product_List!$A$2:$B$61,2,FALSE) -> Mouse Basic 54 | F22: =_xlfn.XLOOKUP(E22,Product_List!$B$2:$B$61,Product_List!$E$2:$E$61,2) -> OfficeHub | G22: =VLOOKUP(E22,Product_List!$B$2:$C$61,2,FALSE) -> Office | H22: =SUBSTITUTE(SUBSTITUTE('Sales_RAW(BEFORE)'!G22,"kom",""),".","") -> 18 | I22: =VLOOKUP(E22,Product_List!$B$2:$D$61,3,FALSE) -> 801.23 | J22: =IF(IFERROR(VALUE(SUBSTITUTE(SUBSTITUTE(TRIM('Sales_RAW(BEFORE)'!I22), "%", ""), ",", ".")), 0) > 1, IFERROR(VALUE(SUBSTITUTE(SUBSTITUTE(TRIM('Sales_RAW(BEFORE)'!I22), "%", ""), ",", ".")), 0) / 100, IFERROR(VALUE(SUBSTITUTE(SUBSTITUTE(TRIM('Sales_RAW(BEFORE)'!I22), "%", ""), ",", ".")), 0)) -> 0.05 | K22: =IFERROR(H22*I22,0) -> 14422.14 | L22: {=_xlfn.LET( _xlpm.valuta, UPPER(TRIM('Sales_RAW(BEFORE)'!K22)), _xlfn.IFS( _xlpm.valuta = "", "", OR(_xlpm.valuta = "USD", _xlpm.valuta = "$"), "$", OR(_xlpm.valuta = "EUR", _xlpm.valuta = "€"), "€", TRUE, _xlpm.valuta ) )} -> $ | M22: ="E" & TEXT(VALUE(SUBSTITUTE(SUBSTITUTE(SUBSTITUTE(UPPER(TRIM('Sales_RAW(BEFORE)'!L22)), "EMP", ""), "E", ""), "-", "")),"000") -> E005 | N22: =_xlfn.XLOOKUP(M22,Employees!$D$2:$D$26,Employees!$A$2:$A$26) -> Laura Williams | O22: =_xlfn.XLOOKUP(N22,Employees!$A$2:$A$26,Employees!$C$2:$C$26,2) -> Online | P22: =PROPER('Sales_RAW(BEFORE)'!N22) -> East | Q22: =VLOOKUP(N22,Employees!$A$2:$B$26,2,FALSE) -> Houston | R22: =PROPER('Sales_RAW(BEFORE)'!P22) -> Wayne Llc | S22: =SUBSTITUTE(SUBSTITUTE('Sales_RAW(BEFORE)'!Q22,"EIN",""),":","") -> 852761906 | T22: sophia.yahoo.com | U22: +1 352 452 1730 | V22: 648 Wilson Street | W22: 21467 | X22: USA | Y22: =PROPER('Sales_RAW(BEFORE)'!W22) -> Cash | Z22: =PROPER('Sales_RAW(BEFORE)'!X22) -> Processing | AA22: {=_xlfn.LET( _xlpm.val, TRIM(LOWER('Sales_RAW(BEFORE)'!Y22)), _xlfn.IFS( OR(_xlpm.val="yes", _xlpm.val="paid"), "Paid", OR(_xlpm.val="no", _xlpm.val="unpaid"), "Unpaid", OR(_xlpm.val="partial", _xlpm.val="partial paid"), "Partial", _xlpm.val="", "", TRUE, 'Sales_RAW(BEFORE)'!AY22 ) )} -> Paid | AB22: INV/2026/0017 | AC22: =PROPER('Sales_RAW(BEFORE)'!AA22) -> Online | AD22: =SUBSTITUTE(SUBSTITUTE(SUBSTITUTE(SUBSTITUTE('Sales_RAW(BEFORE)'!AB22,"st",""),"q",""),"Q",""),"uarter","") -> 1 | AE22: =TEXT(IFERROR(DATEVALUE('Sales_RAW(BEFORE)'!AC22 & " 1"), IFERROR(DATE(2025, 'Sales_RAW(BEFORE)'!AC22, 1), 'Sales_RAW(BEFORE)'!AC22)), "mmmm") -> August | AF22: =_xlfn.LET( _xlpm.raw, TRIM(SUBSTITUTE('Sales_RAW(BEFORE)'!AD22, "'", "")), _xlpm.num, IFERROR(VALUE(_xlpm.raw), 0), IF(_xlpm.num < 100, 2000 + _xlpm.num, _xlpm.num) ) -> 2026 | AG22: =PROPER('Sales_RAW(BEFORE)'!AE22) -> 15 | AH22: {=_xlfn.LET( _xlpm.val, LOWER(TRIM('Sales_RAW(BEFORE)'!AF22)), _xlfn.IFS( OR(_xlpm.val="", _xlpm.val="null", _xlpm.val="N/A", _xlpm.val="-", _xlpm.val="#N/A"), 0, ISNUMBER('Sales_RAW(BEFORE)'!AF22), 'Sales_RAW(BEFORE)'!AF22, TRUE, IFERROR(_xlfn.NUMBERVALUE(_xlpm.val), 0) ) )} -> 72 | AI22: =IF(IFERROR(VALUE(SUBSTITUTE(SUBSTITUTE(TRIM('Sales_RAW(BEFORE)'!AG22), "%", ""), ",", ".")), 0) > 1, IFERROR(VALUE(SUBSTITUTE(SUBSTITUTE(TRIM('Sales_RAW(BEFORE)'!AG22), "%", ""), ",", ".")), 0) / 100, IFERROR(VALUE(SUBSTITUTE(SUBSTITUTE(TRIM('Sales_RAW(BEFORE)'!AG22), "%", ""), ",", ".")), 0)) -> 0.08 | AJ22: =K22*AI22 -> 1153.7712 | AK22: =AJ22+K22 -> 15575.911 | AL22: =IFERROR(VALUE(SUBSTITUTE(SUBSTITUTE(SUBSTITUTE('Sales_RAW(BEFORE)'!AJ22,"$",""),"USD",""),",",".")),0) -> 13.08 | AM22: =SUBSTITUTE(SUBSTITUTE(PROPER('Sales_RAW(BEFORE)'!AK22), "Fed Ex", "FedEx"),"Fedex","FedEx") -> FedEx | AN22: FX923827298 | AO22: =SUBSTITUTE('Sales_RAW(BEFORE)'!AM22,"kg","") -> 17.83 | AP22: =_xlfn.LET( _xlpm.raw, UPPER(TRIM('Sales_RAW(BEFORE)'!AN22)), _xlpm.clean, RIGHT(_xlpm.raw, 1), IF(OR(_xlpm.raw="", _xlpm.raw="null"), "N/A", _xlpm.clean) ) -> B | AQ22: 102 | AR22: {=_xlfn.LET( _xlpm.raw, LOWER(TRIM('Sales_RAW(BEFORE)'!AP22)), _xlfn.IFS( OR(_xlpm.raw="", _xlpm.raw="null"), "", _xlpm.raw="excellent", 5, _xlpm.raw="good", 4, _xlpm.raw="average", 3, _xlpm.raw="poor", 2, _xlpm.raw="terrible", 1, ISNUMBER(SEARCH("/", _xlpm.raw)), _xlfn.NUMBERVALUE(_xlfn.TEXTBEFORE(_xlpm.raw, "/")), TRUE, IFERROR(_xlfn.NUMBERVALUE(_xlpm.raw), "") ) )} -> 5 | AV22: =IF(IFERROR(VALUE(SUBSTITUTE(SUBSTITUTE(TRIM('Sales_RAW(BEFORE)'!AT22), "%", ""), ",", ".")), 0) > 1, IFERROR(VALUE(SUBSTITUTE(SUBSTITUTE(TRIM('Sales_RAW(BEFORE)'!AT22), "%", ""), ",", ".")), 0) / 100, IFERROR(VALUE(SUBSTITUTE(SUBSTITUTE(TRIM('Sales_RAW(BEFORE)'!AT22), "%", ""), ",", ".")), 0)) -> 0.25 | AW22: =BA22*(_xlfn.XLOOKUP(N22,Employees!$A$2:$A$26,Employees!$E$2:$E$26,2)) -> 397.18574 | AX22: =PROPER('Sales_RAW(BEFORE)'!AV22) -> Sophia Taylor | AY22: =AX22 -> Sophia Taylor | BA22: =AK22*(1-(_xlfn.XLOOKUP(G22, Exchange_Rates!$B$8:$F$8, Exchange_Rates!$B$9:$F$9, 0)+J22)) -> 13239.525 | BB22: {=_xlfn.LET( _xlpm.raw_dt, SUBSTITUTE(TRIM(C22), ".", "/"), _xlpm.dt, IFERROR(DATEVALUE(_xlpm.raw_dt), C22), _xlpm.p_code, TRIM(E22), _xlpm.w_text, LOWER(_xlfn.XLOOKUP(_xlpm.p_code, Product_List!$B$2:$B$61, Product_List!$F$2:$F$61, "24")), _xlpm.m_count, _xlfn.IFS( ISNUMBER(SEARCH("36", _xlpm.w_text)), 36, ISNUMBER(SEARCH("3 yr", _xlpm.w_text)), 36, ISNUMBER(SEARCH("12", _xlpm.w_text)), 12, ISNUMBER(SEARCH("1 yr", _xlpm.w_text)), 12, TRUE, 24 ), IFERROR(EDATE(_xlpm.dt, _xlpm.m_count), "Empty") )} -> 46983 | BC22: =BA22*AV22 -> 3309.8811
A23: TR-2025018 | B23: =DATE(2025,5,3) -> 45780 | C23: =DATE(2025,5,5) -> 45782 | D23: ="P-" & TEXT(VALUE(SUBSTITUTE(SUBSTITUTE(SUBSTITUTE(UPPER(TRIM('Sales_RAW(BEFORE)'!D23)), "P", ""), "-", ""), "_", "")),"000") -> P-041 | E23: =VLOOKUP(D23,Product_List!$A$2:$B$61,2,FALSE) -> Monitor X 41 | F23: =_xlfn.XLOOKUP(E23,Product_List!$B$2:$B$61,Product_List!$E$2:$E$61,2) -> TechSupply Co | G23: =VLOOKUP(E23,Product_List!$B$2:$C$61,2,FALSE) -> Software | H23: =SUBSTITUTE(SUBSTITUTE('Sales_RAW(BEFORE)'!G23,"kom",""),".","") -> 6 | I23: =VLOOKUP(E23,Product_List!$B$2:$D$61,3,FALSE) -> 247.64 | J23: =IF(IFERROR(VALUE(SUBSTITUTE(SUBSTITUTE(TRIM('Sales_RAW(BEFORE)'!I23), "%", ""), ",", ".")), 0) > 1, IFERROR(VALUE(SUBSTITUTE(SUBSTITUTE(TRIM('Sales_RAW(BEFORE)'!I23), "%", ""), ",", ".")), 0) / 100, IFERROR(VALUE(SUBSTITUTE(SUBSTITUTE(TRIM('Sales_RAW(BEFORE)'!I23), "%", ""), ",", ".")), 0)) -> 0.1 | K23: =IFERROR(H23*I23,0) -> 1485.84 | L23: {=_xlfn.LET( _xlpm.valuta, UPPER(TRIM('Sales_RAW(BEFORE)'!K23)), _xlfn.IFS( _xlpm.valuta = "", "", OR(_xlpm.valuta = "USD", _xlpm.valuta = "$"), "$", OR(_xlpm.valuta = "EUR", _xlpm.valuta = "€"), "€", TRUE, _xlpm.valuta ) )} -> $ | M23: ="E" & TEXT(VALUE(SUBSTITUTE(SUBSTITUTE(SUBSTITUTE(UPPER(TRIM('Sales_RAW(BEFORE)'!L23)), "EMP", ""), "E", ""), "-", "")),"000") -> E013 | N23: =_xlfn.XLOOKUP(M23,Employees!$D$2:$D$26,Employees!$A$2:$A$26) -> Robert Williams | O23: =_xlfn.XLOOKUP(N23,Employees!$A$2:$A$26,Employees!$C$2:$C$26,2) -> Wholesale | P23: =PROPER('Sales_RAW(BEFORE)'!N23) -> East | Q23: =VLOOKUP(N23,Employees!$A$2:$B$26,2,FALSE) -> Houston | R23: =PROPER('Sales_RAW(BEFORE)'!P23) -> Stark Inc | S23: =SUBSTITUTE(SUBSTITUTE('Sales_RAW(BEFORE)'!Q23,"EIN",""),":","") -> 375962955 | T23: david.gmail.com | U23: (588) 372-8231 | V23: 161 Brown Street | W23: 82088 | X23: USA | Y23: =PROPER('Sales_RAW(BEFORE)'!W23) -> Wire Transfer | Z23: =PROPER('Sales_RAW(BEFORE)'!X23) -> Delivered | AA23: {=_xlfn.LET( _xlpm.val, TRIM(LOWER('Sales_RAW(BEFORE)'!Y23)), _xlfn.IFS( OR(_xlpm.val="yes", _xlpm.val="paid"), "Paid", OR(_xlpm.val="no", _xlpm.val="unpaid"), "Unpaid", OR(_xlpm.val="partial", _xlpm.val="partial paid"), "Partial", _xlpm.val="", "", TRUE, 'Sales_RAW(BEFORE)'!AY23 ) )} -> Partial | AB23: INV/2025/0018 | AC23: =PROPER('Sales_RAW(BEFORE)'!AA23) -> Online | AD23: =SUBSTITUTE(SUBSTITUTE(SUBSTITUTE(SUBSTITUTE('Sales_RAW(BEFORE)'!AB23,"st",""),"q",""),"Q",""),"uarter","") -> 4 | AE23: =TEXT(IFERROR(DATEVALUE('Sales_RAW(BEFORE)'!AC23 & " 1"), IFERROR(DATE(2025, 'Sales_RAW(BEFORE)'!AC23, 1), 'Sales_RAW(BEFORE)'!AC23)), "mmmm") -> May | AF23: =_xlfn.LET( _xlpm.raw, TRIM(SUBSTITUTE('Sales_RAW(BEFORE)'!AD23, "'", "")), _xlpm.num, IFERROR(VALUE(_xlpm.raw), 0), IF(_xlpm.num < 100, 2000 + _xlpm.num, _xlpm.num) ) -> 2025 | AG23: =PROPER('Sales_RAW(BEFORE)'!AE23) -> Net 60 | AH23: {=_xlfn.LET( _xlpm.val, LOWER(TRIM('Sales_RAW(BEFORE)'!AF23)), _xlfn.IFS( OR(_xlpm.val="", _xlpm.val="null", _xlpm.val="N/A", _xlpm.val="-", _xlpm.val="#N/A"), 0, ISNUMBER('Sales_RAW(BEFORE)'!AF23), 'Sales_RAW(BEFORE)'!AF23, TRUE, IFERROR(_xlfn.NUMBERVALUE(_xlpm.val), 0) ) )} -> 41 | AI23: =IF(IFERROR(VALUE(SUBSTITUTE(SUBSTITUTE(TRIM('Sales_RAW(BEFORE)'!AG23), "%", ""), ",", ".")), 0) > 1, IFERROR(VALUE(SUBSTITUTE(SUBSTITUTE(TRIM('Sales_RAW(BEFORE)'!AG23), "%", ""), ",", ".")), 0) / 100, IFERROR(VALUE(SUBSTITUTE(SUBSTITUTE(TRIM('Sales_RAW(BEFORE)'!AG23), "%", ""), ",", ".")), 0)) -> 0.08 | AJ23: =K23*AI23 -> 118.8672 | AK23: =AJ23+K23 -> 1604.7072 | AL23: =IFERROR(VALUE(SUBSTITUTE(SUBSTITUTE(SUBSTITUTE('Sales_RAW(BEFORE)'!AJ23,"$",""),"USD",""),",",".")),0) -> 5.78 | AM23: =SUBSTITUTE(SUBSTITUTE(PROPER('Sales_RAW(BEFORE)'!AK23), "Fed Ex", "FedEx"),"Fedex","FedEx") -> FedEx | AN23: DH160909509 | AO23: =SUBSTITUTE('Sales_RAW(BEFORE)'!AM23,"kg","") -> 13.6 | AP23: =_xlfn.LET( _xlpm.raw, UPPER(TRIM('Sales_RAW(BEFORE)'!AN23)), _xlpm.clean, RIGHT(_xlpm.raw, 1), IF(OR(_xlpm.raw="", _xlpm.raw="null"), "N/A", _xlpm.clean) ) -> A | AQ23: 136 | AR23: {=_xlfn.LET( _xlpm.raw, LOWER(TRIM('Sales_RAW(BEFORE)'!AP23)), _xlfn.IFS( OR(_xlpm.raw="", _xlpm.raw="null"), "", _xlpm.raw="excellent", 5, _xlpm.raw="good", 4, _xlpm.raw="average", 3, _xlpm.raw="poor", 2, _xlpm.raw="terrible", 1, ISNUMBER(SEARCH("/", _xlpm.raw)), _xlfn.NUMBERVALUE(_xlfn.TEXTBEFORE(_xlpm.raw, "/")), TRUE, IFERROR(_xlfn.NUMBERVALUE(_xlpm.raw), "") ) )} -> 4 | AV23: =IF(IFERROR(VALUE(SUBSTITUTE(SUBSTITUTE(TRIM('Sales_RAW(BEFORE)'!AT23), "%", ""), ",", ".")), 0) > 1, IFERROR(VALUE(SUBSTITUTE(SUBSTITUTE(TRIM('Sales_RAW(BEFORE)'!AT23), "%", ""), ",", ".")), 0) / 100, IFERROR(VALUE(SUBSTITUTE(SUBSTITUTE(TRIM('Sales_RAW(BEFORE)'!AT23), "%", ""), ",", ".")), 0)) -> 0.15 | AW23: =BA23*(_xlfn.XLOOKUP(N23,Employees!$A$2:$A$26,Employees!$E$2:$E$26,2)) -> 60.17652 | AX23: =PROPER('Sales_RAW(BEFORE)'!AV23) -> David Miller | AY23: =AX23 -> David Miller | BA23: =AK23*(1-(_xlfn.XLOOKUP(G23, Exchange_Rates!$B$8:$F$8, Exchange_Rates!$B$9:$F$9, 0)+J23)) -> 1203.5304 | BB23: {=_xlfn.LET( _xlpm.raw_dt, SUBSTITUTE(TRIM(C23), ".", "/"), _xlpm.dt, IFERROR(DATEVALUE(_xlpm.raw_dt), C23), _xlpm.p_code, TRIM(E23), _xlpm.w_text, LOWER(_xlfn.XLOOKUP(_xlpm.p_code, Product_List!$B$2:$B$61, Product_List!$F$2:$F$61, "24")), _xlpm.m_count, _xlfn.IFS( ISNUMBER(SEARCH("36", _xlpm.w_text)), 36, ISNUMBER(SEARCH("3 yr", _xlpm.w_text)), 36, ISNUMBER(SEARCH("12", _xlpm.w_text)), 12, ISNUMBER(SEARCH("1 yr", _xlpm.w_text)), 12, TRUE, 24 ), IFERROR(EDATE(_xlpm.dt, _xlpm.m_count), "Empty") )} -> 46512 | BC23: =BA23*AV23 -> 180.52956
A24: TR-2025019 | B24: 45874 | C24: 45969 | D24: ="P-" & TEXT(VALUE(SUBSTITUTE(SUBSTITUTE(SUBSTITUTE(UPPER(TRIM('Sales_RAW(BEFORE)'!D24)), "P", ""), "-", ""), "_", "")),"000") -> P-033 | E24: =VLOOKUP(D24,Product_List!$A$2:$B$61,2,FALSE) -> Printer X 33 | F24: =_xlfn.XLOOKUP(E24,Product_List!$B$2:$B$61,Product_List!$E$2:$E$61,2) -> Global Distrib | G24: =VLOOKUP(E24,Product_List!$B$2:$C$61,2,FALSE) -> Office | H24: =SUBSTITUTE(SUBSTITUTE('Sales_RAW(BEFORE)'!G24,"kom",""),".","") -> 31 | I24: =VLOOKUP(E24,Product_List!$B$2:$D$61,3,FALSE) -> 129.06 | J24: =IF(IFERROR(VALUE(SUBSTITUTE(SUBSTITUTE(TRIM('Sales_RAW(BEFORE)'!I24), "%", ""), ",", ".")), 0) > 1, IFERROR(VALUE(SUBSTITUTE(SUBSTITUTE(TRIM('Sales_RAW(BEFORE)'!I24), "%", ""), ",", ".")), 0) / 100, IFERROR(VALUE(SUBSTITUTE(SUBSTITUTE(TRIM('Sales_RAW(BEFORE)'!I24), "%", ""), ",", ".")), 0)) -> 0.1 | K24: =IFERROR(H24*I24,0) -> 4000.86 | L24: {=_xlfn.LET( _xlpm.valuta, UPPER(TRIM('Sales_RAW(BEFORE)'!K24)), _xlfn.IFS( _xlpm.valuta = "", "", OR(_xlpm.valuta = "USD", _xlpm.valuta = "$"), "$", OR(_xlpm.valuta = "EUR", _xlpm.valuta = "€"), "€", TRUE, _xlpm.valuta ) )} -> $ | M24: ="E" & TEXT(VALUE(SUBSTITUTE(SUBSTITUTE(SUBSTITUTE(UPPER(TRIM('Sales_RAW(BEFORE)'!L24)), "EMP", ""), "E", ""), "-", "")),"000") -> E002 | N24: =_xlfn.XLOOKUP(M24,Employees!$D$2:$D$26,Employees!$A$2:$A$26) -> Sarah Wilson | O24: =_xlfn.XLOOKUP(N24,Employees!$A$2:$A$26,Employees!$C$2:$C$26,2) -> Online | P24: =PROPER('Sales_RAW(BEFORE)'!N24) -> South | Q24: =VLOOKUP(N24,Employees!$A$2:$B$26,2,FALSE) -> Los Angeles | R24: =PROPER('Sales_RAW(BEFORE)'!P24) -> Acme Inc | S24: =SUBSTITUTE(SUBSTITUTE('Sales_RAW(BEFORE)'!Q24,"EIN",""),":","") -> 884743535 | T24: sophia.yahoo.com | U24: +1 796 515 4314 | V24: 862 Smith Ave | W24: 44937 | X24: USA | Y24: =PROPER('Sales_RAW(BEFORE)'!W24) -> Credit Card | Z24: =PROPER('Sales_RAW(BEFORE)'!X24) -> Delivered | AA24: {=_xlfn.LET( _xlpm.val, TRIM(LOWER('Sales_RAW(BEFORE)'!Y24)), _xlfn.IFS( OR(_xlpm.val="yes", _xlpm.val="paid"), "Paid", OR(_xlpm.val="no", _xlpm.val="unpaid"), "Unpaid", OR(_xlpm.val="partial", _xlpm.val="partial paid"), "Partial", _xlpm.val="", "", TRUE, 'Sales_RAW(BEFORE)'!AY24 ) )} -> Partial | AB24: INV/2025/0019 | AC24: =PROPER('Sales_RAW(BEFORE)'!AA24) -> Phone | AD24: =SUBSTITUTE(SUBSTITUTE(SUBSTITUTE(SUBSTITUTE('Sales_RAW(BEFORE)'!AB24,"st",""),"q",""),"Q",""),"uarter","") -> 1 | AE24: =TEXT(IFERROR(DATEVALUE('Sales_RAW(BEFORE)'!AC24 & " 1"), IFERROR(DATE(2025, 'Sales_RAW(BEFORE)'!AC24, 1), 'Sales_RAW(BEFORE)'!AC24)), "mmmm") -> August | AF24: =_xlfn.LET( _xlpm.raw, TRIM(SUBSTITUTE('Sales_RAW(BEFORE)'!AD24, "'", "")), _xlpm.num, IFERROR(VALUE(_xlpm.raw), 0), IF(_xlpm.num < 100, 2000 + _xlpm.num, _xlpm.num) ) -> 2025 | AG24: =PROPER('Sales_RAW(BEFORE)'!AE24) -> 15 | AH24: {=_xlfn.LET( _xlpm.val, LOWER(TRIM('Sales_RAW(BEFORE)'!AF24)), _xlfn.IFS( OR(_xlpm.val="", _xlpm.val="null", _xlpm.val="N/A", _xlpm.val="-", _xlpm.val="#N/A"), 0, ISNUMBER('Sales_RAW(BEFORE)'!AF24), 'Sales_RAW(BEFORE)'!AF24, TRUE, IFERROR(_xlfn.NUMBERVALUE(_xlpm.val), 0) ) )} -> 23 | AI24: =IF(IFERROR(VALUE(SUBSTITUTE(SUBSTITUTE(TRIM('Sales_RAW(BEFORE)'!AG24), "%", ""), ",", ".")), 0) > 1, IFERROR(VALUE(SUBSTITUTE(SUBSTITUTE(TRIM('Sales_RAW(BEFORE)'!AG24), "%", ""), ",", ".")), 0) / 100, IFERROR(VALUE(SUBSTITUTE(SUBSTITUTE(TRIM('Sales_RAW(BEFORE)'!AG24), "%", ""), ",", ".")), 0)) -> 0.08 | AJ24: =K24*AI24 -> 320.0688 | AK24: =AJ24+K24 -> 4320.9288 | AL24: =IFERROR(VALUE(SUBSTITUTE(SUBSTITUTE(SUBSTITUTE('Sales_RAW(BEFORE)'!AJ24,"$",""),"USD",""),",",".")),0) -> 1.83 | AM24: =SUBSTITUTE(SUBSTITUTE(PROPER('Sales_RAW(BEFORE)'!AK24), "Fed Ex", "FedEx"),"Fedex","FedEx") -> Dhl | AN24: 1Z482420536 | AO24: =SUBSTITUTE('Sales_RAW(BEFORE)'!AM24,"kg","") -> 15.64 | AP24: =_xlfn.LET( _xlpm.raw, UPPER(TRIM('Sales_RAW(BEFORE)'!AN24)), _xlpm.clean, RIGHT(_xlpm.raw, 1), IF(OR(_xlpm.raw="", _xlpm.raw="null"), "N/A", _xlpm.clean) ) -> B | AQ24: 365 | AR24: {=_xlfn.LET( _xlpm.raw, LOWER(TRIM('Sales_RAW(BEFORE)'!AP24)), _xlfn.IFS( OR(_xlpm.raw="", _xlpm.raw="null"), "", _xlpm.raw="excellent", 5, _xlpm.raw="good", 4, _xlpm.raw="average", 3, _xlpm.raw="poor", 2, _xlpm.raw="terrible", 1, ISNUMBER(SEARCH("/", _xlpm.raw)), _xlfn.NUMBERVALUE(_xlfn.TEXTBEFORE(_xlpm.raw, "/")), TRUE, IFERROR(_xlfn.NUMBERVALUE(_xlpm.raw), "") ) )} -> 5 | AV24: =IF(IFERROR(VALUE(SUBSTITUTE(SUBSTITUTE(TRIM('Sales_RAW(BEFORE)'!AT24), "%", ""), ",", ".")), 0) > 1, IFERROR(VALUE(SUBSTITUTE(SUBSTITUTE(TRIM('Sales_RAW(BEFORE)'!AT24), "%", ""), ",", ".")), 0) / 100, IFERROR(VALUE(SUBSTITUTE(SUBSTITUTE(TRIM('Sales_RAW(BEFORE)'!AT24), "%", ""), ",", ".")), 0)) -> 0.15 | AW24: =BA24*(_xlfn.XLOOKUP(N24,Employees!$A$2:$A$26,Employees!$E$2:$E$26,2)) -> 103.70229 | AX24: =PROPER('Sales_RAW(BEFORE)'!AV24) -> Sophia Jones | AY24: =AX24 -> Sophia Jones | BA24: =AK24*(1-(_xlfn.XLOOKUP(G24, Exchange_Rates!$B$8:$F$8, Exchange_Rates!$B$9:$F$9, 0)+J24)) -> 3456.743 | BB24: {=_xlfn.LET( _xlpm.raw_dt, SUBSTITUTE(TRIM(C24), ".", "/"), _xlpm.dt, IFERROR(DATEVALUE(_xlpm.raw_dt), C24), _xlpm.p_code, TRIM(E24), _xlpm.w_text, LOWER(_xlfn.XLOOKUP(_xlpm.p_code, Product_List!$B$2:$B$61, Product_List!$F$2:$F$61, "24")), _xlpm.m_count, _xlfn.IFS( ISNUMBER(SEARCH("36", _xlpm.w_text)), 36, ISNUMBER(SEARCH("3 yr", _xlpm.w_text)), 36, ISNUMBER(SEARCH("12", _xlpm.w_text)), 12, ISNUMBER(SEARCH("1 yr", _xlpm.w_text)), 12, TRUE, 24 ), IFERROR(EDATE(_xlpm.dt, _xlpm.m_count), "Empty") )} -> 46699 | BC24: =BA24*AV24 -> 518.51146
A25: TR-2025020 | B25: 45795 | C25: 45797 | D25: ="P-" & TEXT(VALUE(SUBSTITUTE(SUBSTITUTE(SUBSTITUTE(UPPER(TRIM('Sales_RAW(BEFORE)'!D26)), "P", ""), "-", ""), "_", "")),"000") -> P-052 | E25: =VLOOKUP(D25,Product_List!$A$2:$B$61,2,FALSE) -> Laptop Max 52 | F25: =_xlfn.XLOOKUP(E25,Product_List!$B$2:$B$61,Product_List!$E$2:$E$61,2) -> TechSupply Co | G25: =VLOOKUP(E25,Product_List!$B$2:$C$61,2,FALSE) -> Furniture | H25: =SUBSTITUTE(SUBSTITUTE('Sales_RAW(BEFORE)'!G26,"kom",""),".","") -> 16 | I25: =VLOOKUP(E25,Product_List!$B$2:$D$61,3,FALSE) -> 1467.86 | J25: =IF(IFERROR(VALUE(SUBSTITUTE(SUBSTITUTE(TRIM('Sales_RAW(BEFORE)'!I26), "%", ""), ",", ".")), 0) > 1, IFERROR(VALUE(SUBSTITUTE(SUBSTITUTE(TRIM('Sales_RAW(BEFORE)'!I26), "%", ""), ",", ".")), 0) / 100, IFERROR(VALUE(SUBSTITUTE(SUBSTITUTE(TRIM('Sales_RAW(BEFORE)'!I26), "%", ""), ",", ".")), 0)) -> 0.1 | K25: =IFERROR(H25*I25,0) -> 23485.76 | L25: {=_xlfn.LET( _xlpm.valuta, UPPER(TRIM('Sales_RAW(BEFORE)'!K26)), _xlfn.IFS( _xlpm.valuta = "", "", OR(_xlpm.valuta = "USD", _xlpm.valuta = "$"), "$", OR(_xlpm.valuta = "EUR", _xlpm.valuta = "€"), "€", TRUE, _xlpm.valuta ) )} -> $ | M25: ="E" & TEXT(VALUE(SUBSTITUTE(SUBSTITUTE(SUBSTITUTE(UPPER(TRIM('Sales_RAW(BEFORE)'!L26)), "EMP", ""), "E", ""), "-", "")),"000") -> E018 | N25: =_xlfn.XLOOKUP(M25,Employees!$D$2:$D$26,Employees!$A$2:$A$26) -> John Miller | O25: =_xlfn.XLOOKUP(N25,Employees!$A$2:$A$26,Employees!$C$2:$C$26,2) -> Retail | P25: =PROPER('Sales_RAW(BEFORE)'!N26) -> South | Q25: =VLOOKUP(N25,Employees!$A$2:$B$26,2,FALSE) -> Houston | R25: =PROPER('Sales_RAW(BEFORE)'!P26) -> Stark Inc | S25: =SUBSTITUTE(SUBSTITUTE('Sales_RAW(BEFORE)'!Q26,"EIN",""),":","") -> 901632584 | T25: emily.gmail.com | U25: +1 910 630 9611 | V25: 347 Davis St. | W25: 44919 | X25: USA | Y25: =PROPER('Sales_RAW(BEFORE)'!W26) -> Cash | Z25: =PROPER('Sales_RAW(BEFORE)'!X26) -> Cancelled | AA25: {=_xlfn.LET( _xlpm.val, TRIM(LOWER('Sales_RAW(BEFORE)'!Y26)), _xlfn.IFS( OR(_xlpm.val="yes", _xlpm.val="paid"), "Paid", OR(_xlpm.val="no", _xlpm.val="unpaid"), "Unpaid", OR(_xlpm.val="partial", _xlpm.val="partial paid"), "Partial", _xlpm.val="", "", TRUE, 'Sales_RAW(BEFORE)'!AY26 ) )} -> Paid | AB25: INV/2025/0020 | AC25: =PROPER('Sales_RAW(BEFORE)'!AA26) -> Online | AD25: =SUBSTITUTE(SUBSTITUTE(SUBSTITUTE(SUBSTITUTE('Sales_RAW(BEFORE)'!AB26,"st",""),"q",""),"Q",""),"uarter","") -> 1 | AE25: =TEXT(IFERROR(DATEVALUE('Sales_RAW(BEFORE)'!AC26 & " 1"), IFERROR(DATE(2025, 'Sales_RAW(BEFORE)'!AC26, 1), 'Sales_RAW(BEFORE)'!AC26)), "mmmm") -> May | AF25: =_xlfn.LET( _xlpm.raw, TRIM(SUBSTITUTE('Sales_RAW(BEFORE)'!AD26, "'", "")), _xlpm.num, IFERROR(VALUE(_xlpm.raw), 0), IF(_xlpm.num < 100, 2000 + _xlpm.num, _xlpm.num) ) -> 2025 | AG25: =PROPER('Sales_RAW(BEFORE)'!AE26) -> Net 60 | AH25: {=_xlfn.LET( _xlpm.val, LOWER(TRIM('Sales_RAW(BEFORE)'!AF26)), _xlfn.IFS( OR(_xlpm.val="", _xlpm.val="null", _xlpm.val="N/A", _xlpm.val="-", _xlpm.val="#N/A"), 0, ISNUMBER('Sales_RAW(BEFORE)'!AF26), 'Sales_RAW(BEFORE)'!AF26, TRUE, IFERROR(_xlfn.NUMBERVALUE(_xlpm.val), 0) ) )} -> 31 | AI25: =IF(IFERROR(VALUE(SUBSTITUTE(SUBSTITUTE(TRIM('Sales_RAW(BEFORE)'!AG26), "%", ""), ",", ".")), 0) > 1, IFERROR(VALUE(SUBSTITUTE(SUBSTITUTE(TRIM('Sales_RAW(BEFORE)'!AG26), "%", ""), ",", ".")), 0) / 100, IFERROR(VALUE(SUBSTITUTE(SUBSTITUTE(TRIM('Sales_RAW(BEFORE)'!AG26), "%", ""), ",", ".")), 0)) -> 0.08 | AJ25: =K25*AI25 -> 1878.8608 | AK25: =AJ25+K25 -> 25364.621 | AL25: =IFERROR(VALUE(SUBSTITUTE(SUBSTITUTE(SUBSTITUTE('Sales_RAW(BEFORE)'!AJ26,"$",""),"USD",""),",",".")),0) -> 18.22 | AM25: =SUBSTITUTE(SUBSTITUTE(PROPER('Sales_RAW(BEFORE)'!AK26), "Fed Ex", "FedEx"),"Fedex","FedEx") -> Ups | AN25: FX315591108 | AO25: =SUBSTITUTE('Sales_RAW(BEFORE)'!AM26,"kg","") -> 0.7 | AP25: =_xlfn.LET( _xlpm.raw, UPPER(TRIM('Sales_RAW(BEFORE)'!AN26)), _xlpm.clean, RIGHT(_xlpm.raw, 1), IF(OR(_xlpm.raw="", _xlpm.raw="null"), "N/A", _xlpm.clean) ) -> B | AR25: {=_xlfn.LET( _xlpm.raw, LOWER(TRIM('Sales_RAW(BEFORE)'!AP26)), _xlfn.IFS( OR(_xlpm.raw="", _xlpm.raw="null"), "", _xlpm.raw="excellent", 5, _xlpm.raw="good", 4, _xlpm.raw="average", 3, _xlpm.raw="poor", 2, _xlpm.raw="terrible", 1, ISNUMBER(SEARCH("/", _xlpm.raw)), _xlfn.NUMBERVALUE(_xlfn.TEXTBEFORE(_xlpm.raw, "/")), TRUE, IFERROR(_xlfn.NUMBERVALUE(_xlpm.raw), "") ) )} -> 1 | AS25: complaint | AT25: Yes | AU25: Doesn't fit | AV25: =IF(IFERROR(VALUE(SUBSTITUTE(SUBSTITUTE(TRIM('Sales_RAW(BEFORE)'!AT26), "%", ""), ",", ".")), 0) > 1, IFERROR(VALUE(SUBSTITUTE(SUBSTITUTE(TRIM('Sales_RAW(BEFORE)'!AT26), "%", ""), ",", ".")), 0) / 100, IFERROR(VALUE(SUBSTITUTE(SUBSTITUTE(TRIM('Sales_RAW(BEFORE)'!AT26), "%", ""), ",", ".")), 0)) -> 0.3 | AW25: =BA25*(_xlfn.XLOOKUP(N25,Employees!$A$2:$A$26,Employees!$E$2:$E$26,2)) -> 405.83393 | AX25: =PROPER('Sales_RAW(BEFORE)'!AV26) -> Emily Brown | AY25: =AX25 -> Emily Brown | BA25: =AK25*(1-(_xlfn.XLOOKUP(G25, Exchange_Rates!$B$8:$F$8, Exchange_Rates!$B$9:$F$9, 0)+J25)) -> 20291.697 | BB25: {=_xlfn.LET( _xlpm.raw_dt, SUBSTITUTE(TRIM(C25), ".", "/"), _xlpm.dt, IFERROR(DATEVALUE(_xlpm.raw_dt), C25), _xlpm.p_code, TRIM(E25), _xlpm.w_text, LOWER(_xlfn.XLOOKUP(_xlpm.p_code, Product_List!$B$2:$B$61, Product_List!$F$2:$F$61, "24")), _xlpm.m_count, _xlfn.IFS( ISNUMBER(SEARCH("36", _xlpm.w_text)), 36, ISNUMBER(SEARCH("3 yr", _xlpm.w_text)), 36, ISNUMBER(SEARCH("12", _xlpm.w_text)), 12, ISNUMBER(SEARCH("1 yr", _xlpm.w_text)), 12, TRUE, 24 ), IFERROR(EDATE(_xlpm.dt, _xlpm.m_count), "Empty") )} -> 46893 | BC25: =BA25*AV25 -> 6087.509
A26: TR-2025021 | B26: =DATE(2026,3,21) -> 46102 | C26: 46105 | D26: ="P-" & TEXT(VALUE(SUBSTITUTE(SUBSTITUTE(SUBSTITUTE(UPPER(TRIM('Sales_RAW(BEFORE)'!D27)), "P", ""), "-", ""), "_", "")),"000") -> P-034 | E26: =VLOOKUP(D26,Product_List!$A$2:$B$61,2,FALSE) -> Mouse X 34 | F26: =_xlfn.XLOOKUP(E26,Product_List!$B$2:$B$61,Product_List!$E$2:$E$61,2) -> Global Distrib | G26: =VLOOKUP(E26,Product_List!$B$2:$C$61,2,FALSE) -> Office | H26: =SUBSTITUTE(SUBSTITUTE('Sales_RAW(BEFORE)'!G27,"kom",""),".","") -> 3 | I26: =VLOOKUP(E26,Product_List!$B$2:$D$61,3,FALSE) -> 23.03 | J26: =IF(IFERROR(VALUE(SUBSTITUTE(SUBSTITUTE(TRIM('Sales_RAW(BEFORE)'!I27), "%", ""), ",", ".")), 0) > 1, IFERROR(VALUE(SUBSTITUTE(SUBSTITUTE(TRIM('Sales_RAW(BEFORE)'!I27), "%", ""), ",", ".")), 0) / 100, IFERROR(VALUE(SUBSTITUTE(SUBSTITUTE(TRIM('Sales_RAW(BEFORE)'!I27), "%", ""), ",", ".")), 0)) -> 0 | K26: =(H26*I26)/(HLOOKUP(AE26,Exchange_Rates!$B$1:$M$2,2,FALSE)) -> 74.290323 | L26: {=_xlfn.LET( _xlpm.valuta, UPPER(TRIM('Sales_RAW(BEFORE)'!K27)), _xlfn.IFS( _xlpm.valuta = "", "", OR(_xlpm.valuta = "USD", _xlpm.valuta = "$"), "$", OR(_xlpm.valuta = "EUR", _xlpm.valuta = "€"), "€", TRUE, _xlpm.valuta ) )} -> € | M26: ="E" & TEXT(VALUE(SUBSTITUTE(SUBSTITUTE(SUBSTITUTE(UPPER(TRIM('Sales_RAW(BEFORE)'!L27)), "EMP", ""), "E", ""), "-", "")),"000") -> E001 | N26: =_xlfn.XLOOKUP(M26,Employees!$D$2:$D$26,Employees!$A$2:$A$26) -> Sarah Wilson | O26: =_xlfn.XLOOKUP(N26,Employees!$A$2:$A$26,Employees!$C$2:$C$26,2) -> Online | P26: =PROPER('Sales_RAW(BEFORE)'!N27) -> East | Q26: =VLOOKUP(N26,Employees!$A$2:$B$26,2,FALSE) -> Los Angeles | R26: =PROPER('Sales_RAW(BEFORE)'!P27) -> Initech Inc | S26: =SUBSTITUTE(SUBSTITUTE('Sales_RAW(BEFORE)'!Q27,"EIN",""),":","") -> 650238460 | T26: david.company.com | U26: (561) 366-4908 | V26: 303 Smith Street | W26: 21783 | X26: USA | Y26: =PROPER('Sales_RAW(BEFORE)'!W27) -> Cash | Z26: =PROPER('Sales_RAW(BEFORE)'!X27) -> Cancelled | AA26: {=_xlfn.LET( _xlpm.val, TRIM(LOWER('Sales_RAW(BEFORE)'!Y27)), _xlfn.IFS( OR(_xlpm.val="yes", _xlpm.val="paid"), "Paid", OR(_xlpm.val="no", _xlpm.val="unpaid"), "Unpaid", OR(_xlpm.val="partial", _xlpm.val="partial paid"), "Partial", _xlpm.val="", "", TRUE, 'Sales_RAW(BEFORE)'!AY27 ) )} -> Unpaid | AB26: INV/2026/0021 | AC26: =PROPER('Sales_RAW(BEFORE)'!AA27) -> Online | AD26: =SUBSTITUTE(SUBSTITUTE(SUBSTITUTE(SUBSTITUTE('Sales_RAW(BEFORE)'!AB27,"st",""),"q",""),"Q",""),"uarter","") -> 3 | AE26: =TEXT(IFERROR(DATEVALUE('Sales_RAW(BEFORE)'!AC27 & " 1"), IFERROR(DATE(2025, 'Sales_RAW(BEFORE)'!AC27, 1), 'Sales_RAW(BEFORE)'!AC27)), "mmmm") -> March | AF26: =_xlfn.LET( _xlpm.raw, TRIM(SUBSTITUTE('Sales_RAW(BEFORE)'!AD27, "'", "")), _xlpm.num, IFERROR(VALUE(_xlpm.raw), 0), IF(_xlpm.num < 100, 2000 + _xlpm.num, _xlpm.num) ) -> 2026 | AG26: =PROPER('Sales_RAW(BEFORE)'!AE27) -> Net 60 | AH26: {=_xlfn.LET( _xlpm.val, LOWER(TRIM('Sales_RAW(BEFORE)'!AF27)), _xlfn.IFS( OR(_xlpm.val="", _xlpm.val="null", _xlpm.val="N/A", _xlpm.val="-", _xlpm.val="#N/A"), 0, ISNUMBER('Sales_RAW(BEFORE)'!AF27), 'Sales_RAW(BEFORE)'!AF27, TRUE, IFERROR(_xlfn.NUMBERVALUE(_xlpm.val), 0) ) )} -> 13 | AI26: =IF(IFERROR(VALUE(SUBSTITUTE(SUBSTITUTE(TRIM('Sales_RAW(BEFORE)'!AG27), "%", ""), ",", ".")), 0) > 1, IFERROR(VALUE(SUBSTITUTE(SUBSTITUTE(TRIM('Sales_RAW(BEFORE)'!AG27), "%", ""), ",", ".")), 0) / 100, IFERROR(VALUE(SUBSTITUTE(SUBSTITUTE(TRIM('Sales_RAW(BEFORE)'!AG27), "%", ""), ",", ".")), 0)) -> 0.08 | AJ26: =K26*AI26 -> 5.9432258 | AK26: =AJ26+K26 -> 80.233548 | AL26: =IFERROR(VALUE(SUBSTITUTE(SUBSTITUTE(SUBSTITUTE('Sales_RAW(BEFORE)'!AJ27,"$",""),"USD",""),",",".")),0) -> 20.84 | AM26: =SUBSTITUTE(SUBSTITUTE(PROPER('Sales_RAW(BEFORE)'!AK27), "Fed Ex", "FedEx"),"Fedex","FedEx") -> Usps | AN26: 1Z761743464 | AO26: =SUBSTITUTE('Sales_RAW(BEFORE)'!AM27,"kg","") -> 18.36 | AP26: =_xlfn.LET( _xlpm.raw, UPPER(TRIM('Sales_RAW(BEFORE)'!AN27)), _xlpm.clean, RIGHT(_xlpm.raw, 1), IF(OR(_xlpm.raw="", _xlpm.raw="null"), "N/A", _xlpm.clean) ) -> B | AQ26: 137 | AR26: {=_xlfn.LET( _xlpm.raw, LOWER(TRIM('Sales_RAW(BEFORE)'!AP27)), _xlfn.IFS( OR(_xlpm.raw="", _xlpm.raw="null"), "", _xlpm.raw="excellent", 5, _xlpm.raw="good", 4, _xlpm.raw="average", 3, _xlpm.raw="poor", 2, _xlpm.raw="terrible", 1, ISNUMBER(SEARCH("/", _xlpm.raw)), _xlfn.NUMBERVALUE(_xlfn.TEXTBEFORE(_xlpm.raw, "/")), TRUE, IFERROR(_xlfn.NUMBERVALUE(_xlpm.raw), "") ) )} -> 3 | AV26: =IF(IFERROR(VALUE(SUBSTITUTE(SUBSTITUTE(TRIM('Sales_RAW(BEFORE)'!AT27), "%", ""), ",", ".")), 0) > 1, IFERROR(VALUE(SUBSTITUTE(SUBSTITUTE(TRIM('Sales_RAW(BEFORE)'!AT27), "%", ""), ",", ".")), 0) / 100, IFERROR(VALUE(SUBSTITUTE(SUBSTITUTE(TRIM('Sales_RAW(BEFORE)'!AT27), "%", ""), ",", ".")), 0)) -> 0.25 | AW26: =BA26*(_xlfn.XLOOKUP(N26,Employees!$A$2:$A$26,Employees!$E$2:$E$26,2)) -> 2.1663058 | AX26: =PROPER('Sales_RAW(BEFORE)'!AV27) -> David Johnson | AY26: =AX26 -> David Johnson | BA26: =AK26*(1-(_xlfn.XLOOKUP(G26, Exchange_Rates!$B$8:$F$8, Exchange_Rates!$B$9:$F$9, 0)+J26)) -> 72.210194 | BB26: {=_xlfn.LET( _xlpm.raw_dt, SUBSTITUTE(TRIM(C26), ".", "/"), _xlpm.dt, IFERROR(DATEVALUE(_xlpm.raw_dt), C26), _xlpm.p_code, TRIM(E26), _xlpm.w_text, LOWER(_xlfn.XLOOKUP(_xlpm.p_code, Product_List!$B$2:$B$61, Product_List!$F$2:$F$61, "24")), _xlpm.m_count, _xlfn.IFS( ISNUMBER(SEARCH("36", _xlpm.w_text)), 36, ISNUMBER(SEARCH("3 yr", _xlpm.w_text)), 36, ISNUMBER(SEARCH("12", _xlpm.w_text)), 12, ISNUMBER(SEARCH("1 yr", _xlpm.w_text)), 12, TRUE, 24 ), IFERROR(EDATE(_xlpm.dt, _xlpm.m_count), "Empty") )} -> 46836 | BC26: =BA26*AV26 -> 18.052548
A27: TR-2025022 | B27: 45771 | C27: 45777 | D27: ="P-" & TEXT(VALUE(SUBSTITUTE(SUBSTITUTE(SUBSTITUTE(UPPER(TRIM('Sales_RAW(BEFORE)'!D28)), "P", ""), "-", ""), "_", "")),"000") -> P-055 | E27: =VLOOKUP(D27,Product_List!$A$2:$B$61,2,FALSE) -> Cable Basic 55 | F27: =_xlfn.XLOOKUP(E27,Product_List!$B$2:$B$61,Product_List!$E$2:$E$61,2) -> BestParts | G27: =VLOOKUP(E27,Product_List!$B$2:$C$61,2,FALSE) -> Office | H27: =SUBSTITUTE(SUBSTITUTE('Sales_RAW(BEFORE)'!G28,"kom",""),".","") -> 29 | I27: =VLOOKUP(E27,Product_List!$B$2:$D$61,3,FALSE) -> 921.78 | J27: =IF(IFERROR(VALUE(SUBSTITUTE(SUBSTITUTE(TRIM('Sales_RAW(BEFORE)'!I28), "%", ""), ",", ".")), 0) > 1, IFERROR(VALUE(SUBSTITUTE(SUBSTITUTE(TRIM('Sales_RAW(BEFORE)'!I28), "%", ""), ",", ".")), 0) / 100, IFERROR(VALUE(SUBSTITUTE(SUBSTITUTE(TRIM('Sales_RAW(BEFORE)'!I28), "%", ""), ",", ".")), 0)) -> 0.1 | K27: =IFERROR(H27*I27,0) -> 26731.62 | L27: {=_xlfn.LET( _xlpm.valuta, UPPER(TRIM('Sales_RAW(BEFORE)'!K28)), _xlfn.IFS( _xlpm.valuta = "", "", OR(_xlpm.valuta = "USD", _xlpm.valuta = "$"), "$", OR(_xlpm.valuta = "EUR", _xlpm.valuta = "€"), "€", TRUE, _xlpm.valuta ) )} -> $ | M27: ="E" & TEXT(VALUE(SUBSTITUTE(SUBSTITUTE(SUBSTITUTE(UPPER(TRIM('Sales_RAW(BEFORE)'!L28)), "EMP", ""), "E", ""), "-", "")),"000") -> E009 | N27: =_xlfn.XLOOKUP(M27,Employees!$D$2:$D$26,Employees!$A$2:$A$26) -> Olivia Wilson | O27: =_xlfn.XLOOKUP(N27,Employees!$A$2:$A$26,Employees!$C$2:$C$26,2) -> Wholesale | P27: =PROPER('Sales_RAW(BEFORE)'!N28) -> North | Q27: =VLOOKUP(N27,Employees!$A$2:$B$26,2,FALSE) -> Miami | R27: =PROPER('Sales_RAW(BEFORE)'!P28) -> Initech Inc | S27: =SUBSTITUTE(SUBSTITUTE('Sales_RAW(BEFORE)'!Q28,"EIN",""),":","") -> 930519543 | T27: emma.company.com | U27: (647) 729-9474 | V27: 609 Miller Blvd | W27: 02360 | X27: USA | Y27: =PROPER('Sales_RAW(BEFORE)'!W28) -> Credit Card | Z27: =PROPER('Sales_RAW(BEFORE)'!X28) -> Delivered | AA27: {=_xlfn.LET( _xlpm.val, TRIM(LOWER('Sales_RAW(BEFORE)'!Y28)), _xlfn.IFS( OR(_xlpm.val="yes", _xlpm.val="paid"), "Paid", OR(_xlpm.val="no", _xlpm.val="unpaid"), "Unpaid", OR(_xlpm.val="partial", _xlpm.val="partial paid"), "Partial", _xlpm.val="", "", TRUE, 'Sales_RAW(BEFORE)'!AY28 ) )} -> Partial | AB27: INV/2025/0022 | AC27: =PROPER('Sales_RAW(BEFORE)'!AA28) -> Store | AD27: =SUBSTITUTE(SUBSTITUTE(SUBSTITUTE(SUBSTITUTE('Sales_RAW(BEFORE)'!AB28,"st",""),"q",""),"Q",""),"uarter","") -> 3 | AE27: =TEXT(IFERROR(DATEVALUE('Sales_RAW(BEFORE)'!AC28 & " 1"), IFERROR(DATE(2025, 'Sales_RAW(BEFORE)'!AC28, 1), 'Sales_RAW(BEFORE)'!AC28)), "mmmm") -> April | AF27: =_xlfn.LET( _xlpm.raw, TRIM(SUBSTITUTE('Sales_RAW(BEFORE)'!AD28, "'", "")), _xlpm.num, IFERROR(VALUE(_xlpm.raw), 0), IF(_xlpm.num < 100, 2000 + _xlpm.num, _xlpm.num) ) -> 2025 | AG27: =PROPER('Sales_RAW(BEFORE)'!AE28) -> 15 | AH27: {=_xlfn.LET( _xlpm.val, LOWER(TRIM('Sales_RAW(BEFORE)'!AF28)), _xlfn.IFS( OR(_xlpm.val="", _xlpm.val="null", _xlpm.val="N/A", _xlpm.val="-", _xlpm.val="#N/A"), 0, ISNUMBER('Sales_RAW(BEFORE)'!AF28), 'Sales_RAW(BEFORE)'!AF28, TRUE, IFERROR(_xlfn.NUMBERVALUE(_xlpm.val), 0) ) )} -> 24 | AI27: =IF(IFERROR(VALUE(SUBSTITUTE(SUBSTITUTE(TRIM('Sales_RAW(BEFORE)'!AG28), "%", ""), ",", ".")), 0) > 1, IFERROR(VALUE(SUBSTITUTE(SUBSTITUTE(TRIM('Sales_RAW(BEFORE)'!AG28), "%", ""), ",", ".")), 0) / 100, IFERROR(VALUE(SUBSTITUTE(SUBSTITUTE(TRIM('Sales_RAW(BEFORE)'!AG28), "%", ""), ",", ".")), 0)) -> 0.08 | AJ27: =K27*AI27 -> 2138.5296 | AK27: =AJ27+K27 -> 28870.15 | AL27: =IFERROR(VALUE(SUBSTITUTE(SUBSTITUTE(SUBSTITUTE('Sales_RAW(BEFORE)'!AJ28,"$",""),"USD",""),",",".")),0) -> 20.08 | AM27: =SUBSTITUTE(SUBSTITUTE(PROPER('Sales_RAW(BEFORE)'!AK28), "Fed Ex", "FedEx"),"Fedex","FedEx") -> Dhl | AN27: FX842576360 | AO27: =SUBSTITUTE('Sales_RAW(BEFORE)'!AM28,"kg","") -> 24.5 | AP27: =_xlfn.LET( _xlpm.raw, UPPER(TRIM('Sales_RAW(BEFORE)'!AN28)), _xlpm.clean, RIGHT(_xlpm.raw, 1), IF(OR(_xlpm.raw="", _xlpm.raw="null"), "N/A", _xlpm.clean) ) -> B | AQ27: 500 | AR27: {=_xlfn.LET( _xlpm.raw, LOWER(TRIM('Sales_RAW(BEFORE)'!AP28)), _xlfn.IFS( OR(_xlpm.raw="", _xlpm.raw="null"), "", _xlpm.raw="excellent", 5, _xlpm.raw="good", 4, _xlpm.raw="average", 3, _xlpm.raw="poor", 2, _xlpm.raw="terrible", 1, ISNUMBER(SEARCH("/", _xlpm.raw)), _xlfn.NUMBERVALUE(_xlfn.TEXTBEFORE(_xlpm.raw, "/")), TRUE, IFERROR(_xlfn.NUMBERVALUE(_xlpm.raw), "") ) )} -> 5 | AV27: =IF(IFERROR(VALUE(SUBSTITUTE(SUBSTITUTE(TRIM('Sales_RAW(BEFORE)'!AT28), "%", ""), ",", ".")), 0) > 1, IFERROR(VALUE(SUBSTITUTE(SUBSTITUTE(TRIM('Sales_RAW(BEFORE)'!AT28), "%", ""), ",", ".")), 0) / 100, IFERROR(VALUE(SUBSTITUTE(SUBSTITUTE(TRIM('Sales_RAW(BEFORE)'!AT28), "%", ""), ",", ".")), 0)) -> 0.3 | AW27: =BA27*(_xlfn.XLOOKUP(N27,Employees!$A$2:$A$26,Employees!$E$2:$E$26,2)) -> 692.88359 | AX27: =PROPER('Sales_RAW(BEFORE)'!AV28) -> Emma Wilson | AY27: =AX27 -> Emma Wilson | BA27: =AK27*(1-(_xlfn.XLOOKUP(G27, Exchange_Rates!$B$8:$F$8, Exchange_Rates!$B$9:$F$9, 0)+J27)) -> 23096.12 | BB27: {=_xlfn.LET( _xlpm.raw_dt, SUBSTITUTE(TRIM(C27), ".", "/"), _xlpm.dt, IFERROR(DATEVALUE(_xlpm.raw_dt), C27), _xlpm.p_code, TRIM(E27), _xlpm.w_text, LOWER(_xlfn.XLOOKUP(_xlpm.p_code, Product_List!$B$2:$B$61, Product_List!$F$2:$F$61, "24")), _xlpm.m_count, _xlfn.IFS( ISNUMBER(SEARCH("36", _xlpm.w_text)), 36, ISNUMBER(SEARCH("3 yr", _xlpm.w_text)), 36, ISNUMBER(SEARCH("12", _xlpm.w_text)), 12, ISNUMBER(SEARCH("1 yr", _xlpm.w_text)), 12, TRUE, 24 ), IFERROR(EDATE(_xlpm.dt, _xlpm.m_count), "Empty") )} -> 46507 | BC27: =BA27*AV27 -> 6928.8359
